Workbook

Sheet Start Here
A1: Seller Profit Sheet
A2: Find out which products actually make you money after every fee, shipping label, return and ad dollar.
A4: SETUP (about 10 minutes, once)
A5: 1. Settings tab: check the fee rates for the platforms you sell on (they are pre-filled with US rates as of Oct 2026, edit if yours differ). Enter your labor rate, monthly overhead and monthly ad spend.
A6: 2. Products tab: one row per product. Name must match the listing title exactly as it appears in your sales export (or fill in SKU, which is matched first).
A7: Enter material, packaging, labor minutes and what you pay for the shipping label. Yellow cells are yours to fill; grey cells calculate themselves.
A9: EACH MONTH (about 2 minutes)
A10: Etsy: Shop Manager > Settings > Options > Download Data > 'Order Items' CSV for the month. Open it, select all, copy, and paste into cell A1 of the 'Etsy Import' tab (replace what was there).
A11: Shopify: Orders > Export > 'Current page' or a date range, 'CSV for Excel'. Paste into cell A1 of the 'Shopify Import' tab.
A12: Amazon, eBay, markets, anything else: type sales into the 'Manual Sales' tab, one row per product sold.
A13: Then open 'Profit by Product'. Products marked LOSING MONEY cost you more than they bring in. 'Price Calculator' tells you what to charge to hit the margin you want.
A15: IF SOMETHING LOOKS WRONG
... A20: Google Sheets: File > Import > Upload this file > 'Replace spreadsheet'. Everything works the same.

Sheet Profit by Product
A1: Profit by Product
A2: For whatever period you pasted in. Sorted the same way as Products.
A4: Gross sales (matched products) | B4: =SUM(C11:C210)
A5: Net profit from products | B5: =SUM(H11:H210)
A6: Monthly overhead | B6: =-Settings!$B$13
A7: Store profit | B7: =B5+B6
A8: Sales not matched to a product | B8: =SUMIFS('Etsy Calc'!$J$2:$J$1501,'Etsy Calc'!$L$2:$L$1501,"⚠ not in Products")+SUMIFS('Shopify Calc'!$J$2:$J$1501,'Shopify Calc'!$L$2:$L$1501,"⚠ not in Products")+SUMIFS('Manual Sales'!$S$2:$S$1501,'Manual Sales'!$U$2:$U$1501,"⚠ not in Products") | C8: =IF(B8>0,"⚠ Some sales have no costs entered, so profit above is overstated. See Start Here.","")
A10: Product | B10: Units sold | C10: Gross sales | D10: Platform fees | E10: Product costs (materials, labor, label) | F10: Return allowance | G10: Ad spend share | H10: Net profit | I10: Profit per unit | J10: Margin | K10: Verdict
A11: =IF(Products!A5="","",Products!A5) | B11: =IF(A11="","",SUMIFS('Etsy Calc'!$D$2:$D$1501,'Etsy Calc'!$L$2:$L$1501,A11)+SUMIFS('Shopify Calc'!$D$2:$D$1501,'Shopify Calc'!$L$2:$L$1501,A11)+SUMIFS('Manual Sales'!$M$2:$M$1501,'Manual Sales'!$U$2:$U$1501,A11)) | C11: =IF(A11="","",SUMIFS('Etsy Calc'!$J$2:$J$1501,'Etsy Calc'!$L$2:$L$1501,A11)+SUMIFS('Shopify Calc'!$J$2:$J$1501,'Shopify Calc'!$L$2:$L$1501,A11)+SUMIFS('Manual Sales'!$S$2:$S$1501,'Manual Sales'!$U$2:$U$1501,A11)) | D11: =IF(A11="","",SUMIFS('Etsy Calc'!$M$2:$M$1501,'Etsy Calc'!$L$2:$L$1501,A11)+SUMIFS('Shopify Calc'!$M$2:$M$1501,'Shopify Calc'!$L$2:$L$1501,A11)+SUMIFS('Manual Sales'!$V$2:$V$1501,'Manual Sales'!$U$2:$U$1501,A11)) | E11: =IF(A11="","",SUMIFS('Etsy Calc'!$N$2:$N$1501,'Etsy Calc'!$L$2:$L$1501,A11)+SUMIFS('Shopify Calc'!$N$2:$N$1501,'Shopify Calc'!$L$2:$L$1501,A11)+SUMIFS('Manual Sales'!$W$2:$W$1501,'Manual Sales'!$U$2:$U$1501,A11)) | F11: =IF(A11="","",SUMIFS('Etsy Calc'!$O$2:$O$1501,'Etsy Calc'!$L$2:$L$1501,A11)+SUMIFS('Shopify Calc'!$O$2:$O$1501,'Shopify Calc'!$L$2:$L$1501,A11)+SUMIFS('Manual Sales'!$X$2:$X$1501,'Manual Sales'!$U$2:$U$1501,A11)) | G11: =IF(A11="","",IF($B$4=0,0,Settings!$B$14*C11/$B$4)) | H11: =IF(A11="","",C11-D11-E11-F11-G11) | I11: =IF(OR(A11="",N(B11)=0),"",H11/B11) | J11: =IF(OR(A11="",N(C11)=0),"",H11/C11) | K11: =IF(A11="","",IF(N(B11)=0,"No sales",IF(H11<0,"LOSING MONEY",IF(J11<0.15,"Thin margin","Healthy"))))
A12: =IF(Products!A6="","",Products!A6) | B12: =IF(A12="","",SUMIFS('Etsy Calc'!$D$2:$D$1501,'Etsy Calc'!$L$2:$L$1501,A12)+SUMIFS('Shopify Calc'!$D$2:$D$1501,'Shopify Calc'!$L$2:$L$1501,A12)+SUMIFS('Manual Sales'!$M$2:$M$1501,'Manual Sales'!$U$2:$U$1501,A12)) | C12: =IF(A12="","",SUMIFS('Etsy Calc'!$J$2:$J$1501,'Etsy Calc'!$L$2:$L$1501,A12)+SUMIFS('Shopify Calc'!$J$2:$J$1501,'Shopify Calc'!$L$2:$L$1501,A12)+SUMIFS('Manual Sales'!$S$2:$S$1501,'Manual Sales'!$U$2:$U$1501,A12)) | D12: =IF(A12="","",SUMIFS('Etsy Calc'!$M$2:$M$1501,'Etsy Calc'!$L$2:$L$1501,A12)+SUMIFS('Shopify Calc'!$M$2:$M$1501,'Shopify Calc'!$L$2:$L$1501,A12)+SUMIFS('Manual Sales'!$V$2:$V$1501,'Manual Sales'!$U$2:$U$1501,A12)) | E12: =IF(A12="","",SUMIFS('Etsy Calc'!$N$2:$N$1501,'Etsy Calc'!$L$2:$L$1501,A12)+SUMIFS('Shopify Calc'!$N$2:$N$1501,'Shopify Calc'!$L$2:$L$1501,A12)+SUMIFS('Manual Sales'!$W$2:$W$1501,'Manual Sales'!$U$2:$U$1501,A12)) | F12: =IF(A12="","",SUMIFS('Etsy Calc'!$O$2:$O$1501,'Etsy Calc'!$L$2:$L$1501,A12)+SUMIFS('Shopify Calc'!$O$2:$O$1501,'Shopify Calc'!$L$2:$L$1501,A12)+SUMIFS('Manual Sales'!$X$2:$X$1501,'Manual Sales'!$U$2:$U$1501,A12)) | G12: =IF(A12="","",IF($B$4=0,0,Settings!$B$14*C12/$B$4)) | H12: =IF(A12="","",C12-D12-E12-F12-G12) | I12: =IF(OR(A12="",N(B12)=0),"",H12/B12) | J12: =IF(OR(A12="",N(C12)=0),"",H12/C12) | K12: =IF(A12="","",IF(N(B12)=0,"No sales",IF(H12<0,"LOSING MONEY",IF(J12<0.15,"Thin margin","Healthy"))))
A13: =IF(Products!A7="","",Products!A7) | B13: =IF(A13="","",SUMIFS('Etsy Calc'!$D$2:$D$1501,'Etsy Calc'!$L$2:$L$1501,A13)+SUMIFS('Shopify Calc'!$D$2:$D$1501,'Shopify Calc'!$L$2:$L$1501,A13)+SUMIFS('Manual Sales'!$M$2:$M$1501,'Manual Sales'!$U$2:$U$1501,A13)) | C13: =IF(A13="","",SUMIFS('Etsy Calc'!$J$2:$J$1501,'Etsy Calc'!$L$2:$L$1501,A13)+SUMIFS('Shopify Calc'!$J$2:$J$1501,'Shopify Calc'!$L$2:$L$1501,A13)+SUMIFS('Manual Sales'!$S$2:$S$1501,'Manual Sales'!$U$2:$U$1501,A13)) | D13: =IF(A13="","",SUMIFS('Etsy Calc'!$M$2:$M$1501,'Etsy Calc'!$L$2:$L$1501,A13)+SUMIFS('Shopify Calc'!$M$2:$M$1501,'Shopify Calc'!$L$2:$L$1501,A13)+SUMIFS('Manual Sales'!$V$2:$V$1501,'Manual Sales'!$U$2:$U$1501,A13)) | E13: =IF(A13="","",SUMIFS('Etsy Calc'!$N$2:$N$1501,'Etsy Calc'!$L$2:$L$1501,A13)+SUMIFS('Shopify Calc'!$N$2:$N$1501,'Shopify Calc'!$L$2:$L$1501,A13)+SUMIFS('Manual Sales'!$W$2:$W$1501,'Manual Sales'!$U$2:$U$1501,A13)) | F13: =IF(A13="","",SUMIFS('Etsy Calc'!$O$2:$O$1501,'Etsy Calc'!$L$2:$L$1501,A13)+SUMIFS('Shopify Calc'!$O$2:$O$1501,'Shopify Calc'!$L$2:$L$1501,A13)+SUMIFS('Manual Sales'!$X$2:$X$1501,'Manual Sales'!$U$2:$U$1501,A13)) | G13: =IF(A13="","",IF($B$4=0,0,Settings!$B$14*C13/$B$4)) | H13: =IF(A13="","",C13-D13-E13-F13-G13) | I13: =IF(OR(A13="",N(B13)=0),"",H13/B13) | J13: =IF(OR(A13="",N(C13)=0),"",H13/C13) | K13: =IF(A13="","",IF(N(B13)=0,"No sales",IF(H13<0,"LOSING MONEY",IF(J13<0.15,"Thin margin","Healthy"))))
A14: =IF(Products!A8="","",Products!A8) | B14: =IF(A14="","",SUMIFS('Etsy Calc'!$D$2:$D$1501,'Etsy Calc'!$L$2:$L$1501,A14)+SUMIFS('Shopify Calc'!$D$2:$D$1501,'Shopify Calc'!$L$2:$L$1501,A14)+SUMIFS('Manual Sales'!$M$2:$M$1501,'Manual Sales'!$U$2:$U$1501,A14)) | C14: =IF(A14="","",SUMIFS('Etsy Calc'!$J$2:$J$1501,'Etsy Calc'!$L$2:$L$1501,A14)+SUMIFS('Shopify Calc'!$J$2:$J$1501,'Shopify Calc'!$L$2:$L$1501,A14)+SUMIFS('Manual Sales'!$S$2:$S$1501,'Manual Sales'!$U$2:$U$1501,A14)) | D14: =IF(A14="","",SUMIFS('Etsy Calc'!$M$2:$M$1501,'Etsy Calc'!$L$2:$L$1501,A14)+SUMIFS('Shopify Calc'!$M$2:$M$1501,'Shopify Calc'!$L$2:$L$1501,A14)+SUMIFS('Manual Sales'!$V$2:$V$1501,'Manual Sales'!$U$2:$U$1501,A14)) | E14: =IF(A14="","",SUMIFS('Etsy Calc'!$N$2:$N$1501,'Etsy Calc'!$L$2:$L$1501,A14)+SUMIFS('Shopify Calc'!$N$2:$N$1501,'Shopify Calc'!$L$2:$L$1501,A14)+SUMIFS('Manual Sales'!$W$2:$W$1501,'Manual Sales'!$U$2:$U$1501,A14)) | F14: =IF(A14="","",SUMIFS('Etsy Calc'!$O$2:$O$1501,'Etsy Calc'!$L$2:$L$1501,A14)+SUMIFS('Shopify Calc'!$O$2:$O$1501,'Shopify Calc'!$L$2:$L$1501,A14)+SUMIFS('Manual Sales'!$X$2:$X$1501,'Manual Sales'!$U$2:$U$1501,A14)) | G14: =IF(A14="","",IF($B$4=0,0,Settings!$B$14*C14/$B$4)) | H14: =IF(A14="","",C14-D14-E14-F14-G14) | I14: =IF(OR(A14="",N(B14)=0),"",H14/B14) | J14: =IF(OR(A14="",N(C14)=0),"",H14/C14) | K14: =IF(A14="","",IF(N(B14)=0,"No sales",IF(H14<0,"LOSING MONEY",IF(J14<0.15,"Thin margin","Healthy"))))
A15: =IF(Products!A9="","",Products!A9) | B15: =IF(A15="","",SUMIFS('Etsy Calc'!$D$2:$D$1501,'Etsy Calc'!$L$2:$L$1501,A15)+SUMIFS('Shopify Calc'!$D$2:$D$1501,'Shopify Calc'!$L$2:$L$1501,A15)+SUMIFS('Manual Sales'!$M$2:$M$1501,'Manual Sales'!$U$2:$U$1501,A15)) | C15: =IF(A15="","",SUMIFS('Etsy Calc'!$J$2:$J$1501,'Etsy Calc'!$L$2:$L$1501,A15)+SUMIFS('Shopify Calc'!$J$2:$J$1501,'Shopify Calc'!$L$2:$L$1501,A15)+SUMIFS('Manual Sales'!$S$2:$S$1501,'Manual Sales'!$U$2:$U$1501,A15)) | D15: =IF(A15="","",SUMIFS('Etsy Calc'!$M$2:$M$1501,'Etsy Calc'!$L$2:$L$1501,A15)+SUMIFS('Shopify Calc'!$M$2:$M$1501,'Shopify Calc'!$L$2:$L$1501,A15)+SUMIFS('Manual Sales'!$V$2:$V$1501,'Manual Sales'!$U$2:$U$1501,A15)) | E15: =IF(A15="","",SUMIFS('Etsy Calc'!$N$2:$N$1501,'Etsy Calc'!$L$2:$L$1501,A15)+SUMIFS('Shopify Calc'!$N$2:$N$1501,'Shopify Calc'!$L$2:$L$1501,A15)+SUMIFS('Manual Sales'!$W$2:$W$1501,'Manual Sales'!$U$2:$U$1501,A15)) | F15: =IF(A15="","",SUMIFS('Etsy Calc'!$O$2:$O$1501,'Etsy Calc'!$L$2:$L$1501,A15)+SUMIFS('Shopify Calc'!$O$2:$O$1501,'Shopify Calc'!$L$2:$L$1501,A15)+SUMIFS('Manual Sales'!$X$2:$X$1501,'Manual Sales'!$U$2:$U$1501,A15)) | G15: =IF(A15="","",IF($B$4=0,0,Settings!$B$14*C15/$B$4)) | H15: =IF(A15="","",C15-D15-E15-F15-G15) | I15: =IF(OR(A15="",N(B15)=0),"",H15/B15) | J15: =IF(OR(A15="",N(C15)=0),"",H15/C15) | K15: =IF(A15="","",IF(N(B15)=0,"No sales",IF(H15<0,"LOSING MONEY",IF(J15<0.15,"Thin margin","Healthy"))))
A16: =IF(Products!A10="","",Products!A10) | B16: =IF(A16="","",SUMIFS('Etsy Calc'!$D$2:$D$1501,'Etsy Calc'!$L$2:$L$1501,A16)+SUMIFS('Shopify Calc'!$D$2:$D$1501,'Shopify Calc'!$L$2:$L$1501,A16)+SUMIFS('Manual Sales'!$M$2:$M$1501,'Manual Sales'!$U$2:$U$1501,A16)) | C16: =IF(A16="","",SUMIFS('Etsy Calc'!$J$2:$J$1501,'Etsy Calc'!$L$2:$L$1501,A16)+SUMIFS('Shopify Calc'!$J$2:$J$1501,'Shopify Calc'!$L$2:$L$1501,A16)+SUMIFS('Manual Sales'!$S$2:$S$1501,'Manual Sales'!$U$2:$U$1501,A16)) | D16: =IF(A16="","",SUMIFS('Etsy Calc'!$M$2:$M$1501,'Etsy Calc'!$L$2:$L$1501,A16)+SUMIFS('Shopify Calc'!$M$2:$M$1501,'Shopify Calc'!$L$2:$L$1501,A16)+SUMIFS('Manual Sales'!$V$2:$V$1501,'Manual Sales'!$U$2:$U$1501,A16)) | E16: =IF(A16="","",SUMIFS('Etsy Calc'!$N$2:$N$1501,'Etsy Calc'!$L$2:$L$1501,A16)+SUMIFS('Shopify Calc'!$N$2:$N$1501,'Shopify Calc'!$L$2:$L$1501,A16)+SUMIFS('Manual Sales'!$W$2:$W$1501,'Manual Sales'!$U$2:$U$1501,A16)) | F16: =IF(A16="","",SUMIFS('Etsy Calc'!$O$2:$O$1501,'Etsy Calc'!$L$2:$L$1501,A16)+SUMIFS('Shopify Calc'!$O$2:$O$1501,'Shopify Calc'!$L$2:$L$1501,A16)+SUMIFS('Manual Sales'!$X$2:$X$1501,'Manual Sales'!$U$2:$U$1501,A16)) | G16: =IF(A16="","",IF($B$4=0,0,Settings!$B$14*C16/$B$4)) | H16: =IF(A16="","",C16-D16-E16-F16-G16) | I16: =IF(OR(A16="",N(B16)=0),"",H16/B16) | J16: =IF(OR(A16="",N(C16)=0),"",H16/C16) | K16: =IF(A16="","",IF(N(B16)=0,"No sales",IF(H16<0,"LOSING MONEY",IF(J16<0.15,"Thin margin","Healthy"))))
A17: =IF(Products!A11="","",Products!A11) | B17: =IF(A17="","",SUMIFS('Etsy Calc'!$D$2:$D$1501,'Etsy Calc'!$L$2:$L$1501,A17)+SUMIFS('Shopify Calc'!$D$2:$D$1501,'Shopify Calc'!$L$2:$L$1501,A17)+SUMIFS('Manual Sales'!$M$2:$M$1501,'Manual Sales'!$U$2:$U$1501,A17)) | C17: =IF(A17="","",SUMIFS('Etsy Calc'!$J$2:$J$1501,'Etsy Calc'!$L$2:$L$1501,A17)+SUMIFS('Shopify Calc'!$J$2:$J$1501,'Shopify Calc'!$L$2:$L$1501,A17)+SUMIFS('Manual Sales'!$S$2:$S$1501,'Manual Sales'!$U$2:$U$1501,A17)) | D17: =IF(A17="","",SUMIFS('Etsy Calc'!$M$2:$M$1501,'Etsy Calc'!$L$2:$L$1501,A17)+SUMIFS('Shopify Calc'!$M$2:$M$1501,'Shopify Calc'!$L$2:$L$1501,A17)+SUMIFS('Manual Sales'!$V$2:$V$1501,'Manual Sales'!$U$2:$U$1501,A17)) | E17: =IF(A17="","",SUMIFS('Etsy Calc'!$N$2:$N$1501,'Etsy Calc'!$L$2:$L$1501,A17)+SUMIFS('Shopify Calc'!$N$2:$N$1501,'Shopify Calc'!$L$2:$L$1501,A17)+SUMIFS('Manual Sales'!$W$2:$W$1501,'Manual Sales'!$U$2:$U$1501,A17)) | F17: =IF(A17="","",SUMIFS('Etsy Calc'!$O$2:$O$1501,'Etsy Calc'!$L$2:$L$1501,A17)+SUMIFS('Shopify Calc'!$O$2:$O$1501,'Shopify Calc'!$L$2:$L$1501,A17)+SUMIFS('Manual Sales'!$X$2:$X$1501,'Manual Sales'!$U$2:$U$1501,A17)) | G17: =IF(A17="","",IF($B$4=0,0,Settings!$B$14*C17/$B$4)) | H17: =IF(A17="","",C17-D17-E17-F17-G17) | I17: =IF(OR(A17="",N(B17)=0),"",H17/B17) | J17: =IF(OR(A17="",N(C17)=0),"",H17/C17) | K17: =IF(A17="","",IF(N(B17)=0,"No sales",IF(H17<0,"LOSING MONEY",IF(J17<0.15,"Thin margin","Healthy"))))
A18: =IF(Products!A12="","",Products!A12) | B18: =IF(A18="","",SUMIFS('Etsy Calc'!$D$2:$D$1501,'Etsy Calc'!$L$2:$L$1501,A18)+SUMIFS('Shopify Calc'!$D$2:$D$1501,'Shopify Calc'!$L$2:$L$1501,A18)+SUMIFS('Manual Sales'!$M$2:$M$1501,'Manual Sales'!$U$2:$U$1501,A18)) | C18: =IF(A18="","",SUMIFS('Etsy Calc'!$J$2:$J$1501,'Etsy Calc'!$L$2:$L$1501,A18)+SUMIFS('Shopify Calc'!$J$2:$J$1501,'Shopify Calc'!$L$2:$L$1501,A18)+SUMIFS('Manual Sales'!$S$2:$S$1501,'Manual Sales'!$U$2:$U$1501,A18)) | D18: =IF(A18="","",SUMIFS('Etsy Calc'!$M$2:$M$1501,'Etsy Calc'!$L$2:$L$1501,A18)+SUMIFS('Shopify Calc'!$M$2:$M$1501,'Shopify Calc'!$L$2:$L$1501,A18)+SUMIFS('Manual Sales'!$V$2:$V$1501,'Manual Sales'!$U$2:$U$1501,A18)) | E18: =IF(A18="","",SUMIFS('Etsy Calc'!$N$2:$N$1501,'Etsy Calc'!$L$2:$L$1501,A18)+SUMIFS('Shopify Calc'!$N$2:$N$1501,'Shopify Calc'!$L$2:$L$1501,A18)+SUMIFS('Manual Sales'!$W$2:$W$1501,'Manual Sales'!$U$2:$U$1501,A18)) | F18: =IF(A18="","",SUMIFS('Etsy Calc'!$O$2:$O$1501,'Etsy Calc'!$L$2:$L$1501,A18)+SUMIFS('Shopify Calc'!$O$2:$O$1501,'Shopify Calc'!$L$2:$L$1501,A18)+SUMIFS('Manual Sales'!$X$2:$X$1501,'Manual Sales'!$U$2:$U$1501,A18)) | G18: =IF(A18="","",IF($B$4=0,0,Settings!$B$14*C18/$B$4)) | H18: =IF(A18="","",C18-D18-E18-F18-G18) | I18: =IF(OR(A18="",N(B18)=0),"",H18/B18) | J18: =IF(OR(A18="",N(C18)=0),"",H18/C18) | K18: =IF(A18="","",IF(N(B18)=0,"No sales",IF(H18<0,"LOSING MONEY",IF(J18<0.15,"Thin margin","Healthy"))))
A19: =IF(Products!A13="","",Products!A13) | B19: =IF(A19="","",SUMIFS('Etsy Calc'!$D$2:$D$1501,'Etsy Calc'!$L$2:$L$1501,A19)+SUMIFS('Shopify Calc'!$D$2:$D$1501,'Shopify Calc'!$L$2:$L$1501,A19)+SUMIFS('Manual Sales'!$M$2:$M$1501,'Manual Sales'!$U$2:$U$1501,A19)) | C19: =IF(A19="","",SUMIFS('Etsy Calc'!$J$2:$J$1501,'Etsy Calc'!$L$2:$L$1501,A19)+SUMIFS('Shopify Calc'!$J$2:$J$1501,'Shopify Calc'!$L$2:$L$1501,A19)+SUMIFS('Manual Sales'!$S$2:$S$1501,'Manual Sales'!$U$2:$U$1501,A19)) | D19: =IF(A19="","",SUMIFS('Etsy Calc'!$M$2:$M$1501,'Etsy Calc'!$L$2:$L$1501,A19)+SUMIFS('Shopify Calc'!$M$2:$M$1501,'Shopify Calc'!$L$2:$L$1501,A19)+SUMIFS('Manual Sales'!$V$2:$V$1501,'Manual Sales'!$U$2:$U$1501,A19)) | E19: =IF(A19="","",SUMIFS('Etsy Calc'!$N$2:$N$1501,'Etsy Calc'!$L$2:$L$1501,A19)+SUMIFS('Shopify Calc'!$N$2:$N$1501,'Shopify Calc'!$L$2:$L$1501,A19)+SUMIFS('Manual Sales'!$W$2:$W$1501,'Manual Sales'!$U$2:$U$1501,A19)) | F19: =IF(A19="","",SUMIFS('Etsy Calc'!$O$2:$O$1501,'Etsy Calc'!$L$2:$L$1501,A19)+SUMIFS('Shopify Calc'!$O$2:$O$1501,'Shopify Calc'!$L$2:$L$1501,A19)+SUMIFS('Manual Sales'!$X$2:$X$1501,'Manual Sales'!$U$2:$U$1501,A19)) | G19: =IF(A19="","",IF($B$4=0,0,Settings!$B$14*C19/$B$4)) | H19: =IF(A19="","",C19-D19-E19-F19-G19) | I19: =IF(OR(A19="",N(B19)=0),"",H19/B19) | J19: =IF(OR(A19="",N(C19)=0),"",H19/C19) | K19: =IF(A19="","",IF(N(B19)=0,"No sales",IF(H19<0,"LOSING MONEY",IF(J19<0.15,"Thin margin","Healthy"))))
A20: =IF(Products!A14="","",Products!A14) | B20: =IF(A20="","",SUMIFS('Etsy Calc'!$D$2:$D$1501,'Etsy Calc'!$L$2:$L$1501,A20)+SUMIFS('Shopify Calc'!$D$2:$D$1501,'Shopify Calc'!$L$2:$L$1501,A20)+SUMIFS('Manual Sales'!$M$2:$M$1501,'Manual Sales'!$U$2:$U$1501,A20)) | C20: =IF(A20="","",SUMIFS('Etsy Calc'!$J$2:$J$1501,'Etsy Calc'!$L$2:$L$1501,A20)+SUMIFS('Shopify Calc'!$J$2:$J$1501,'Shopify Calc'!$L$2:$L$1501,A20)+SUMIFS('Manual Sales'!$S$2:$S$1501,'Manual Sales'!$U$2:$U$1501,A20)) | D20: =IF(A20="","",SUMIFS('Etsy Calc'!$M$2:$M$1501,'Etsy Calc'!$L$2:$L$1501,A20)+SUMIFS('Shopify Calc'!$M$2:$M$1501,'Shopify Calc'!$L$2:$L$1501,A20)+SUMIFS('Manual Sales'!$V$2:$V$1501,'Manual Sales'!$U$2:$U$1501,A20)) | E20: =IF(A20="","",SUMIFS('Etsy Calc'!$N$2:$N$1501,'Etsy Calc'!$L$2:$L$1501,A20)+SUMIFS('Shopify Calc'!$N$2:$N$1501,'Shopify Calc'!$L$2:$L$1501,A20)+SUMIFS('Manual Sales'!$W$2:$W$1501,'Manual Sales'!$U$2:$U$1501,A20)) | F20: =IF(A20="","",SUMIFS('Etsy Calc'!$O$2:$O$1501,'Etsy Calc'!$L$2:$L$1501,A20)+SUMIFS('Shopify Calc'!$O$2:$O$1501,'Shopify Calc'!$L$2:$L$1501,A20)+SUMIFS('Manual Sales'!$X$2:$X$1501,'Manual Sales'!$U$2:$U$1501,A20)) | G20: =IF(A20="","",IF($B$4=0,0,Settings!$B$14*C20/$B$4)) | H20: =IF(A20="","",C20-D20-E20-F20-G20) | I20: =IF(OR(A20="",N(B20)=0),"",H20/B20) | J20: =IF(OR(A20="",N(C20)=0),"",H20/C20) | K20: =IF(A20="","",IF(N(B20)=0,"No sales",IF(H20<0,"LOSING MONEY",IF(J20<0.15,"Thin margin","Healthy"))))
A21: =IF(Products!A15="","",Products!A15) | B21: =IF(A21="","",SUMIFS('Etsy Calc'!$D$2:$D$1501,'Etsy Calc'!$L$2:$L$1501,A21)+SUMIFS('Shopify Calc'!$D$2:$D$1501,'Shopify Calc'!$L$2:$L$1501,A21)+SUMIFS('Manual Sales'!$M$2:$M$1501,'Manual Sales'!$U$2:$U$1501,A21)) | C21: =IF(A21="","",SUMIFS('Etsy Calc'!$J$2:$J$1501,'Etsy Calc'!$L$2:$L$1501,A21)+SUMIFS('Shopify Calc'!$J$2:$J$1501,'Shopify Calc'!$L$2:$L$1501,A21)+SUMIFS('Manual Sales'!$S$2:$S$1501,'Manual Sales'!$U$2:$U$1501,A21)) | D21: =IF(A21="","",SUMIFS('Etsy Calc'!$M$2:$M$1501,'Etsy Calc'!$L$2:$L$1501,A21)+SUMIFS('Shopify Calc'!$M$2:$M$1501,'Shopify Calc'!$L$2:$L$1501,A21)+SUMIFS('Manual Sales'!$V$2:$V$1501,'Manual Sales'!$U$2:$U$1501,A21)) | E21: =IF(A21="","",SUMIFS('Etsy Calc'!$N$2:$N$1501,'Etsy Calc'!$L$2:$L$1501,A21)+SUMIFS('Shopify Calc'!$N$2:$N$1501,'Shopify Calc'!$L$2:$L$1501,A21)+SUMIFS('Manual Sales'!$W$2:$W$1501,'Manual Sales'!$U$2:$U$1501,A21)) | F21: =IF(A21="","",SUMIFS('Etsy Calc'!$O$2:$O$1501,'Etsy Calc'!$L$2:$L$1501,A21)+SUMIFS('Shopify Calc'!$O$2:$O$1501,'Shopify Calc'!$L$2:$L$1501,A21)+SUMIFS('Manual Sales'!$X$2:$X$1501,'Manual Sales'!$U$2:$U$1501,A21)) | G21: =IF(A21="","",IF($B$4=0,0,Settings!$B$14*C21/$B$4)) | H21: =IF(A21="","",C21-D21-E21-F21-G21) | I21: =IF(OR(A21="",N(B21)=0),"",H21/B21) | J21: =IF(OR(A21="",N(C21)=0),"",H21/C21) | K21: =IF(A21="","",IF(N(B21)=0,"No sales",IF(H21<0,"LOSING MONEY",IF(J21<0.15,"Thin margin","Healthy"))))
A22: =IF(Products!A16="","",Products!A16) | B22: =IF(A22="","",SUMIFS('Etsy Calc'!$D$2:$D$1501,'Etsy Calc'!$L$2:$L$1501,A22)+SUMIFS('Shopify Calc'!$D$2:$D$1501,'Shopify Calc'!$L$2:$L$1501,A22)+SUMIFS('Manual Sales'!$M$2:$M$1501,'Manual Sales'!$U$2:$U$1501,A22)) | C22: =IF(A22="","",SUMIFS('Etsy Calc'!$J$2:$J$1501,'Etsy Calc'!$L$2:$L$1501,A22)+SUMIFS('Shopify Calc'!$J$2:$J$1501,'Shopify Calc'!$L$2:$L$1501,A22)+SUMIFS('Manual Sales'!$S$2:$S$1501,'Manual Sales'!$U$2:$U$1501,A22)) | D22: =IF(A22="","",SUMIFS('Etsy Calc'!$M$2:$M$1501,'Etsy Calc'!$L$2:$L$1501,A22)+SUMIFS('Shopify Calc'!$M$2:$M$1501,'Shopify Calc'!$L$2:$L$1501,A22)+SUMIFS('Manual Sales'!$V$2:$V$1501,'Manual Sales'!$U$2:$U$1501,A22)) | E22: =IF(A22="","",SUMIFS('Etsy Calc'!$N$2:$N$1501,'Etsy Calc'!$L$2:$L$1501,A22)+SUMIFS('Shopify Calc'!$N$2:$N$1501,'Shopify Calc'!$L$2:$L$1501,A22)+SUMIFS('Manual Sales'!$W$2:$W$1501,'Manual Sales'!$U$2:$U$1501,A22)) | F22: =IF(A22="","",SUMIFS('Etsy Calc'!$O$2:$O$1501,'Etsy Calc'!$L$2:$L$1501,A22)+SUMIFS('Shopify Calc'!$O$2:$O$1501,'Shopify Calc'!$L$2:$L$1501,A22)+SUMIFS('Manual Sales'!$X$2:$X$1501,'Manual Sales'!$U$2:$U$1501,A22)) | G22: =IF(A22="","",IF($B$4=0,0,Settings!$B$14*C22/$B$4)) | H22: =IF(A22="","",C22-D22-E22-F22-G22) | I22: =IF(OR(A22="",N(B22)=0),"",H22/B22) | J22: =IF(OR(A22="",N(C22)=0),"",H22/C22) | K22: =IF(A22="","",IF(N(B22)=0,"No sales",IF(H22<0,"LOSING MONEY",IF(J22<0.15,"Thin margin","Healthy"))))
... A210: =IF(Products!A204="","",Products!A204) | B210: =IF(A210="","",SUMIFS('Etsy Calc'!$D$2:$D$1501,'Etsy Calc'!$L$2:$L$1501,A210)+SUMIFS('Shopify Calc'!$D$2:$D$1501,'Shopify Calc'!$L$2:$L$1501,A210)+SUMIFS('Manual Sales'!$M$2:$M$1501,'Manual Sales'!$U$2:$U$1501,A210)) | C210: =IF(A210="","",SUMIFS('Etsy Calc'!$J$2:$J$1501,'Etsy Calc'!$L$2:$L$1501,A210)+SUMIFS('Shopify Calc'!$J$2:$J$1501,'Shopify Calc'!$L$2:$L$1501,A210)+SUMIFS('Manual Sales'!$S$2:$S$1501,'Manual Sales'!$U$2:$U$1501,A210)) | D210: =IF(A210="","",SUMIFS('Etsy Calc'!$M$2:$M$1501,'Etsy Calc'!$L$2:$L$1501,A210)+SUMIFS('Shopify Calc'!$M$2:$M$1501,'Shopify Calc'!$L$2:$L$1501,A210)+SUMIFS('Manual Sales'!$V$2:$V$1501,'Manual Sales'!$U$2:$U$1501,A210)) | E210: =IF(A210="","",SUMIFS('Etsy Calc'!$N$2:$N$1501,'Etsy Calc'!$L$2:$L$1501,A210)+SUMIFS('Shopify Calc'!$N$2:$N$1501,'Shopify Calc'!$L$2:$L$1501,A210)+SUMIFS('Manual Sales'!$W$2:$W$1501,'Manual Sales'!$U$2:$U$1501,A210)) | F210: =IF(A210="","",SUMIFS('Etsy Calc'!$O$2:$O$1501,'Etsy Calc'!$L$2:$L$1501,A210)+SUMIFS('Shopify Calc'!$O$2:$O$1501,'Shopify Calc'!$L$2:$L$1501,A210)+SUMIFS('Manual Sales'!$X$2:$X$1501,'Manual Sales'!$U$2:$U$1501,A210)) | G210: =IF(A210="","",IF($B$4=0,0,Settings!$B$14*C210/$B$4)) | H210: =IF(A210="","",C210-D210-E210-F210-G210) | I210: =IF(OR(A210="",N(B210)=0),"",H210/B210) | J210: =IF(OR(A210="",N(C210)=0),"",H210/C210) | K210: =IF(A210="","",IF(N(B210)=0,"No sales",IF(H210<0,"LOSING MONEY",IF(J210<0.15,"Thin margin","Healthy"))))

Sheet Price Calculator
A1: Price Calculator
A2: Price = (cost + fixed fees) / (1 - fee % - return rate - target margin). Fees are a % of the sale price, not of your cost, which is why 'cost x 2' often loses money.
A4: Product | B4: Platform | C4: Total cost per unit | D4: Target margin | E4: Your current price | F4: Price to hit target | G4: Profit per unit at current price | H4: Margin at current price | I4: Check
A5: =IF(Products!A5="","",Products!A5) | B5: Etsy | C5: =IF(A5="","",Products!I5) | D5: 0.3 | E5: 18 | F5: =IF(A5="","",IF(1-(IFERROR(INDEX(Settings!$B$5:$B$9,MATCH(B5,Settings!$A$5:$A$9,0)),0)+IFERROR(INDEX(Settings!$E$5:$E$9,MATCH(B5,Settings!$A$5:$A$9,0)),0)+IFERROR(INDEX(Settings!$G$5:$G$9,MATCH(B5,Settings!$A$5:$A$9,0)),0)+N(Products!H5))-D5<=0,"margin too high",(C5+(IFERROR(INDEX(Settings!$C$5:$C$9,MATCH(B5,Settings!$A$5:$A$9,0)),0)+IFERROR(INDEX(Settings!$D$5:$D$9,MATCH(B5,Settings!$A$5:$A$9,0)),0)+IFERROR(INDEX(Settings!$F$5:$F$9,MATCH(B5,Settings!$A$5:$A$9,0)),0)))/(1-(IFERROR(INDEX(Settings!$B$5:$B$9,MATCH(B5,Settings!$A$5:$A$9,0)),0)+IFERROR(INDEX(Settings!$E$5:$E$9,MATCH(B5,Settings!$A$5:$A$9,0)),0)+IFERROR(INDEX(Settings!$G$5:$G$9,MATCH(B5,Settings!$A$5:$A$9,0)),0)+N(Products!H5))-D5))) | G5: =IF(OR(A5="",N(E5)=0),"",E5*(1-(IFERROR(INDEX(Settings!$B$5:$B$9,MATCH(B5,Settings!$A$5:$A$9,0)),0)+IFERROR(INDEX(Settings!$E$5:$E$9,MATCH(B5,Settings!$A$5:$A$9,0)),0)+IFERROR(INDEX(Settings!$G$5:$G$9,MATCH(B5,Settings!$A$5:$A$9,0)),0)+N(Products!H5)))-(IFERROR(INDEX(Settings!$C$5:$C$9,MATCH(B5,Settings!$A$5:$A$9,0)),0)+IFERROR(INDEX(Settings!$D$5:$D$9,MATCH(B5,Settings!$A$5:$A$9,0)),0)+IFERROR(INDEX(Settings!$F$5:$F$9,MATCH(B5,Settings!$A$5:$A$9,0)),0))-C5) | H5: =IF(OR(A5="",N(E5)=0),"",G5/E5) | I5: =IF(OR(A5="",N(E5)=0),"",IF(G5<0,"Loses money at this price",IF(E5<F5,"Below target: raise to "&TEXT(F5,"$0.00"),"On target")))
A6: =IF(Products!A6="","",Products!A6) | B6: Etsy | C6: =IF(A6="","",Products!I6) | D6: 0.3 | E6: 28 | F6: =IF(A6="","",IF(1-(IFERROR(INDEX(Settings!$B$5:$B$9,MATCH(B6,Settings!$A$5:$A$9,0)),0)+IFERROR(INDEX(Settings!$E$5:$E$9,MATCH(B6,Settings!$A$5:$A$9,0)),0)+IFERROR(INDEX(Settings!$G$5:$G$9,MATCH(B6,Settings!$A$5:$A$9,0)),0)+N(Products!H6))-D6<=0,"margin too high",(C6+(IFERROR(INDEX(Settings!$C$5:$C$9,MATCH(B6,Settings!$A$5:$A$9,0)),0)+IFERROR(INDEX(Settings!$D$5:$D$9,MATCH(B6,Settings!$A$5:$A$9,0)),0)+IFERROR(INDEX(Settings!$F$5:$F$9,MATCH(B6,Settings!$A$5:$A$9,0)),0)))/(1-(IFERROR(INDEX(Settings!$B$5:$B$9,MATCH(B6,Settings!$A$5:$A$9,0)),0)+IFERROR(INDEX(Settings!$E$5:$E$9,MATCH(B6,Settings!$A$5:$A$9,0)),0)+IFERROR(INDEX(Settings!$G$5:$G$9,MATCH(B6,Settings!$A$5:$A$9,0)),0)+N(Products!H6))-D6))) | G6: =IF(OR(A6="",N(E6)=0),"",E6*(1-(IFERROR(INDEX(Settings!$B$5:$B$9,MATCH(B6,Settings!$A$5:$A$9,0)),0)+IFERROR(INDEX(Settings!$E$5:$E$9,MATCH(B6,Settings!$A$5:$A$9,0)),0)+IFERROR(INDEX(Settings!$G$5:$G$9,MATCH(B6,Settings!$A$5:$A$9,0)),0)+N(Products!H6)))-(IFERROR(INDEX(Settings!$C$5:$C$9,MATCH(B6,Settings!$A$5:$A$9,0)),0)+IFERROR(INDEX(Settings!$D$5:$D$9,MATCH(B6,Settings!$A$5:$A$9,0)),0)+IFERROR(INDEX(Settings!$F$5:$F$9,MATCH(B6,Settings!$A$5:$A$9,0)),0))-C6) | H6: =IF(OR(A6="",N(E6)=0),"",G6/E6) | I6: =IF(OR(A6="",N(E6)=0),"",IF(G6<0,"Loses money at this price",IF(E6<F6,"Below target: raise to "&TEXT(F6,"$0.00"),"On target")))
A7: =IF(Products!A7="","",Products!A7) | B7: Etsy | C7: =IF(A7="","",Products!I7) | D7: 0.3 | E7: 6 | F7: =IF(A7="","",IF(1-(IFERROR(INDEX(Settings!$B$5:$B$9,MATCH(B7,Settings!$A$5:$A$9,0)),0)+IFERROR(INDEX(Settings!$E$5:$E$9,MATCH(B7,Settings!$A$5:$A$9,0)),0)+IFERROR(INDEX(Settings!$G$5:$G$9,MATCH(B7,Settings!$A$5:$A$9,0)),0)+N(Products!H7))-D7<=0,"margin too high",(C7+(IFERROR(INDEX(Settings!$C$5:$C$9,MATCH(B7,Settings!$A$5:$A$9,0)),0)+IFERROR(INDEX(Settings!$D$5:$D$9,MATCH(B7,Settings!$A$5:$A$9,0)),0)+IFERROR(INDEX(Settings!$F$5:$F$9,MATCH(B7,Settings!$A$5:$A$9,0)),0)))/(1-(IFERROR(INDEX(Settings!$B$5:$B$9,MATCH(B7,Settings!$A$5:$A$9,0)),0)+IFERROR(INDEX(Settings!$E$5:$E$9,MATCH(B7,Settings!$A$5:$A$9,0)),0)+IFERROR(INDEX(Settings!$G$5:$G$9,MATCH(B7,Settings!$A$5:$A$9,0)),0)+N(Products!H7))-D7))) | G7: =IF(OR(A7="",N(E7)=0),"",E7*(1-(IFERROR(INDEX(Settings!$B$5:$B$9,MATCH(B7,Settings!$A$5:$A$9,0)),0)+IFERROR(INDEX(Settings!$E$5:$E$9,MATCH(B7,Settings!$A$5:$A$9,0)),0)+IFERROR(INDEX(Settings!$G$5:$G$9,MATCH(B7,Settings!$A$5:$A$9,0)),0)+N(Products!H7)))-(IFERROR(INDEX(Settings!$C$5:$C$9,MATCH(B7,Settings!$A$5:$A$9,0)),0)+IFERROR(INDEX(Settings!$D$5:$D$9,MATCH(B7,Settings!$A$5:$A$9,0)),0)+IFERROR(INDEX(Settings!$F$5:$F$9,MATCH(B7,Settings!$A$5:$A$9,0)),0))-C7) | H7: =IF(OR(A7="",N(E7)=0),"",G7/E7) | I7: =IF(OR(A7="",N(E7)=0),"",IF(G7<0,"Loses money at this price",IF(E7<F7,"Below target: raise to "&TEXT(F7,"$0.00"),"On target")))
A8: =IF(Products!A8="","",Products!A8) | B8: Amazon | C8: =IF(A8="","",Products!I8) | D8: 0.3 | E8: 24 | F8: =IF(A8="","",IF(1-(IFERROR(INDEX(Settings!$B$5:$B$9,MATCH(B8,Settings!$A$5:$A$9,0)),0)+IFERROR(INDEX(Settings!$E$5:$E$9,MATCH(B8,Settings!$A$5:$A$9,0)),0)+IFERROR(INDEX(Settings!$G$5:$G$9,MATCH(B8,Settings!$A$5:$A$9,0)),0)+N(Products!H8))-D8<=0,"margin too high",(C8+(IFERROR(INDEX(Settings!$C$5:$C$9,MATCH(B8,Settings!$A$5:$A$9,0)),0)+IFERROR(INDEX(Settings!$D$5:$D$9,MATCH(B8,Settings!$A$5:$A$9,0)),0)+IFERROR(INDEX(Settings!$F$5:$F$9,MATCH(B8,Settings!$A$5:$A$9,0)),0)))/(1-(IFERROR(INDEX(Settings!$B$5:$B$9,MATCH(B8,Settings!$A$5:$A$9,0)),0)+IFERROR(INDEX(Settings!$E$5:$E$9,MATCH(B8,Settings!$A$5:$A$9,0)),0)+IFERROR(INDEX(Settings!$G$5:$G$9,MATCH(B8,Settings!$A$5:$A$9,0)),0)+N(Products!H8))-D8))) | G8: =IF(OR(A8="",N(E8)=0),"",E8*(1-(IFERROR(INDEX(Settings!$B$5:$B$9,MATCH(B8,Settings!$A$5:$A$9,0)),0)+IFERROR(INDEX(Settings!$E$5:$E$9,MATCH(B8,Settings!$A$5:$A$9,0)),0)+IFERROR(INDEX(Settings!$G$5:$G$9,MATCH(B8,Settings!$A$5:$A$9,0)),0)+N(Products!H8)))-(IFERROR(INDEX(Settings!$C$5:$C$9,MATCH(B8,Settings!$A$5:$A$9,0)),0)+IFERROR(INDEX(Settings!$D$5:$D$9,MATCH(B8,Settings!$A$5:$A$9,0)),0)+IFERROR(INDEX(Settings!$F$5:$F$9,MATCH(B8,Settings!$A$5:$A$9,0)),0))-C8) | H8: =IF(OR(A8="",N(E8)=0),"",G8/E8) | I8: =IF(OR(A8="",N(E8)=0),"",IF(G8<0,"Loses money at this price",IF(E8<F8,"Below target: raise to "&TEXT(F8,"$0.00"),"On target")))
A9: =IF(Products!A9="","",Products!A9) | B9: Etsy | C9: =IF(A9="","",Products!I9) | D9: 0.3 | F9: =IF(A9="","",IF(1-(IFERROR(INDEX(Settings!$B$5:$B$9,MATCH(B9,Settings!$A$5:$A$9,0)),0)+IFERROR(INDEX(Settings!$E$5:$E$9,MATCH(B9,Settings!$A$5:$A$9,0)),0)+IFERROR(INDEX(Settings!$G$5:$G$9,MATCH(B9,Settings!$A$5:$A$9,0)),0)+N(Products!H9))-D9<=0,"margin too high",(C9+(IFERROR(INDEX(Settings!$C$5:$C$9,MATCH(B9,Settings!$A$5:$A$9,0)),0)+IFERROR(INDEX(Settings!$D$5:$D$9,MATCH(B9,Settings!$A$5:$A$9,0)),0)+IFERROR(INDEX(Settings!$F$5:$F$9,MATCH(B9,Settings!$A$5:$A$9,0)),0)))/(1-(IFERROR(INDEX(Settings!$B$5:$B$9,MATCH(B9,Settings!$A$5:$A$9,0)),0)+IFERROR(INDEX(Settings!$E$5:$E$9,MATCH(B9,Settings!$A$5:$A$9,0)),0)+IFERROR(INDEX(Settings!$G$5:$G$9,MATCH(B9,Settings!$A$5:$A$9,0)),0)+N(Products!H9))-D9))) | G9: =IF(OR(A9="",N(E9)=0),"",E9*(1-(IFERROR(INDEX(Settings!$B$5:$B$9,MATCH(B9,Settings!$A$5:$A$9,0)),0)+IFERROR(INDEX(Settings!$E$5:$E$9,MATCH(B9,Settings!$A$5:$A$9,0)),0)+IFERROR(INDEX(Settings!$G$5:$G$9,MATCH(B9,Settings!$A$5:$A$9,0)),0)+N(Products!H9)))-(IFERROR(INDEX(Settings!$C$5:$C$9,MATCH(B9,Settings!$A$5:$A$9,0)),0)+IFERROR(INDEX(Settings!$D$5:$D$9,MATCH(B9,Settings!$A$5:$A$9,0)),0)+IFERROR(INDEX(Settings!$F$5:$F$9,MATCH(B9,Settings!$A$5:$A$9,0)),0))-C9) | H9: =IF(OR(A9="",N(E9)=0),"",G9/E9) | I9: =IF(OR(A9="",N(E9)=0),"",IF(G9<0,"Loses money at this price",IF(E9<F9,"Below target: raise to "&TEXT(F9,"$0.00"),"On target")))
A10: =IF(Products!A10="","",Products!A10) | B10: Etsy | C10: =IF(A10="","",Products!I10) | D10: 0.3 | F10: =IF(A10="","",IF(1-(IFERROR(INDEX(Settings!$B$5:$B$9,MATCH(B10,Settings!$A$5:$A$9,0)),0)+IFERROR(INDEX(Settings!$E$5:$E$9,MATCH(B10,Settings!$A$5:$A$9,0)),0)+IFERROR(INDEX(Settings!$G$5:$G$9,MATCH(B10,Settings!$A$5:$A$9,0)),0)+N(Products!H10))-D10<=0,"margin too high",(C10+(IFERROR(INDEX(Settings!$C$5:$C$9,MATCH(B10,Settings!$A$5:$A$9,0)),0)+IFERROR(INDEX(Settings!$D$5:$D$9,MATCH(B10,Settings!$A$5:$A$9,0)),0)+IFERROR(INDEX(Settings!$F$5:$F$9,MATCH(B10,Settings!$A$5:$A$9,0)),0)))/(1-(IFERROR(INDEX(Settings!$B$5:$B$9,MATCH(B10,Settings!$A$5:$A$9,0)),0)+IFERROR(INDEX(Settings!$E$5:$E$9,MATCH(B10,Settings!$A$5:$A$9,0)),0)+IFERROR(INDEX(Settings!$G$5:$G$9,MATCH(B10,Settings!$A$5:$A$9,0)),0)+N(Products!H10))-D10))) | G10: =IF(OR(A10="",N(E10)=0),"",E10*(1-(IFERROR(INDEX(Settings!$B$5:$B$9,MATCH(B10,Settings!$A$5:$A$9,0)),0)+IFERROR(INDEX(Settings!$E$5:$E$9,MATCH(B10,Settings!$A$5:$A$9,0)),0)+IFERROR(INDEX(Settings!$G$5:$G$9,MATCH(B10,Settings!$A$5:$A$9,0)),0)+N(Products!H10)))-(IFERROR(INDEX(Settings!$C$5:$C$9,MATCH(B10,Settings!$A$5:$A$9,0)),0)+IFERROR(INDEX(Settings!$D$5:$D$9,MATCH(B10,Settings!$A$5:$A$9,0)),0)+IFERROR(INDEX(Settings!$F$5:$F$9,MATCH(B10,Settings!$A$5:$A$9,0)),0))-C10) | H10: =IF(OR(A10="",N(E10)=0),"",G10/E10) | I10: =IF(OR(A10="",N(E10)=0),"",IF(G10<0,"Loses money at this price",IF(E10<F10,"Below target: raise to "&TEXT(F10,"$0.00"),"On target")))
A11: =IF(Products!A11="","",Products!A11) | B11: Etsy | C11: =IF(A11="","",Products!I11) | D11: 0.3 | F11: =IF(A11="","",IF(1-(IFERROR(INDEX(Settings!$B$5:$B$9,MATCH(B11,Settings!$A$5:$A$9,0)),0)+IFERROR(INDEX(Settings!$E$5:$E$9,MATCH(B11,Settings!$A$5:$A$9,0)),0)+IFERROR(INDEX(Settings!$G$5:$G$9,MATCH(B11,Settings!$A$5:$A$9,0)),0)+N(Products!H11))-D11<=0,"margin too high",(C11+(IFERROR(INDEX(Settings!$C$5:$C$9,MATCH(B11,Settings!$A$5:$A$9,0)),0)+IFERROR(INDEX(Settings!$D$5:$D$9,MATCH(B11,Settings!$A$5:$A$9,0)),0)+IFERROR(INDEX(Settings!$F$5:$F$9,MATCH(B11,Settings!$A$5:$A$9,0)),0)))/(1-(IFERROR(INDEX(Settings!$B$5:$B$9,MATCH(B11,Settings!$A$5:$A$9,0)),0)+IFERROR(INDEX(Settings!$E$5:$E$9,MATCH(B11,Settings!$A$5:$A$9,0)),0)+IFERROR(INDEX(Settings!$G$5:$G$9,MATCH(B11,Settings!$A$5:$A$9,0)),0)+N(Products!H11))-D11))) | G11: =IF(OR(A11="",N(E11)=0),"",E11*(1-(IFERROR(INDEX(Settings!$B$5:$B$9,MATCH(B11,Settings!$A$5:$A$9,0)),0)+IFERROR(INDEX(Settings!$E$5:$E$9,MATCH(B11,Settings!$A$5:$A$9,0)),0)+IFERROR(INDEX(Settings!$G$5:$G$9,MATCH(B11,Settings!$A$5:$A$9,0)),0)+N(Products!H11)))-(IFERROR(INDEX(Settings!$C$5:$C$9,MATCH(B11,Settings!$A$5:$A$9,0)),0)+IFERROR(INDEX(Settings!$D$5:$D$9,MATCH(B11,Settings!$A$5:$A$9,0)),0)+IFERROR(INDEX(Settings!$F$5:$F$9,MATCH(B11,Settings!$A$5:$A$9,0)),0))-C11) | H11: =IF(OR(A11="",N(E11)=0),"",G11/E11) | I11: =IF(OR(A11="",N(E11)=0),"",IF(G11<0,"Loses money at this price",IF(E11<F11,"Below target: raise to "&TEXT(F11,"$0.00"),"On target")))
A12: =IF(Products!A12="","",Products!A12) | B12: Etsy | C12: =IF(A12="","",Products!I12) | D12: 0.3 | F12: =IF(A12="","",IF(1-(IFERROR(INDEX(Settings!$B$5:$B$9,MATCH(B12,Settings!$A$5:$A$9,0)),0)+IFERROR(INDEX(Settings!$E$5:$E$9,MATCH(B12,Settings!$A$5:$A$9,0)),0)+IFERROR(INDEX(Settings!$G$5:$G$9,MATCH(B12,Settings!$A$5:$A$9,0)),0)+N(Products!H12))-D12<=0,"margin too high",(C12+(IFERROR(INDEX(Settings!$C$5:$C$9,MATCH(B12,Settings!$A$5:$A$9,0)),0)+IFERROR(INDEX(Settings!$D$5:$D$9,MATCH(B12,Settings!$A$5:$A$9,0)),0)+IFERROR(INDEX(Settings!$F$5:$F$9,MATCH(B12,Settings!$A$5:$A$9,0)),0)))/(1-(IFERROR(INDEX(Settings!$B$5:$B$9,MATCH(B12,Settings!$A$5:$A$9,0)),0)+IFERROR(INDEX(Settings!$E$5:$E$9,MATCH(B12,Settings!$A$5:$A$9,0)),0)+IFERROR(INDEX(Settings!$G$5:$G$9,MATCH(B12,Settings!$A$5:$A$9,0)),0)+N(Products!H12))-D12))) | G12: =IF(OR(A12="",N(E12)=0),"",E12*(1-(IFERROR(INDEX(Settings!$B$5:$B$9,MATCH(B12,Settings!$A$5:$A$9,0)),0)+IFERROR(INDEX(Settings!$E$5:$E$9,MATCH(B12,Settings!$A$5:$A$9,0)),0)+IFERROR(INDEX(Settings!$G$5:$G$9,MATCH(B12,Settings!$A$5:$A$9,0)),0)+N(Products!H12)))-(IFERROR(INDEX(Settings!$C$5:$C$9,MATCH(B12,Settings!$A$5:$A$9,0)),0)+IFERROR(INDEX(Settings!$D$5:$D$9,MATCH(B12,Settings!$A$5:$A$9,0)),0)+IFERROR(INDEX(Settings!$F$5:$F$9,MATCH(B12,Settings!$A$5:$A$9,0)),0))-C12) | H12: =IF(OR(A12="",N(E12)=0),"",G12/E12) | I12: =IF(OR(A12="",N(E12)=0),"",IF(G12<0,"Loses money at this price",IF(E12<F12,"Below target: raise to "&TEXT(F12,"$0.00"),"On target")))
A13: =IF(Products!A13="","",Products!A13) | B13: Etsy | C13: =IF(A13="","",Products!I13) | D13: 0.3 | F13: =IF(A13="","",IF(1-(IFERROR(INDEX(Settings!$B$5:$B$9,MATCH(B13,Settings!$A$5:$A$9,0)),0)+IFERROR(INDEX(Settings!$E$5:$E$9,MATCH(B13,Settings!$A$5:$A$9,0)),0)+IFERROR(INDEX(Settings!$G$5:$G$9,MATCH(B13,Settings!$A$5:$A$9,0)),0)+N(Products!H13))-D13<=0,"margin too high",(C13+(IFERROR(INDEX(Settings!$C$5:$C$9,MATCH(B13,Settings!$A$5:$A$9,0)),0)+IFERROR(INDEX(Settings!$D$5:$D$9,MATCH(B13,Settings!$A$5:$A$9,0)),0)+IFERROR(INDEX(Settings!$F$5:$F$9,MATCH(B13,Settings!$A$5:$A$9,0)),0)))/(1-(IFERROR(INDEX(Settings!$B$5:$B$9,MATCH(B13,Settings!$A$5:$A$9,0)),0)+IFERROR(INDEX(Settings!$E$5:$E$9,MATCH(B13,Settings!$A$5:$A$9,0)),0)+IFERROR(INDEX(Settings!$G$5:$G$9,MATCH(B13,Settings!$A$5:$A$9,0)),0)+N(Products!H13))-D13))) | G13: =IF(OR(A13="",N(E13)=0),"",E13*(1-(IFERROR(INDEX(Settings!$B$5:$B$9,MATCH(B13,Settings!$A$5:$A$9,0)),0)+IFERROR(INDEX(Settings!$E$5:$E$9,MATCH(B13,Settings!$A$5:$A$9,0)),0)+IFERROR(INDEX(Settings!$G$5:$G$9,MATCH(B13,Settings!$A$5:$A$9,0)),0)+N(Products!H13)))-(IFERROR(INDEX(Settings!$C$5:$C$9,MATCH(B13,Settings!$A$5:$A$9,0)),0)+IFERROR(INDEX(Settings!$D$5:$D$9,MATCH(B13,Settings!$A$5:$A$9,0)),0)+IFERROR(INDEX(Settings!$F$5:$F$9,MATCH(B13,Settings!$A$5:$A$9,0)),0))-C13) | H13: =IF(OR(A13="",N(E13)=0),"",G13/E13) | I13: =IF(OR(A13="",N(E13)=0),"",IF(G13<0,"Loses money at this price",IF(E13<F13,"Below target: raise to "&TEXT(F13,"$0.00"),"On target")))
A14: =IF(Products!A14="","",Products!A14) | B14: Etsy | C14: =IF(A14="","",Products!I14) | D14: 0.3 | F14: =IF(A14="","",IF(1-(IFERROR(INDEX(Settings!$B$5:$B$9,MATCH(B14,Settings!$A$5:$A$9,0)),0)+IFERROR(INDEX(Settings!$E$5:$E$9,MATCH(B14,Settings!$A$5:$A$9,0)),0)+IFERROR(INDEX(Settings!$G$5:$G$9,MATCH(B14,Settings!$A$5:$A$9,0)),0)+N(Products!H14))-D14<=0,"margin too high",(C14+(IFERROR(INDEX(Settings!$C$5:$C$9,MATCH(B14,Settings!$A$5:$A$9,0)),0)+IFERROR(INDEX(Settings!$D$5:$D$9,MATCH(B14,Settings!$A$5:$A$9,0)),0)+IFERROR(INDEX(Settings!$F$5:$F$9,MATCH(B14,Settings!$A$5:$A$9,0)),0)))/(1-(IFERROR(INDEX(Settings!$B$5:$B$9,MATCH(B14,Settings!$A$5:$A$9,0)),0)+IFERROR(INDEX(Settings!$E$5:$E$9,MATCH(B14,Settings!$A$5:$A$9,0)),0)+IFERROR(INDEX(Settings!$G$5:$G$9,MATCH(B14,Settings!$A$5:$A$9,0)),0)+N(Products!H14))-D14))) | G14: =IF(OR(A14="",N(E14)=0),"",E14*(1-(IFERROR(INDEX(Settings!$B$5:$B$9,MATCH(B14,Settings!$A$5:$A$9,0)),0)+IFERROR(INDEX(Settings!$E$5:$E$9,MATCH(B14,Settings!$A$5:$A$9,0)),0)+IFERROR(INDEX(Settings!$G$5:$G$9,MATCH(B14,Settings!$A$5:$A$9,0)),0)+N(Products!H14)))-(IFERROR(INDEX(Settings!$C$5:$C$9,MATCH(B14,Settings!$A$5:$A$9,0)),0)+IFERROR(INDEX(Settings!$D$5:$D$9,MATCH(B14,Settings!$A$5:$A$9,0)),0)+IFERROR(INDEX(Settings!$F$5:$F$9,MATCH(B14,Settings!$A$5:$A$9,0)),0))-C14) | H14: =IF(OR(A14="",N(E14)=0),"",G14/E14) | I14: =IF(OR(A14="",N(E14)=0),"",IF(G14<0,"Loses money at this price",IF(E14<F14,"Below target: raise to "&TEXT(F14,"$0.00"),"On target")))
A15: =IF(Products!A15="","",Products!A15) | B15: Etsy | C15: =IF(A15="","",Products!I15) | D15: 0.3 | F15: =IF(A15="","",IF(1-(IFERROR(INDEX(Settings!$B$5:$B$9,MATCH(B15,Settings!$A$5:$A$9,0)),0)+IFERROR(INDEX(Settings!$E$5:$E$9,MATCH(B15,Settings!$A$5:$A$9,0)),0)+IFERROR(INDEX(Settings!$G$5:$G$9,MATCH(B15,Settings!$A$5:$A$9,0)),0)+N(Products!H15))-D15<=0,"margin too high",(C15+(IFERROR(INDEX(Settings!$C$5:$C$9,MATCH(B15,Settings!$A$5:$A$9,0)),0)+IFERROR(INDEX(Settings!$D$5:$D$9,MATCH(B15,Settings!$A$5:$A$9,0)),0)+IFERROR(INDEX(Settings!$F$5:$F$9,MATCH(B15,Settings!$A$5:$A$9,0)),0)))/(1-(IFERROR(INDEX(Settings!$B$5:$B$9,MATCH(B15,Settings!$A$5:$A$9,0)),0)+IFERROR(INDEX(Settings!$E$5:$E$9,MATCH(B15,Settings!$A$5:$A$9,0)),0)+IFERROR(INDEX(Settings!$G$5:$G$9,MATCH(B15,Settings!$A$5:$A$9,0)),0)+N(Products!H15))-D15))) | G15: =IF(OR(A15="",N(E15)=0),"",E15*(1-(IFERROR(INDEX(Settings!$B$5:$B$9,MATCH(B15,Settings!$A$5:$A$9,0)),0)+IFERROR(INDEX(Settings!$E$5:$E$9,MATCH(B15,Settings!$A$5:$A$9,0)),0)+IFERROR(INDEX(Settings!$G$5:$G$9,MATCH(B15,Settings!$A$5:$A$9,0)),0)+N(Products!H15)))-(IFERROR(INDEX(Settings!$C$5:$C$9,MATCH(B15,Settings!$A$5:$A$9,0)),0)+IFERROR(INDEX(Settings!$D$5:$D$9,MATCH(B15,Settings!$A$5:$A$9,0)),0)+IFERROR(INDEX(Settings!$F$5:$F$9,MATCH(B15,Settings!$A$5:$A$9,0)),0))-C15) | H15: =IF(OR(A15="",N(E15)=0),"",G15/E15) | I15: =IF(OR(A15="",N(E15)=0),"",IF(G15<0,"Loses money at this price",IF(E15<F15,"Below target: raise to "&TEXT(F15,"$0.00"),"On target")))
A16: =IF(Products!A16="","",Products!A16) | B16: Etsy | C16: =IF(A16="","",Products!I16) | D16: 0.3 | F16: =IF(A16="","",IF(1-(IFERROR(INDEX(Settings!$B$5:$B$9,MATCH(B16,Settings!$A$5:$A$9,0)),0)+IFERROR(INDEX(Settings!$E$5:$E$9,MATCH(B16,Settings!$A$5:$A$9,0)),0)+IFERROR(INDEX(Settings!$G$5:$G$9,MATCH(B16,Settings!$A$5:$A$9,0)),0)+N(Products!H16))-D16<=0,"margin too high",(C16+(IFERROR(INDEX(Settings!$C$5:$C$9,MATCH(B16,Settings!$A$5:$A$9,0)),0)+IFERROR(INDEX(Settings!$D$5:$D$9,MATCH(B16,Settings!$A$5:$A$9,0)),0)+IFERROR(INDEX(Settings!$F$5:$F$9,MATCH(B16,Settings!$A$5:$A$9,0)),0)))/(1-(IFERROR(INDEX(Settings!$B$5:$B$9,MATCH(B16,Settings!$A$5:$A$9,0)),0)+IFERROR(INDEX(Settings!$E$5:$E$9,MATCH(B16,Settings!$A$5:$A$9,0)),0)+IFERROR(INDEX(Settings!$G$5:$G$9,MATCH(B16,Settings!$A$5:$A$9,0)),0)+N(Products!H16))-D16))) | G16: =IF(OR(A16="",N(E16)=0),"",E16*(1-(IFERROR(INDEX(Settings!$B$5:$B$9,MATCH(B16,Settings!$A$5:$A$9,0)),0)+IFERROR(INDEX(Settings!$E$5:$E$9,MATCH(B16,Settings!$A$5:$A$9,0)),0)+IFERROR(INDEX(Settings!$G$5:$G$9,MATCH(B16,Settings!$A$5:$A$9,0)),0)+N(Products!H16)))-(IFERROR(INDEX(Settings!$C$5:$C$9,MATCH(B16,Settings!$A$5:$A$9,0)),0)+IFERROR(INDEX(Settings!$D$5:$D$9,MATCH(B16,Settings!$A$5:$A$9,0)),0)+IFERROR(INDEX(Settings!$F$5:$F$9,MATCH(B16,Settings!$A$5:$A$9,0)),0))-C16) | H16: =IF(OR(A16="",N(E16)=0),"",G16/E16) | I16: =IF(OR(A16="",N(E16)=0),"",IF(G16<0,"Loses money at this price",IF(E16<F16,"Below target: raise to "&TEXT(F16,"$0.00"),"On target")))
A17: =IF(Products!A17="","",Products!A17) | B17: Etsy | C17: =IF(A17="","",Products!I17) | D17: 0.3 | F17: =IF(A17="","",IF(1-(IFERROR(INDEX(Settings!$B$5:$B$9,MATCH(B17,Settings!$A$5:$A$9,0)),0)+IFERROR(INDEX(Settings!$E$5:$E$9,MATCH(B17,Settings!$A$5:$A$9,0)),0)+IFERROR(INDEX(Settings!$G$5:$G$9,MATCH(B17,Settings!$A$5:$A$9,0)),0)+N(Products!H17))-D17<=0,"margin too high",(C17+(IFERROR(INDEX(Settings!$C$5:$C$9,MATCH(B17,Settings!$A$5:$A$9,0)),0)+IFERROR(INDEX(Settings!$D$5:$D$9,MATCH(B17,Settings!$A$5:$A$9,0)),0)+IFERROR(INDEX(Settings!$F$5:$F$9,MATCH(B17,Settings!$A$5:$A$9,0)),0)))/(1-(IFERROR(INDEX(Settings!$B$5:$B$9,MATCH(B17,Settings!$A$5:$A$9,0)),0)+IFERROR(INDEX(Settings!$E$5:$E$9,MATCH(B17,Settings!$A$5:$A$9,0)),0)+IFERROR(INDEX(Settings!$G$5:$G$9,MATCH(B17,Settings!$A$5:$A$9,0)),0)+N(Products!H17))-D17))) | G17: =IF(OR(A17="",N(E17)=0),"",E17*(1-(IFERROR(INDEX(Settings!$B$5:$B$9,MATCH(B17,Settings!$A$5:$A$9,0)),0)+IFERROR(INDEX(Settings!$E$5:$E$9,MATCH(B17,Settings!$A$5:$A$9,0)),0)+IFERROR(INDEX(Settings!$G$5:$G$9,MATCH(B17,Settings!$A$5:$A$9,0)),0)+N(Products!H17)))-(IFERROR(INDEX(Settings!$C$5:$C$9,MATCH(B17,Settings!$A$5:$A$9,0)),0)+IFERROR(INDEX(Settings!$D$5:$D$9,MATCH(B17,Settings!$A$5:$A$9,0)),0)+IFERROR(INDEX(Settings!$F$5:$F$9,MATCH(B17,Settings!$A$5:$A$9,0)),0))-C17) | H17: =IF(OR(A17="",N(E17)=0),"",G17/E17) | I17: =IF(OR(A17="",N(E17)=0),"",IF(G17<0,"Loses money at this price",IF(E17<F17,"Below target: raise to "&TEXT(F17,"$0.00"),"On target")))
A18: =IF(Products!A18="","",Products!A18) | B18: Etsy | C18: =IF(A18="","",Products!I18) | D18: 0.3 | F18: =IF(A18="","",IF(1-(IFERROR(INDEX(Settings!$B$5:$B$9,MATCH(B18,Settings!$A$5:$A$9,0)),0)+IFERROR(INDEX(Settings!$E$5:$E$9,MATCH(B18,Settings!$A$5:$A$9,0)),0)+IFERROR(INDEX(Settings!$G$5:$G$9,MATCH(B18,Settings!$A$5:$A$9,0)),0)+N(Products!H18))-D18<=0,"margin too high",(C18+(IFERROR(INDEX(Settings!$C$5:$C$9,MATCH(B18,Settings!$A$5:$A$9,0)),0)+IFERROR(INDEX(Settings!$D$5:$D$9,MATCH(B18,Settings!$A$5:$A$9,0)),0)+IFERROR(INDEX(Settings!$F$5:$F$9,MATCH(B18,Settings!$A$5:$A$9,0)),0)))/(1-(IFERROR(INDEX(Settings!$B$5:$B$9,MATCH(B18,Settings!$A$5:$A$9,0)),0)+IFERROR(INDEX(Settings!$E$5:$E$9,MATCH(B18,Settings!$A$5:$A$9,0)),0)+IFERROR(INDEX(Settings!$G$5:$G$9,MATCH(B18,Settings!$A$5:$A$9,0)),0)+N(Products!H18))-D18))) | G18: =IF(OR(A18="",N(E18)=0),"",E18*(1-(IFERROR(INDEX(Settings!$B$5:$B$9,MATCH(B18,Settings!$A$5:$A$9,0)),0)+IFERROR(INDEX(Settings!$E$5:$E$9,MATCH(B18,Settings!$A$5:$A$9,0)),0)+IFERROR(INDEX(Settings!$G$5:$G$9,MATCH(B18,Settings!$A$5:$A$9,0)),0)+N(Products!H18)))-(IFERROR(INDEX(Settings!$C$5:$C$9,MATCH(B18,Settings!$A$5:$A$9,0)),0)+IFERROR(INDEX(Settings!$D$5:$D$9,MATCH(B18,Settings!$A$5:$A$9,0)),0)+IFERROR(INDEX(Settings!$F$5:$F$9,MATCH(B18,Settings!$A$5:$A$9,0)),0))-C18) | H18: =IF(OR(A18="",N(E18)=0),"",G18/E18) | I18: =IF(OR(A18="",N(E18)=0),"",IF(G18<0,"Loses money at this price",IF(E18<F18,"Below target: raise to "&TEXT(F18,"$0.00"),"On target")))
A19: =IF(Products!A19="","",Products!A19) | B19: Etsy | C19: =IF(A19="","",Products!I19) | D19: 0.3 | F19: =IF(A19="","",IF(1-(IFERROR(INDEX(Settings!$B$5:$B$9,MATCH(B19,Settings!$A$5:$A$9,0)),0)+IFERROR(INDEX(Settings!$E$5:$E$9,MATCH(B19,Settings!$A$5:$A$9,0)),0)+IFERROR(INDEX(Settings!$G$5:$G$9,MATCH(B19,Settings!$A$5:$A$9,0)),0)+N(Products!H19))-D19<=0,"margin too high",(C19+(IFERROR(INDEX(Settings!$C$5:$C$9,MATCH(B19,Settings!$A$5:$A$9,0)),0)+IFERROR(INDEX(Settings!$D$5:$D$9,MATCH(B19,Settings!$A$5:$A$9,0)),0)+IFERROR(INDEX(Settings!$F$5:$F$9,MATCH(B19,Settings!$A$5:$A$9,0)),0)))/(1-(IFERROR(INDEX(Settings!$B$5:$B$9,MATCH(B19,Settings!$A$5:$A$9,0)),0)+IFERROR(INDEX(Settings!$E$5:$E$9,MATCH(B19,Settings!$A$5:$A$9,0)),0)+IFERROR(INDEX(Settings!$G$5:$G$9,MATCH(B19,Settings!$A$5:$A$9,0)),0)+N(Products!H19))-D19))) | G19: =IF(OR(A19="",N(E19)=0),"",E19*(1-(IFERROR(INDEX(Settings!$B$5:$B$9,MATCH(B19,Settings!$A$5:$A$9,0)),0)+IFERROR(INDEX(Settings!$E$5:$E$9,MATCH(B19,Settings!$A$5:$A$9,0)),0)+IFERROR(INDEX(Settings!$G$5:$G$9,MATCH(B19,Settings!$A$5:$A$9,0)),0)+N(Products!H19)))-(IFERROR(INDEX(Settings!$C$5:$C$9,MATCH(B19,Settings!$A$5:$A$9,0)),0)+IFERROR(INDEX(Settings!$D$5:$D$9,MATCH(B19,Settings!$A$5:$A$9,0)),0)+IFERROR(INDEX(Settings!$F$5:$F$9,MATCH(B19,Settings!$A$5:$A$9,0)),0))-C19) | H19: =IF(OR(A19="",N(E19)=0),"",G19/E19) | I19: =IF(OR(A19="",N(E19)=0),"",IF(G19<0,"Loses money at this price",IF(E19<F19,"Below target: raise to "&TEXT(F19,"$0.00"),"On target")))
A20: =IF(Products!A20="","",Products!A20) | B20: Etsy | C20: =IF(A20="","",Products!I20) | D20: 0.3 | F20: =IF(A20="","",IF(1-(IFERROR(INDEX(Settings!$B$5:$B$9,MATCH(B20,Settings!$A$5:$A$9,0)),0)+IFERROR(INDEX(Settings!$E$5:$E$9,MATCH(B20,Settings!$A$5:$A$9,0)),0)+IFERROR(INDEX(Settings!$G$5:$G$9,MATCH(B20,Settings!$A$5:$A$9,0)),0)+N(Products!H20))-D20<=0,"margin too high",(C20+(IFERROR(INDEX(Settings!$C$5:$C$9,MATCH(B20,Settings!$A$5:$A$9,0)),0)+IFERROR(INDEX(Settings!$D$5:$D$9,MATCH(B20,Settings!$A$5:$A$9,0)),0)+IFERROR(INDEX(Settings!$F$5:$F$9,MATCH(B20,Settings!$A$5:$A$9,0)),0)))/(1-(IFERROR(INDEX(Settings!$B$5:$B$9,MATCH(B20,Settings!$A$5:$A$9,0)),0)+IFERROR(INDEX(Settings!$E$5:$E$9,MATCH(B20,Settings!$A$5:$A$9,0)),0)+IFERROR(INDEX(Settings!$G$5:$G$9,MATCH(B20,Settings!$A$5:$A$9,0)),0)+N(Products!H20))-D20))) | G20: =IF(OR(A20="",N(E20)=0),"",E20*(1-(IFERROR(INDEX(Settings!$B$5:$B$9,MATCH(B20,Settings!$A$5:$A$9,0)),0)+IFERROR(INDEX(Settings!$E$5:$E$9,MATCH(B20,Settings!$A$5:$A$9,0)),0)+IFERROR(INDEX(Settings!$G$5:$G$9,MATCH(B20,Settings!$A$5:$A$9,0)),0)+N(Products!H20)))-(IFERROR(INDEX(Settings!$C$5:$C$9,MATCH(B20,Settings!$A$5:$A$9,0)),0)+IFERROR(INDEX(Settings!$D$5:$D$9,MATCH(B20,Settings!$A$5:$A$9,0)),0)+IFERROR(INDEX(Settings!$F$5:$F$9,MATCH(B20,Settings!$A$5:$A$9,0)),0))-C20) | H20: =IF(OR(A20="",N(E20)=0),"",G20/E20) | I20: =IF(OR(A20="",N(E20)=0),"",IF(G20<0,"Loses money at this price",IF(E20<F20,"Below target: raise to "&TEXT(F20,"$0.00"),"On target")))
... A204: =IF(Products!A204="","",Products!A204) | B204: Etsy | C204: =IF(A204="","",Products!I204) | D204: 0.3 | F204: =IF(A204="","",IF(1-(IFERROR(INDEX(Settings!$B$5:$B$9,MATCH(B204,Settings!$A$5:$A$9,0)),0)+IFERROR(INDEX(Settings!$E$5:$E$9,MATCH(B204,Settings!$A$5:$A$9,0)),0)+IFERROR(INDEX(Settings!$G$5:$G$9,MATCH(B204,Settings!$A$5:$A$9,0)),0)+N(Products!H204))-D204<=0,"margin too high",(C204+(IFERROR(INDEX(Settings!$C$5:$C$9,MATCH(B204,Settings!$A$5:$A$9,0)),0)+IFERROR(INDEX(Settings!$D$5:$D$9,MATCH(B204,Settings!$A$5:$A$9,0)),0)+IFERROR(INDEX(Settings!$F$5:$F$9,MATCH(B204,Settings!$A$5:$A$9,0)),0)))/(1-(IFERROR(INDEX(Settings!$B$5:$B$9,MATCH(B204,Settings!$A$5:$A$9,0)),0)+IFERROR(INDEX(Settings!$E$5:$E$9,MATCH(B204,Settings!$A$5:$A$9,0)),0)+IFERROR(INDEX(Settings!$G$5:$G$9,MATCH(B204,Settings!$A$5:$A$9,0)),0)+N(Products!H204))-D204))) | G204: =IF(OR(A204="",N(E204)=0),"",E204*(1-(IFERROR(INDEX(Settings!$B$5:$B$9,MATCH(B204,Settings!$A$5:$A$9,0)),0)+IFERROR(INDEX(Settings!$E$5:$E$9,MATCH(B204,Settings!$A$5:$A$9,0)),0)+IFERROR(INDEX(Settings!$G$5:$G$9,MATCH(B204,Settings!$A$5:$A$9,0)),0)+N(Products!H204)))-(IFERROR(INDEX(Settings!$C$5:$C$9,MATCH(B204,Settings!$A$5:$A$9,0)),0)+IFERROR(INDEX(Settings!$D$5:$D$9,MATCH(B204,Settings!$A$5:$A$9,0)),0)+IFERROR(INDEX(Settings!$F$5:$F$9,MATCH(B204,Settings!$A$5:$A$9,0)),0))-C204) | H204: =IF(OR(A204="",N(E204)=0),"",G204/E204) | I204: =IF(OR(A204="",N(E204)=0),"",IF(G204<0,"Loses money at this price",IF(E204<F204,"Below target: raise to "&TEXT(F204,"$0.00"),"On target")))

Sheet Settings
A1: Settings
A3: Platform fees
A4: Platform | B4: Sale fee % (of item + shipping) | C4: Fixed fee per order | D4: Fixed fee per unit | E4: Payment % | F4: Payment fixed per order | G4: Ads fee % (e.g. offsite ads) | H4: Notes
A5: Etsy | B5: 0.065 | C5: 0 | D5: 0.2 | E5: 0.03 | F5: 0.25 | G5: 0 | H5: 6.5% transaction, $0.20 listing renewal per unit sold, 3% + $0.25 payment (US). Offsite ads: 15% or 12% if you get them.
A6: Shopify | B6: 0 | C6: 0 | D6: 0 | E6: 0.029 | F6: 0.3 | G6: 0 | H6: Basic plan, Shopify Payments online rate. Plan fee goes in overhead.
A7: Amazon | B7: 0.15 | C7: 0 | D7: 0 | E7: 0 | F7: 0 | G7: 0 | H7: 15% referral (most categories). Put FBA fees per unit in Products > 'Other per-unit fees'.
A8: eBay | B8: 0.136 | C8: 0.4 | D8: 0 | E8: 0 | F8: 0 | G8: 0 | H8: 13.6% final value fee + $0.40 per order (most categories).
A9: Other | B9: 0 | C9: 0 | D9: 0 | E9: 0.029 | F9: 0.3 | G9: 0 | H9: Markets, your own site, etc. Edit to match your card reader.
A11: Your numbers
A12: Labor rate ($ per hour) | B12: 15
A13: Monthly overhead ($) | B13: 25 | C13: Software, plan fees, supplies not tied to one product.
A14: Monthly ad spend, all platforms ($) | B14: 40 | C14: Etsy Ads, Shopify/Meta ads, Amazon PPC. Shared across products by revenue.
A17: Import column names
A18: Each field is read from the column with this header. Fix a header here if a platform renames it.
A19: Field | B19: Etsy header | C19: Etsy col # | D19: Shopify header | E19: Shopify col #
A20: Product name | B20: Item Name | C20: =IFERROR(MATCH(B20,'Etsy Import'!$1:$1,0),"not found") | D20: Lineitem name | E20: =IFERROR(MATCH(D20,'Shopify Import'!$1:$1,0),"not found")
A21: SKU | B21: SKU | C21: =IFERROR(MATCH(B21,'Etsy Import'!$1:$1,0),"not found") | D21: Lineitem sku | E21: =IFERROR(MATCH(D21,'Shopify Import'!$1:$1,0),"not found")
A22: Order ID | B22: Order ID | C22: =IFERROR(MATCH(B22,'Etsy Import'!$1:$1,0),"not found") | D22: Name | E22: =IFERROR(MATCH(D22,'Shopify Import'!$1:$1,0),"not found")
A23: Quantity | B23: Quantity | C23: =IFERROR(MATCH(B23,'Etsy Import'!$1:$1,0),"not found") | D23: Lineitem quantity | E23: =IFERROR(MATCH(D23,'Shopify Import'!$1:$1,0),"not found")
A24: Unit price | B24: Price | C24: =IFERROR(MATCH(B24,'Etsy Import'!$1:$1,0),"not found") | D24: Lineitem price | E24: =IFERROR(MATCH(D24,'Shopify Import'!$1:$1,0),"not found")
A25: Shipping charged | B25: Order Shipping | C25: =IFERROR(MATCH(B25,'Etsy Import'!$1:$1,0),"not found") | D25: Shipping | E25: =IFERROR(MATCH(D25,'Shopify Import'!$1:$1,0),"not found")
A26: Discount | B26: Discount Amount | C26: =IFERROR(MATCH(B26,'Etsy Import'!$1:$1,0),"not found") | D26: Discount Amount | E26: =IFERROR(MATCH(D26,'Shopify Import'!$1:$1,0),"not found")
A27: Order-level amounts repeat on every item row? | B27: Yes | D27: No
A28: Yes = shipping and discount are split evenly across the items in an order. No = they are counted once, from the row where they appear.

Sheet Products
A1: Products
A2: One row per product. Yellow = you fill in. Name must match your listing title exactly (or use SKU).
A4: Product name (exact listing title) | B4: SKU (optional) | C4: Materials per unit | D4: Packaging per unit | E4: Labor minutes per unit | F4: Shipping label you pay per unit | G4: Other per-unit fees (FBA, etc.) | H4: Return rate % | I4: Total cost per unit
A5: Lavender Soy Candle 8oz | B5: CAN-LAV | C5: 3.1 | D5: 0.8 | E5: 10 | F5: 4.5 | G5: 0 | H5: 0.02 | I5: =IF(A5="","",C5+D5+E5/60*Settings!$B$12+F5+G5)
A6: Handmade Ceramic Mug - Speckled | B6: MUG-01 | C6: 6 | D6: 1.5 | E6: 45 | F6: 7.8 | G6: 0 | H6: 0.05 | I6: =IF(A6="","",C6+D6+E6/60*Settings!$B$12+F6+G6)
A7: Cute Frog Sticker Pack (5) | B7: STK-5 | C7: 0.9 | D7: 0.2 | E7: 2 | F7: 0.73 | G7: 0 | H7: 0.01 | I7: =IF(A7="","",C7+D7+E7/60*Settings!$B$12+F7+G7)
A8: Linen Tote Bag | B8: TOTE-1 | C8: 5.2 | D8: 0.6 | E8: 15 | F8: 0 | G8: 3.22 | H8: 0.03 | I8: =IF(A8="","",C8+D8+E8/60*Settings!$B$12+F8+G8)
I9: =IF(A9="","",C9+D9+E9/60*Settings!$B$12+F9+G9)
I10: =IF(A10="","",C10+D10+E10/60*Settings!$B$12+F10+G10)
I11: =IF(A11="","",C11+D11+E11/60*Settings!$B$12+F11+G11)
I12: =IF(A12="","",C12+D12+E12/60*Settings!$B$12+F12+G12)
I13: =IF(A13="","",C13+D13+E13/60*Settings!$B$12+F13+G13)
I14: =IF(A14="","",C14+D14+E14/60*Settings!$B$12+F14+G14)
I15: =IF(A15="","",C15+D15+E15/60*Settings!$B$12+F15+G15)
I16: =IF(A16="","",C16+D16+E16/60*Settings!$B$12+F16+G16)
I17: =IF(A17="","",C17+D17+E17/60*Settings!$B$12+F17+G17)
I18: =IF(A18="","",C18+D18+E18/60*Settings!$B$12+F18+G18)
I19: =IF(A19="","",C19+D19+E19/60*Settings!$B$12+F19+G19)
I20: =IF(A20="","",C20+D20+E20/60*Settings!$B$12+F20+G20)
... I204: =IF(A204="","",C204+D204+E204/60*Settings!$B$12+F204+G204)

Sheet Etsy Import
A1: Sale Date | B1: Item Name | C1: Buyer | D1: Quantity | E1: Price | F1: Coupon Code | G1: Coupon Details | H1: Discount Amount | I1: Shipping Discount | J1: Order Shipping | K1: Order Sales Tax | L1: Item Total | M1: Currency | N1: Transaction ID | O1: Listing ID | P1: Order ID | Q1: SKU
A2: 10/01/26 | B2: Lavender Soy Candle 8oz | C2: A | D2: 2 | E2: 18 | H2: 0 | I2: 0 | J2: 0 | K2: 0 | L2: 36 | M2: USD | N2: 1 | O2: 11 | P2: 9001 | Q2: CAN-LAV
A3: 10/02/26 | B3: Handmade Ceramic Mug - Speckled | C3: B | D3: 1 | E3: 28 | H3: 0 | I3: 0 | J3: 0 | K3: 0 | L3: 28 | M3: USD | N3: 2 | O3: 12 | P3: 9002 | Q3: MUG-01
A4: 10/03/26 | B4: Cute Frog Sticker Pack (5) | C4: C | D4: 3 | E4: 6 | H4: 0 | I4: 0 | J4: 1.5 | K4: 0 | L4: 18 | M4: USD | N4: 3 | O4: 13 | P4: 9003 | Q4: STK-5
A5: 10/03/26 | B5: Lavender Soy Candle 8oz | C5: C | D5: 1 | E5: 18 | F5: SAVE10 | H5: 2.4 | I5: 0 | J5: 1.5 | K5: 0 | L5: 18 | M5: USD | N5: 4 | O5: 11 | P5: 9003 | Q5: CAN-LAV
A6: 10/05/26 | B6: Handmade Ceramic Mug - Speckled | C6: D | D6: 2 | E6: 28 | H6: 0 | I6: 0 | J6: 0 | K6: 0 | L6: 56 | M6: USD | N6: 5 | O6: 12 | P6: 9004 | Q6: MUG-01
A7: 10/06/26 | B7: Pressed Flower Bookmark | C7: E | D7: 1 | E7: 9 | H7: 0 | I7: 0 | J7: 0 | K7: 0 | L7: 9 | M7: USD | N7: 6 | O7: 14 | P7: 9005

Sheet Shopify Import
A1: Name | B1: Email | C1: Financial Status | D1: Paid at | E1: Currency | F1: Subtotal | G1: Shipping | H1: Taxes | I1: Total | J1: Discount Code | K1: Discount Amount | L1: Lineitem quantity | M1: Lineitem name | N1: Lineitem price | O1: Lineitem sku
A2: #1001 | B2: x@y.z | C2: paid | D2: 2026-10-02 10:00:00 -0400 | E2: USD | F2: 48 | G2: 5 | H2: 0 | I2: 53 | K2: 0 | L2: 2 | M2: Lavender Soy Candle 8oz | N2: 20 | O2: CAN-LAV
A3: #1001 | L3: 1 | M3: Cute Frog Sticker Pack (5) | N3: 8 | O3: STK-5
A4: #1002 | B4: z@y.x | C4: paid | D4: 2026-10-04 12:00:00 -0400 | E4: USD | F4: 30 | G4: 0 | H4: 0 | I4: 27 | J4: WELCOME | K4: 3 | L4: 1 | M4: Handmade Ceramic Mug - Speckled | N4: 30 | O4: MUG-01

Sheet Manual Sales
A1: Date | B1: Platform | C1: Product name | D1: SKU | E1: Qty | F1: Unit price | G1: Shipping charged | H1: Discount | I1: Order ID | J1: Product (as sold) | K1: SKU | L1: Order ID | M1: Qty | N1: Unit price | O1: Item revenue | P1: Items in order | Q1: Shipping charged | R1: Discount | S1: Gross sales | T1: Product row | U1: Matched product | V1: Platform fees | W1: Product costs | X1: Return allowance | Y1: Net profit
A2: 10/04/26 | B2: Amazon | C2: Linen Tote Bag | D2: TOTE-1 | E2: 3 | F2: 24 | G2: 0 | H2: 0 | I2: AMZ-1 | J2: =IFERROR(IF(C2="","",C2)&"","") | K2: =IFERROR(IF(D2="","",D2)&"","") | L2: =IFERROR(IF(I2="","",I2)&"","") | M2: =IF(J2="","",IFERROR(VALUE(SUBSTITUTE(SUBSTITUTE(IF(E2="","",E2)&"","$",""),",","")),0)) | N2: =IF(J2="","",IFERROR(VALUE(SUBSTITUTE(SUBSTITUTE(IF(F2="","",F2)&"","$",""),",","")),0)) | O2: =IF(J2="","",M2*N2) | P2: =IF(J2="","",IF(L2="",1,COUNTIF($L$2:$L$1501,L2))) | Q2: =IF(J2="","",IFERROR(VALUE(SUBSTITUTE(SUBSTITUTE(IF(G2="","",G2)&"","$",""),",","")),0)/IF("No"="Yes",P2,1)) | R2: =IF(J2="","",IFERROR(VALUE(SUBSTITUTE(SUBSTITUTE(IF(H2="","",H2)&"","$",""),",","")),0)/IF("No"="Yes",P2,1)) | S2: =IF(J2="","",O2+Q2-R2) | T2: =IF(J2="","",IFERROR(IF(K2="",NA(),MATCH(K2,Products!$B$5:$B$204,0)),IFERROR(MATCH(J2,Products!$A$5:$A$204,0),""))) | U2: =IF(J2="","",IF(T2="","⚠ not in Products",INDEX(Products!$A$5:$A$204,T2))) | V2: =IF(J2="","",S2*(IFERROR(INDEX(Settings!$B$5:$B$9,MATCH($B2,Settings!$A$5:$A$9,0)),0)+IFERROR(INDEX(Settings!$E$5:$E$9,MATCH($B2,Settings!$A$5:$A$9,0)),0)+IFERROR(INDEX(Settings!$G$5:$G$9,MATCH($B2,Settings!$A$5:$A$9,0)),0))+(IFERROR(INDEX(Settings!$C$5:$C$9,MATCH($B2,Settings!$A$5:$A$9,0)),0)+IFERROR(INDEX(Settings!$F$5:$F$9,MATCH($B2,Settings!$A$5:$A$9,0)),0))/P2+IFERROR(INDEX(Settings!$D$5:$D$9,MATCH($B2,Settings!$A$5:$A$9,0)),0)*M2) | W2: =IF(J2="","",IF(T2="",0,M2*INDEX(Products!$I$5:$I$204,T2))) | X2: =IF(J2="","",IF(T2="",0,S2*INDEX(Products!$H$5:$H$204,T2))) | Y2: =IF(J2="","",S2-V2-W2-X2)
A3: 10/05/26 | B3: Other | C3: Lavender Soy Candle 8oz | E3: 4 | F3: 15 | G3: 0 | H3: 0 | I3: MKT-1 | J3: =IFERROR(IF(C3="","",C3)&"","") | K3: =IFERROR(IF(D3="","",D3)&"","") | L3: =IFERROR(IF(I3="","",I3)&"","") | M3: =IF(J3="","",IFERROR(VALUE(SUBSTITUTE(SUBSTITUTE(IF(E3="","",E3)&"","$",""),",","")),0)) | N3: =IF(J3="","",IFERROR(VALUE(SUBSTITUTE(SUBSTITUTE(IF(F3="","",F3)&"","$",""),",","")),0)) | O3: =IF(J3="","",M3*N3) | P3: =IF(J3="","",IF(L3="",1,COUNTIF($L$2:$L$1501,L3))) | Q3: =IF(J3="","",IFERROR(VALUE(SUBSTITUTE(SUBSTITUTE(IF(G3="","",G3)&"","$",""),",","")),0)/IF("No"="Yes",P3,1)) | R3: =IF(J3="","",IFERROR(VALUE(SUBSTITUTE(SUBSTITUTE(IF(H3="","",H3)&"","$",""),",","")),0)/IF("No"="Yes",P3,1)) | S3: =IF(J3="","",O3+Q3-R3) | T3: =IF(J3="","",IFERROR(IF(K3="",NA(),MATCH(K3,Products!$B$5:$B$204,0)),IFERROR(MATCH(J3,Products!$A$5:$A$204,0),""))) | U3: =IF(J3="","",IF(T3="","⚠ not in Products",INDEX(Products!$A$5:$A$204,T3))) | V3: =IF(J3="","",S3*(IFERROR(INDEX(Settings!$B$5:$B$9,MATCH($B3,Settings!$A$5:$A$9,0)),0)+IFERROR(INDEX(Settings!$E$5:$E$9,MATCH($B3,Settings!$A$5:$A$9,0)),0)+IFERROR(INDEX(Settings!$G$5:$G$9,MATCH($B3,Settings!$A$5:$A$9,0)),0))+(IFERROR(INDEX(Settings!$C$5:$C$9,MATCH($B3,Settings!$A$5:$A$9,0)),0)+IFERROR(INDEX(Settings!$F$5:$F$9,MATCH($B3,Settings!$A$5:$A$9,0)),0))/P3+IFERROR(INDEX(Settings!$D$5:$D$9,MATCH($B3,Settings!$A$5:$A$9,0)),0)*M3) | W3: =IF(J3="","",IF(T3="",0,M3*INDEX(Products!$I$5:$I$204,T3))) | X3: =IF(J3="","",IF(T3="",0,S3*INDEX(Products!$H$5:$H$204,T3))) | Y3: =IF(J3="","",S3-V3-W3-X3)
J4: =IFERROR(IF(C4="","",C4)&"","") | K4: =IFERROR(IF(D4="","",D4)&"","") | L4: =IFERROR(IF(I4="","",I4)&"","") | M4: =IF(J4="","",IFERROR(VALUE(SUBSTITUTE(SUBSTITUTE(IF(E4="","",E4)&"","$",""),",","")),0)) | N4: =IF(J4="","",IFERROR(VALUE(SUBSTITUTE(SUBSTITUTE(IF(F4="","",F4)&"","$",""),",","")),0)) | O4: =IF(J4="","",M4*N4) | P4: =IF(J4="","",IF(L4="",1,COUNTIF($L$2:$L$1501,L4))) | Q4: =IF(J4="","",IFERROR(VALUE(SUBSTITUTE(SUBSTITUTE(IF(G4="","",G4)&"","$",""),",","")),0)/IF("No"="Yes",P4,1)) | R4: =IF(J4="","",IFERROR(VALUE(SUBSTITUTE(SUBSTITUTE(IF(H4="","",H4)&"","$",""),",","")),0)/IF("No"="Yes",P4,1)) | S4: =IF(J4="","",O4+Q4-R4) | T4: =IF(J4="","",IFERROR(IF(K4="",NA(),MATCH(K4,Products!$B$5:$B$204,0)),IFERROR(MATCH(J4,Products!$A$5:$A$204,0),""))) | U4: =IF(J4="","",IF(T4="","⚠ not in Products",INDEX(Products!$A$5:$A$204,T4))) | V4: =IF(J4="","",S4*(IFERROR(INDEX(Settings!$B$5:$B$9,MATCH($B4,Settings!$A$5:$A$9,0)),0)+IFERROR(INDEX(Settings!$E$5:$E$9,MATCH($B4,Settings!$A$5:$A$9,0)),0)+IFERROR(INDEX(Settings!$G$5:$G$9,MATCH($B4,Settings!$A$5:$A$9,0)),0))+(IFERROR(INDEX(Settings!$C$5:$C$9,MATCH($B4,Settings!$A$5:$A$9,0)),0)+IFERROR(INDEX(Settings!$F$5:$F$9,MATCH($B4,Settings!$A$5:$A$9,0)),0))/P4+IFERROR(INDEX(Settings!$D$5:$D$9,MATCH($B4,Settings!$A$5:$A$9,0)),0)*M4) | W4: =IF(J4="","",IF(T4="",0,M4*INDEX(Products!$I$5:$I$204,T4))) | X4: =IF(J4="","",IF(T4="",0,S4*INDEX(Products!$H$5:$H$204,T4))) | Y4: =IF(J4="","",S4-V4-W4-X4)
J5: =IFERROR(IF(C5="","",C5)&"","") | K5: =IFERROR(IF(D5="","",D5)&"","") | L5: =IFERROR(IF(I5="","",I5)&"","") | M5: =IF(J5="","",IFERROR(VALUE(SUBSTITUTE(SUBSTITUTE(IF(E5="","",E5)&"","$",""),",","")),0)) | N5: =IF(J5="","",IFERROR(VALUE(SUBSTITUTE(SUBSTITUTE(IF(F5="","",F5)&"","$",""),",","")),0)) | O5: =IF(J5="","",M5*N5) | P5: =IF(J5="","",IF(L5="",1,COUNTIF($L$2:$L$1501,L5))) | Q5: =IF(J5="","",IFERROR(VALUE(SUBSTITUTE(SUBSTITUTE(IF(G5="","",G5)&"","$",""),",","")),0)/IF("No"="Yes",P5,1)) | R5: =IF(J5="","",IFERROR(VALUE(SUBSTITUTE(SUBSTITUTE(IF(H5="","",H5)&"","$",""),",","")),0)/IF("No"="Yes",P5,1)) | S5: =IF(J5="","",O5+Q5-R5) | T5: =IF(J5="","",IFERROR(IF(K5="",NA(),MATCH(K5,Products!$B$5:$B$204,0)),IFERROR(MATCH(J5,Products!$A$5:$A$204,0),""))) | U5: =IF(J5="","",IF(T5="","⚠ not in Products",INDEX(Products!$A$5:$A$204,T5))) | V5: =IF(J5="","",S5*(IFERROR(INDEX(Settings!$B$5:$B$9,MATCH($B5,Settings!$A$5:$A$9,0)),0)+IFERROR(INDEX(Settings!$E$5:$E$9,MATCH($B5,Settings!$A$5:$A$9,0)),0)+IFERROR(INDEX(Settings!$G$5:$G$9,MATCH($B5,Settings!$A$5:$A$9,0)),0))+(IFERROR(INDEX(Settings!$C$5:$C$9,MATCH($B5,Settings!$A$5:$A$9,0)),0)+IFERROR(INDEX(Settings!$F$5:$F$9,MATCH($B5,Settings!$A$5:$A$9,0)),0))/P5+IFERROR(INDEX(Settings!$D$5:$D$9,MATCH($B5,Settings!$A$5:$A$9,0)),0)*M5) | W5: =IF(J5="","",IF(T5="",0,M5*INDEX(Products!$I$5:$I$204,T5))) | X5: =IF(J5="","",IF(T5="",0,S5*INDEX(Products!$H$5:$H$204,T5))) | Y5: =IF(J5="","",S5-V5-W5-X5)
J6: =IFERROR(IF(C6="","",C6)&"","") | K6: =IFERROR(IF(D6="","",D6)&"","") | L6: =IFERROR(IF(I6="","",I6)&"","") | M6: =IF(J6="","",IFERROR(VALUE(SUBSTITUTE(SUBSTITUTE(IF(E6="","",E6)&"","$",""),",","")),0)) | N6: =IF(J6="","",IFERROR(VALUE(SUBSTITUTE(SUBSTITUTE(IF(F6="","",F6)&"","$",""),",","")),0)) | O6: =IF(J6="","",M6*N6) | P6: =IF(J6="","",IF(L6="",1,COUNTIF($L$2:$L$1501,L6))) | Q6: =IF(J6="","",IFERROR(VALUE(SUBSTITUTE(SUBSTITUTE(IF(G6="","",G6)&"","$",""),",","")),0)/IF("No"="Yes",P6,1)) | R6: =IF(J6="","",IFERROR(VALUE(SUBSTITUTE(SUBSTITUTE(IF(H6="","",H6)&"","$",""),",","")),0)/IF("No"="Yes",P6,1)) | S6: =IF(J6="","",O6+Q6-R6) | T6: =IF(J6="","",IFERROR(IF(K6="",NA(),MATCH(K6,Products!$B$5:$B$204,0)),IFERROR(MATCH(J6,Products!$A$5:$A$204,0),""))) | U6: =IF(J6="","",IF(T6="","⚠ not in Products",INDEX(Products!$A$5:$A$204,T6))) | V6: =IF(J6="","",S6*(IFERROR(INDEX(Settings!$B$5:$B$9,MATCH($B6,Settings!$A$5:$A$9,0)),0)+IFERROR(INDEX(Settings!$E$5:$E$9,MATCH($B6,Settings!$A$5:$A$9,0)),0)+IFERROR(INDEX(Settings!$G$5:$G$9,MATCH($B6,Settings!$A$5:$A$9,0)),0))+(IFERROR(INDEX(Settings!$C$5:$C$9,MATCH($B6,Settings!$A$5:$A$9,0)),0)+IFERROR(INDEX(Settings!$F$5:$F$9,MATCH($B6,Settings!$A$5:$A$9,0)),0))/P6+IFERROR(INDEX(Settings!$D$5:$D$9,MATCH($B6,Settings!$A$5:$A$9,0)),0)*M6) | W6: =IF(J6="","",IF(T6="",0,M6*INDEX(Products!$I$5:$I$204,T6))) | X6: =IF(J6="","",IF(T6="",0,S6*INDEX(Products!$H$5:$H$204,T6))) | Y6: =IF(J6="","",S6-V6-W6-X6)
J7: =IFERROR(IF(C7="","",C7)&"","") | K7: =IFERROR(IF(D7="","",D7)&"","") | L7: =IFERROR(IF(I7="","",I7)&"","") | M7: =IF(J7="","",IFERROR(VALUE(SUBSTITUTE(SUBSTITUTE(IF(E7="","",E7)&"","$",""),",","")),0)) | N7: =IF(J7="","",IFERROR(VALUE(SUBSTITUTE(SUBSTITUTE(IF(F7="","",F7)&"","$",""),",","")),0)) | O7: =IF(J7="","",M7*N7) | P7: =IF(J7="","",IF(L7="",1,COUNTIF($L$2:$L$1501,L7))) | Q7: =IF(J7="","",IFERROR(VALUE(SUBSTITUTE(SUBSTITUTE(IF(G7="","",G7)&"","$",""),",","")),0)/IF("No"="Yes",P7,1)) | R7: =IF(J7="","",IFERROR(VALUE(SUBSTITUTE(SUBSTITUTE(IF(H7="","",H7)&"","$",""),",","")),0)/IF("No"="Yes",P7,1)) | S7: =IF(J7="","",O7+Q7-R7) | T7: =IF(J7="","",IFERROR(IF(K7="",NA(),MATCH(K7,Products!$B$5:$B$204,0)),IFERROR(MATCH(J7,Products!$A$5:$A$204,0),""))) | U7: =IF(J7="","",IF(T7="","⚠ not in Products",INDEX(Products!$A$5:$A$204,T7))) | V7: =IF(J7="","",S7*(IFERROR(INDEX(Settings!$B$5:$B$9,MATCH($B7,Settings!$A$5:$A$9,0)),0)+IFERROR(INDEX(Settings!$E$5:$E$9,MATCH($B7,Settings!$A$5:$A$9,0)),0)+IFERROR(INDEX(Settings!$G$5:$G$9,MATCH($B7,Settings!$A$5:$A$9,0)),0))+(IFERROR(INDEX(Settings!$C$5:$C$9,MATCH($B7,Settings!$A$5:$A$9,0)),0)+IFERROR(INDEX(Settings!$F$5:$F$9,MATCH($B7,Settings!$A$5:$A$9,0)),0))/P7+IFERROR(INDEX(Settings!$D$5:$D$9,MATCH($B7,Settings!$A$5:$A$9,0)),0)*M7) | W7: =IF(J7="","",IF(T7="",0,M7*INDEX(Products!$I$5:$I$204,T7))) | X7: =IF(J7="","",IF(T7="",0,S7*INDEX(Products!$H$5:$H$204,T7))) | Y7: =IF(J7="","",S7-V7-W7-X7)
J8: =IFERROR(IF(C8="","",C8)&"","") | K8: =IFERROR(IF(D8="","",D8)&"","") | L8: =IFERROR(IF(I8="","",I8)&"","") | M8: =IF(J8="","",IFERROR(VALUE(SUBSTITUTE(SUBSTITUTE(IF(E8="","",E8)&"","$",""),",","")),0)) | N8: =IF(J8="","",IFERROR(VALUE(SUBSTITUTE(SUBSTITUTE(IF(F8="","",F8)&"","$",""),",","")),0)) | O8: =IF(J8="","",M8*N8) | P8: =IF(J8="","",IF(L8="",1,COUNTIF($L$2:$L$1501,L8))) | Q8: =IF(J8="","",IFERROR(VALUE(SUBSTITUTE(SUBSTITUTE(IF(G8="","",G8)&"","$",""),",","")),0)/IF("No"="Yes",P8,1)) | R8: =IF(J8="","",IFERROR(VALUE(SUBSTITUTE(SUBSTITUTE(IF(H8="","",H8)&"","$",""),",","")),0)/IF("No"="Yes",P8,1)) | S8: =IF(J8="","",O8+Q8-R8) | T8: =IF(J8="","",IFERROR(IF(K8="",NA(),MATCH(K8,Products!$B$5:$B$204,0)),IFERROR(MATCH(J8,Products!$A$5:$A$204,0),""))) | U8: =IF(J8="","",IF(T8="","⚠ not in Products",INDEX(Products!$A$5:$A$204,T8))) | V8: =IF(J8="","",S8*(IFERROR(INDEX(Settings!$B$5:$B$9,MATCH($B8,Settings!$A$5:$A$9,0)),0)+IFERROR(INDEX(Settings!$E$5:$E$9,MATCH($B8,Settings!$A$5:$A$9,0)),0)+IFERROR(INDEX(Settings!$G$5:$G$9,MATCH($B8,Settings!$A$5:$A$9,0)),0))+(IFERROR(INDEX(Settings!$C$5:$C$9,MATCH($B8,Settings!$A$5:$A$9,0)),0)+IFERROR(INDEX(Settings!$F$5:$F$9,MATCH($B8,Settings!$A$5:$A$9,0)),0))/P8+IFERROR(INDEX(Settings!$D$5:$D$9,MATCH($B8,Settings!$A$5:$A$9,0)),0)*M8) | W8: =IF(J8="","",IF(T8="",0,M8*INDEX(Products!$I$5:$I$204,T8))) | X8: =IF(J8="","",IF(T8="",0,S8*INDEX(Products!$H$5:$H$204,T8))) | Y8: =IF(J8="","",S8-V8-W8-X8)
J9: =IFERROR(IF(C9="","",C9)&"","") | K9: =IFERROR(IF(D9="","",D9)&"","") | L9: =IFERROR(IF(I9="","",I9)&"","") | M9: =IF(J9="","",IFERROR(VALUE(SUBSTITUTE(SUBSTITUTE(IF(E9="","",E9)&"","$",""),",","")),0)) | N9: =IF(J9="","",IFERROR(VALUE(SUBSTITUTE(SUBSTITUTE(IF(F9="","",F9)&"","$",""),",","")),0)) | O9: =IF(J9="","",M9*N9) | P9: =IF(J9="","",IF(L9="",1,COUNTIF($L$2:$L$1501,L9))) | Q9: =IF(J9="","",IFERROR(VALUE(SUBSTITUTE(SUBSTITUTE(IF(G9="","",G9)&"","$",""),",","")),0)/IF("No"="Yes",P9,1)) | R9: =IF(J9="","",IFERROR(VALUE(SUBSTITUTE(SUBSTITUTE(IF(H9="","",H9)&"","$",""),",","")),0)/IF("No"="Yes",P9,1)) | S9: =IF(J9="","",O9+Q9-R9) | T9: =IF(J9="","",IFERROR(IF(K9="",NA(),MATCH(K9,Products!$B$5:$B$204,0)),IFERROR(MATCH(J9,Products!$A$5:$A$204,0),""))) | U9: =IF(J9="","",IF(T9="","⚠ not in Products",INDEX(Products!$A$5:$A$204,T9))) | V9: =IF(J9="","",S9*(IFERROR(INDEX(Settings!$B$5:$B$9,MATCH($B9,Settings!$A$5:$A$9,0)),0)+IFERROR(INDEX(Settings!$E$5:$E$9,MATCH($B9,Settings!$A$5:$A$9,0)),0)+IFERROR(INDEX(Settings!$G$5:$G$9,MATCH($B9,Settings!$A$5:$A$9,0)),0))+(IFERROR(INDEX(Settings!$C$5:$C$9,MATCH($B9,Settings!$A$5:$A$9,0)),0)+IFERROR(INDEX(Settings!$F$5:$F$9,MATCH($B9,Settings!$A$5:$A$9,0)),0))/P9+IFERROR(INDEX(Settings!$D$5:$D$9,MATCH($B9,Settings!$A$5:$A$9,0)),0)*M9) | W9: =IF(J9="","",IF(T9="",0,M9*INDEX(Products!$I$5:$I$204,T9))) | X9: =IF(J9="","",IF(T9="",0,S9*INDEX(Products!$H$5:$H$204,T9))) | Y9: =IF(J9="","",S9-V9-W9-X9)
J10: =IFERROR(IF(C10="","",C10)&"","") | K10: =IFERROR(IF(D10="","",D10)&"","") | L10: =IFERROR(IF(I10="","",I10)&"","") | M10: =IF(J10="","",IFERROR(VALUE(SUBSTITUTE(SUBSTITUTE(IF(E10="","",E10)&"","$",""),",","")),0)) | N10: =IF(J10="","",IFERROR(VALUE(SUBSTITUTE(SUBSTITUTE(IF(F10="","",F10)&"","$",""),",","")),0)) | O10: =IF(J10="","",M10*N10) | P10: =IF(J10="","",IF(L10="",1,COUNTIF($L$2:$L$1501,L10))) | Q10: =IF(J10="","",IFERROR(VALUE(SUBSTITUTE(SUBSTITUTE(IF(G10="","",G10)&"","$",""),",","")),0)/IF("No"="Yes",P10,1)) | R10: =IF(J10="","",IFERROR(VALUE(SUBSTITUTE(SUBSTITUTE(IF(H10="","",H10)&"","$",""),",","")),0)/IF("No"="Yes",P10,1)) | S10: =IF(J10="","",O10+Q10-R10) | T10: =IF(J10="","",IFERROR(IF(K10="",NA(),MATCH(K10,Products!$B$5:$B$204,0)),IFERROR(MATCH(J10,Products!$A$5:$A$204,0),""))) | U10: =IF(J10="","",IF(T10="","⚠ not in Products",INDEX(Products!$A$5:$A$204,T10))) | V10: =IF(J10="","",S10*(IFERROR(INDEX(Settings!$B$5:$B$9,MATCH($B10,Settings!$A$5:$A$9,0)),0)+IFERROR(INDEX(Settings!$E$5:$E$9,MATCH($B10,Settings!$A$5:$A$9,0)),0)+IFERROR(INDEX(Settings!$G$5:$G$9,MATCH($B10,Settings!$A$5:$A$9,0)),0))+(IFERROR(INDEX(Settings!$C$5:$C$9,MATCH($B10,Settings!$A$5:$A$9,0)),0)+IFERROR(INDEX(Settings!$F$5:$F$9,MATCH($B10,Settings!$A$5:$A$9,0)),0))/P10+IFERROR(INDEX(Settings!$D$5:$D$9,MATCH($B10,Settings!$A$5:$A$9,0)),0)*M10) | W10: =IF(J10="","",IF(T10="",0,M10*INDEX(Products!$I$5:$I$204,T10))) | X10: =IF(J10="","",IF(T10="",0,S10*INDEX(Products!$H$5:$H$204,T10))) | Y10: =IF(J10="","",S10-V10-W10-X10)
J11: =IFERROR(IF(C11="","",C11)&"","") | K11: =IFERROR(IF(D11="","",D11)&"","") | L11: =IFERROR(IF(I11="","",I11)&"","") | M11: =IF(J11="","",IFERROR(VALUE(SUBSTITUTE(SUBSTITUTE(IF(E11="","",E11)&"","$",""),",","")),0)) | N11: =IF(J11="","",IFERROR(VALUE(SUBSTITUTE(SUBSTITUTE(IF(F11="","",F11)&"","$",""),",","")),0)) | O11: =IF(J11="","",M11*N11) | P11: =IF(J11="","",IF(L11="",1,COUNTIF($L$2:$L$1501,L11))) | Q11: =IF(J11="","",IFERROR(VALUE(SUBSTITUTE(SUBSTITUTE(IF(G11="","",G11)&"","$",""),",","")),0)/IF("No"="Yes",P11,1)) | R11: =IF(J11="","",IFERROR(VALUE(SUBSTITUTE(SUBSTITUTE(IF(H11="","",H11)&"","$",""),",","")),0)/IF("No"="Yes",P11,1)) | S11: =IF(J11="","",O11+Q11-R11) | T11: =IF(J11="","",IFERROR(IF(K11="",NA(),MATCH(K11,Products!$B$5:$B$204,0)),IFERROR(MATCH(J11,Products!$A$5:$A$204,0),""))) | U11: =IF(J11="","",IF(T11="","⚠ not in Products",INDEX(Products!$A$5:$A$204,T11))) | V11: =IF(J11="","",S11*(IFERROR(INDEX(Settings!$B$5:$B$9,MATCH($B11,Settings!$A$5:$A$9,0)),0)+IFERROR(INDEX(Settings!$E$5:$E$9,MATCH($B11,Settings!$A$5:$A$9,0)),0)+IFERROR(INDEX(Settings!$G$5:$G$9,MATCH($B11,Settings!$A$5:$A$9,0)),0))+(IFERROR(INDEX(Settings!$C$5:$C$9,MATCH($B11,Settings!$A$5:$A$9,0)),0)+IFERROR(INDEX(Settings!$F$5:$F$9,MATCH($B11,Settings!$A$5:$A$9,0)),0))/P11+IFERROR(INDEX(Settings!$D$5:$D$9,MATCH($B11,Settings!$A$5:$A$9,0)),0)*M11) | W11: =IF(J11="","",IF(T11="",0,M11*INDEX(Products!$I$5:$I$204,T11))) | X11: =IF(J11="","",IF(T11="",0,S11*INDEX(Products!$H$5:$H$204,T11))) | Y11: =IF(J11="","",S11-V11-W11-X11)
J12: =IFERROR(IF(C12="","",C12)&"","") | K12: =IFERROR(IF(D12="","",D12)&"","") | L12: =IFERROR(IF(I12="","",I12)&"","") | M12: =IF(J12="","",IFERROR(VALUE(SUBSTITUTE(SUBSTITUTE(IF(E12="","",E12)&"","$",""),",","")),0)) | N12: =IF(J12="","",IFERROR(VALUE(SUBSTITUTE(SUBSTITUTE(IF(F12="","",F12)&"","$",""),",","")),0)) | O12: =IF(J12="","",M12*N12) | P12: =IF(J12="","",IF(L12="",1,COUNTIF($L$2:$L$1501,L12))) | Q12: =IF(J12="","",IFERROR(VALUE(SUBSTITUTE(SUBSTITUTE(IF(G12="","",G12)&"","$",""),",","")),0)/IF("No"="Yes",P12,1)) | R12: =IF(J12="","",IFERROR(VALUE(SUBSTITUTE(SUBSTITUTE(IF(H12="","",H12)&"","$",""),",","")),0)/IF("No"="Yes",P12,1)) | S12: =IF(J12="","",O12+Q12-R12) | T12: =IF(J12="","",IFERROR(IF(K12="",NA(),MATCH(K12,Products!$B$5:$B$204,0)),IFERROR(MATCH(J12,Products!$A$5:$A$204,0),""))) | U12: =IF(J12="","",IF(T12="","⚠ not in Products",INDEX(Products!$A$5:$A$204,T12))) | V12: =IF(J12="","",S12*(IFERROR(INDEX(Settings!$B$5:$B$9,MATCH($B12,Settings!$A$5:$A$9,0)),0)+IFERROR(INDEX(Settings!$E$5:$E$9,MATCH($B12,Settings!$A$5:$A$9,0)),0)+IFERROR(INDEX(Settings!$G$5:$G$9,MATCH($B12,Settings!$A$5:$A$9,0)),0))+(IFERROR(INDEX(Settings!$C$5:$C$9,MATCH($B12,Settings!$A$5:$A$9,0)),0)+IFERROR(INDEX(Settings!$F$5:$F$9,MATCH($B12,Settings!$A$5:$A$9,0)),0))/P12+IFERROR(INDEX(Settings!$D$5:$D$9,MATCH($B12,Settings!$A$5:$A$9,0)),0)*M12) | W12: =IF(J12="","",IF(T12="",0,M12*INDEX(Products!$I$5:$I$204,T12))) | X12: =IF(J12="","",IF(T12="",0,S12*INDEX(Products!$H$5:$H$204,T12))) | Y12: =IF(J12="","",S12-V12-W12-X12)
J13: =IFERROR(IF(C13="","",C13)&"","") | K13: =IFERROR(IF(D13="","",D13)&"","") | L13: =IFERROR(IF(I13="","",I13)&"","") | M13: =IF(J13="","",IFERROR(VALUE(SUBSTITUTE(SUBSTITUTE(IF(E13="","",E13)&"","$",""),",","")),0)) | N13: =IF(J13="","",IFERROR(VALUE(SUBSTITUTE(SUBSTITUTE(IF(F13="","",F13)&"","$",""),",","")),0)) | O13: =IF(J13="","",M13*N13) | P13: =IF(J13="","",IF(L13="",1,COUNTIF($L$2:$L$1501,L13))) | Q13: =IF(J13="","",IFERROR(VALUE(SUBSTITUTE(SUBSTITUTE(IF(G13="","",G13)&"","$",""),",","")),0)/IF("No"="Yes",P13,1)) | R13: =IF(J13="","",IFERROR(VALUE(SUBSTITUTE(SUBSTITUTE(IF(H13="","",H13)&"","$",""),",","")),0)/IF("No"="Yes",P13,1)) | S13: =IF(J13="","",O13+Q13-R13) | T13: =IF(J13="","",IFERROR(IF(K13="",NA(),MATCH(K13,Products!$B$5:$B$204,0)),IFERROR(MATCH(J13,Products!$A$5:$A$204,0),""))) | U13: =IF(J13="","",IF(T13="","⚠ not in Products",INDEX(Products!$A$5:$A$204,T13))) | V13: =IF(J13="","",S13*(IFERROR(INDEX(Settings!$B$5:$B$9,MATCH($B13,Settings!$A$5:$A$9,0)),0)+IFERROR(INDEX(Settings!$E$5:$E$9,MATCH($B13,Settings!$A$5:$A$9,0)),0)+IFERROR(INDEX(Settings!$G$5:$G$9,MATCH($B13,Settings!$A$5:$A$9,0)),0))+(IFERROR(INDEX(Settings!$C$5:$C$9,MATCH($B13,Settings!$A$5:$A$9,0)),0)+IFERROR(INDEX(Settings!$F$5:$F$9,MATCH($B13,Settings!$A$5:$A$9,0)),0))/P13+IFERROR(INDEX(Settings!$D$5:$D$9,MATCH($B13,Settings!$A$5:$A$9,0)),0)*M13) | W13: =IF(J13="","",IF(T13="",0,M13*INDEX(Products!$I$5:$I$204,T13))) | X13: =IF(J13="","",IF(T13="",0,S13*INDEX(Products!$H$5:$H$204,T13))) | Y13: =IF(J13="","",S13-V13-W13-X13)
J14: =IFERROR(IF(C14="","",C14)&"","") | K14: =IFERROR(IF(D14="","",D14)&"","") | L14: =IFERROR(IF(I14="","",I14)&"","") | M14: =IF(J14="","",IFERROR(VALUE(SUBSTITUTE(SUBSTITUTE(IF(E14="","",E14)&"","$",""),",","")),0)) | N14: =IF(J14="","",IFERROR(VALUE(SUBSTITUTE(SUBSTITUTE(IF(F14="","",F14)&"","$",""),",","")),0)) | O14: =IF(J14="","",M14*N14) | P14: =IF(J14="","",IF(L14="",1,COUNTIF($L$2:$L$1501,L14))) | Q14: =IF(J14="","",IFERROR(VALUE(SUBSTITUTE(SUBSTITUTE(IF(G14="","",G14)&"","$",""),",","")),0)/IF("No"="Yes",P14,1)) | R14: =IF(J14="","",IFERROR(VALUE(SUBSTITUTE(SUBSTITUTE(IF(H14="","",H14)&"","$",""),",","")),0)/IF("No"="Yes",P14,1)) | S14: =IF(J14="","",O14+Q14-R14) | T14: =IF(J14="","",IFERROR(IF(K14="",NA(),MATCH(K14,Products!$B$5:$B$204,0)),IFERROR(MATCH(J14,Products!$A$5:$A$204,0),""))) | U14: =IF(J14="","",IF(T14="","⚠ not in Products",INDEX(Products!$A$5:$A$204,T14))) | V14: =IF(J14="","",S14*(IFERROR(INDEX(Settings!$B$5:$B$9,MATCH($B14,Settings!$A$5:$A$9,0)),0)+IFERROR(INDEX(Settings!$E$5:$E$9,MATCH($B14,Settings!$A$5:$A$9,0)),0)+IFERROR(INDEX(Settings!$G$5:$G$9,MATCH($B14,Settings!$A$5:$A$9,0)),0))+(IFERROR(INDEX(Settings!$C$5:$C$9,MATCH($B14,Settings!$A$5:$A$9,0)),0)+IFERROR(INDEX(Settings!$F$5:$F$9,MATCH($B14,Settings!$A$5:$A$9,0)),0))/P14+IFERROR(INDEX(Settings!$D$5:$D$9,MATCH($B14,Settings!$A$5:$A$9,0)),0)*M14) | W14: =IF(J14="","",IF(T14="",0,M14*INDEX(Products!$I$5:$I$204,T14))) | X14: =IF(J14="","",IF(T14="",0,S14*INDEX(Products!$H$5:$H$204,T14))) | Y14: =IF(J14="","",S14-V14-W14-X14)
J15: =IFERROR(IF(C15="","",C15)&"","") | K15: =IFERROR(IF(D15="","",D15)&"","") | L15: =IFERROR(IF(I15="","",I15)&"","") | M15: =IF(J15="","",IFERROR(VALUE(SUBSTITUTE(SUBSTITUTE(IF(E15="","",E15)&"","$",""),",","")),0)) | N15: =IF(J15="","",IFERROR(VALUE(SUBSTITUTE(SUBSTITUTE(IF(F15="","",F15)&"","$",""),",","")),0)) | O15: =IF(J15="","",M15*N15) | P15: =IF(J15="","",IF(L15="",1,COUNTIF($L$2:$L$1501,L15))) | Q15: =IF(J15="","",IFERROR(VALUE(SUBSTITUTE(SUBSTITUTE(IF(G15="","",G15)&"","$",""),",","")),0)/IF("No"="Yes",P15,1)) | R15: =IF(J15="","",IFERROR(VALUE(SUBSTITUTE(SUBSTITUTE(IF(H15="","",H15)&"","$",""),",","")),0)/IF("No"="Yes",P15,1)) | S15: =IF(J15="","",O15+Q15-R15) | T15: =IF(J15="","",IFERROR(IF(K15="",NA(),MATCH(K15,Products!$B$5:$B$204,0)),IFERROR(MATCH(J15,Products!$A$5:$A$204,0),""))) | U15: =IF(J15="","",IF(T15="","⚠ not in Products",INDEX(Products!$A$5:$A$204,T15))) | V15: =IF(J15="","",S15*(IFERROR(INDEX(Settings!$B$5:$B$9,MATCH($B15,Settings!$A$5:$A$9,0)),0)+IFERROR(INDEX(Settings!$E$5:$E$9,MATCH($B15,Settings!$A$5:$A$9,0)),0)+IFERROR(INDEX(Settings!$G$5:$G$9,MATCH($B15,Settings!$A$5:$A$9,0)),0))+(IFERROR(INDEX(Settings!$C$5:$C$9,MATCH($B15,Settings!$A$5:$A$9,0)),0)+IFERROR(INDEX(Settings!$F$5:$F$9,MATCH($B15,Settings!$A$5:$A$9,0)),0))/P15+IFERROR(INDEX(Settings!$D$5:$D$9,MATCH($B15,Settings!$A$5:$A$9,0)),0)*M15) | W15: =IF(J15="","",IF(T15="",0,M15*INDEX(Products!$I$5:$I$204,T15))) | X15: =IF(J15="","",IF(T15="",0,S15*INDEX(Products!$H$5:$H$204,T15))) | Y15: =IF(J15="","",S15-V15-W15-X15)
... J1501: =IFERROR(IF(C1501="","",C1501)&"","") | K1501: =IFERROR(IF(D1501="","",D1501)&"","") | L1501: =IFERROR(IF(I1501="","",I1501)&"","") | M1501: =IF(J1501="","",IFERROR(VALUE(SUBSTITUTE(SUBSTITUTE(IF(E1501="","",E1501)&"","$",""),",","")),0)) | N1501: =IF(J1501="","",IFERROR(VALUE(SUBSTITUTE(SUBSTITUTE(IF(F1501="","",F1501)&"","$",""),",","")),0)) | O1501: =IF(J1501="","",M1501*N1501) | P1501: =IF(J1501="","",IF(L1501="",1,COUNTIF($L$2:$L$1501,L1501))) | Q1501: =IF(J1501="","",IFERROR(VALUE(SUBSTITUTE(SUBSTITUTE(IF(G1501="","",G1501)&"","$",""),",","")),0)/IF("No"="Yes",P1501,1)) | R1501: =IF(J1501="","",IFERROR(VALUE(SUBSTITUTE(SUBSTITUTE(IF(H1501="","",H1501)&"","$",""),",","")),0)/IF("No"="Yes",P1501,1)) | S1501: =IF(J1501="","",O1501+Q1501-R1501) | T1501: =IF(J1501="","",IFERROR(IF(K1501="",NA(),MATCH(K1501,Products!$B$5:$B$204,0)),IFERROR(MATCH(J1501,Products!$A$5:$A$204,0),""))) | U1501: =IF(J1501="","",IF(T1501="","⚠ not in Products",INDEX(Products!$A$5:$A$204,T1501))) | V1501: =IF(J1501="","",S1501*(IFERROR(INDEX(Settings!$B$5:$B$9,MATCH($B1501,Settings!$A$5:$A$9,0)),0)+IFERROR(INDEX(Settings!$E$5:$E$9,MATCH($B1501,Settings!$A$5:$A$9,0)),0)+IFERROR(INDEX(Settings!$G$5:$G$9,MATCH($B1501,Settings!$A$5:$A$9,0)),0))+(IFERROR(INDEX(Settings!$C$5:$C$9,MATCH($B1501,Settings!$A$5:$A$9,0)),0)+IFERROR(INDEX(Settings!$F$5:$F$9,MATCH($B1501,Settings!$A$5:$A$9,0)),0))/P1501+IFERROR(INDEX(Settings!$D$5:$D$9,MATCH($B1501,Settings!$A$5:$A$9,0)),0)*M1501) | W1501: =IF(J1501="","",IF(T1501="",0,M1501*INDEX(Products!$I$5:$I$204,T1501))) | X1501: =IF(J1501="","",IF(T1501="",0,S1501*INDEX(Products!$H$5:$H$204,T1501))) | Y1501: =IF(J1501="","",S1501-V1501-W1501-X1501)

Sheet Etsy Calc
A1: Product (as sold) | B1: SKU | C1: Order ID | D1: Qty | E1: Unit price | F1: Item revenue | G1: Items in order | H1: Shipping charged | I1: Discount | J1: Gross sales | K1: Product row | L1: Matched product | M1: Platform fees | N1: Product costs | O1: Return allowance | P1: Net profit
A2: =IFERROR(INDEX('Etsy Import'!$A:$CZ,2,Settings!$C$20)&"","") | B2: =IFERROR(INDEX('Etsy Import'!$A:$CZ,2,Settings!$C$21)&"","") | C2: =IFERROR(INDEX('Etsy Import'!$A:$CZ,2,Settings!$C$22)&"","") | D2: =IF(A2="","",IFERROR(VALUE(SUBSTITUTE(SUBSTITUTE(INDEX('Etsy Import'!$A:$CZ,2,Settings!$C$23)&"","$",""),",","")),0)) | E2: =IF(A2="","",IFERROR(VALUE(SUBSTITUTE(SUBSTITUTE(INDEX('Etsy Import'!$A:$CZ,2,Settings!$C$24)&"","$",""),",","")),0)) | F2: =IF(A2="","",D2*E2) | G2: =IF(A2="","",IF(C2="",1,COUNTIF($C$2:$C$1501,C2))) | H2: =IF(A2="","",IFERROR(VALUE(SUBSTITUTE(SUBSTITUTE(INDEX('Etsy Import'!$A:$CZ,2,Settings!$C$25)&"","$",""),",","")),0)/IF(Settings!$B$27="Yes",G2,1)) | I2: =IF(A2="","",IFERROR(VALUE(SUBSTITUTE(SUBSTITUTE(INDEX('Etsy Import'!$A:$CZ,2,Settings!$C$26)&"","$",""),",","")),0)/IF(Settings!$B$27="Yes",G2,1)) | J2: =IF(A2="","",F2+H2-I2) | K2: =IF(A2="","",IFERROR(IF(B2="",NA(),MATCH(B2,Products!$B$5:$B$204,0)),IFERROR(MATCH(A2,Products!$A$5:$A$204,0),""))) | L2: =IF(A2="","",IF(K2="","⚠ not in Products",INDEX(Products!$A$5:$A$204,K2))) | M2: =IF(A2="","",J2*(IFERROR(INDEX(Settings!$B$5:$B$9,MATCH("Etsy",Settings!$A$5:$A$9,0)),0)+IFERROR(INDEX(Settings!$E$5:$E$9,MATCH("Etsy",Settings!$A$5:$A$9,0)),0)+IFERROR(INDEX(Settings!$G$5:$G$9,MATCH("Etsy",Settings!$A$5:$A$9,0)),0))+(IFERROR(INDEX(Settings!$C$5:$C$9,MATCH("Etsy",Settings!$A$5:$A$9,0)),0)+IFERROR(INDEX(Settings!$F$5:$F$9,MATCH("Etsy",Settings!$A$5:$A$9,0)),0))/G2+IFERROR(INDEX(Settings!$D$5:$D$9,MATCH("Etsy",Settings!$A$5:$A$9,0)),0)*D2) | N2: =IF(A2="","",IF(K2="",0,D2*INDEX(Products!$I$5:$I$204,K2))) | O2: =IF(A2="","",IF(K2="",0,J2*INDEX(Products!$H$5:$H$204,K2))) | P2: =IF(A2="","",J2-M2-N2-O2)
A3: =IFERROR(INDEX('Etsy Import'!$A:$CZ,3,Settings!$C$20)&"","") | B3: =IFERROR(INDEX('Etsy Import'!$A:$CZ,3,Settings!$C$21)&"","") | C3: =IFERROR(INDEX('Etsy Import'!$A:$CZ,3,Settings!$C$22)&"","") | D3: =IF(A3="","",IFERROR(VALUE(SUBSTITUTE(SUBSTITUTE(INDEX('Etsy Import'!$A:$CZ,3,Settings!$C$23)&"","$",""),",","")),0)) | E3: =IF(A3="","",IFERROR(VALUE(SUBSTITUTE(SUBSTITUTE(INDEX('Etsy Import'!$A:$CZ,3,Settings!$C$24)&"","$",""),",","")),0)) | F3: =IF(A3="","",D3*E3) | G3: =IF(A3="","",IF(C3="",1,COUNTIF($C$2:$C$1501,C3))) | H3: =IF(A3="","",IFERROR(VALUE(SUBSTITUTE(SUBSTITUTE(INDEX('Etsy Import'!$A:$CZ,3,Settings!$C$25)&"","$",""),",","")),0)/IF(Settings!$B$27="Yes",G3,1)) | I3: =IF(A3="","",IFERROR(VALUE(SUBSTITUTE(SUBSTITUTE(INDEX('Etsy Import'!$A:$CZ,3,Settings!$C$26)&"","$",""),",","")),0)/IF(Settings!$B$27="Yes",G3,1)) | J3: =IF(A3="","",F3+H3-I3) | K3: =IF(A3="","",IFERROR(IF(B3="",NA(),MATCH(B3,Products!$B$5:$B$204,0)),IFERROR(MATCH(A3,Products!$A$5:$A$204,0),""))) | L3: =IF(A3="","",IF(K3="","⚠ not in Products",INDEX(Products!$A$5:$A$204,K3))) | M3: =IF(A3="","",J3*(IFERROR(INDEX(Settings!$B$5:$B$9,MATCH("Etsy",Settings!$A$5:$A$9,0)),0)+IFERROR(INDEX(Settings!$E$5:$E$9,MATCH("Etsy",Settings!$A$5:$A$9,0)),0)+IFERROR(INDEX(Settings!$G$5:$G$9,MATCH("Etsy",Settings!$A$5:$A$9,0)),0))+(IFERROR(INDEX(Settings!$C$5:$C$9,MATCH("Etsy",Settings!$A$5:$A$9,0)),0)+IFERROR(INDEX(Settings!$F$5:$F$9,MATCH("Etsy",Settings!$A$5:$A$9,0)),0))/G3+IFERROR(INDEX(Settings!$D$5:$D$9,MATCH("Etsy",Settings!$A$5:$A$9,0)),0)*D3) | N3: =IF(A3="","",IF(K3="",0,D3*INDEX(Products!$I$5:$I$204,K3))) | O3: =IF(A3="","",IF(K3="",0,J3*INDEX(Products!$H$5:$H$204,K3))) | P3: =IF(A3="","",J3-M3-N3-O3)
A4: =IFERROR(INDEX('Etsy Import'!$A:$CZ,4,Settings!$C$20)&"","") | B4: =IFERROR(INDEX('Etsy Import'!$A:$CZ,4,Settings!$C$21)&"","") | C4: =IFERROR(INDEX('Etsy Import'!$A:$CZ,4,Settings!$C$22)&"","") | D4: =IF(A4="","",IFERROR(VALUE(SUBSTITUTE(SUBSTITUTE(INDEX('Etsy Import'!$A:$CZ,4,Settings!$C$23)&"","$",""),",","")),0)) | E4: =IF(A4="","",IFERROR(VALUE(SUBSTITUTE(SUBSTITUTE(INDEX('Etsy Import'!$A:$CZ,4,Settings!$C$24)&"","$",""),",","")),0)) | F4: =IF(A4="","",D4*E4) | G4: =IF(A4="","",IF(C4="",1,COUNTIF($C$2:$C$1501,C4))) | H4: =IF(A4="","",IFERROR(VALUE(SUBSTITUTE(SUBSTITUTE(INDEX('Etsy Import'!$A:$CZ,4,Settings!$C$25)&"","$",""),",","")),0)/IF(Settings!$B$27="Yes",G4,1)) | I4: =IF(A4="","",IFERROR(VALUE(SUBSTITUTE(SUBSTITUTE(INDEX('Etsy Import'!$A:$CZ,4,Settings!$C$26)&"","$",""),",","")),0)/IF(Settings!$B$27="Yes",G4,1)) | J4: =IF(A4="","",F4+H4-I4) | K4: =IF(A4="","",IFERROR(IF(B4="",NA(),MATCH(B4,Products!$B$5:$B$204,0)),IFERROR(MATCH(A4,Products!$A$5:$A$204,0),""))) | L4: =IF(A4="","",IF(K4="","⚠ not in Products",INDEX(Products!$A$5:$A$204,K4))) | M4: =IF(A4="","",J4*(IFERROR(INDEX(Settings!$B$5:$B$9,MATCH("Etsy",Settings!$A$5:$A$9,0)),0)+IFERROR(INDEX(Settings!$E$5:$E$9,MATCH("Etsy",Settings!$A$5:$A$9,0)),0)+IFERROR(INDEX(Settings!$G$5:$G$9,MATCH("Etsy",Settings!$A$5:$A$9,0)),0))+(IFERROR(INDEX(Settings!$C$5:$C$9,MATCH("Etsy",Settings!$A$5:$A$9,0)),0)+IFERROR(INDEX(Settings!$F$5:$F$9,MATCH("Etsy",Settings!$A$5:$A$9,0)),0))/G4+IFERROR(INDEX(Settings!$D$5:$D$9,MATCH("Etsy",Settings!$A$5:$A$9,0)),0)*D4) | N4: =IF(A4="","",IF(K4="",0,D4*INDEX(Products!$I$5:$I$204,K4))) | O4: =IF(A4="","",IF(K4="",0,J4*INDEX(Products!$H$5:$H$204,K4))) | P4: =IF(A4="","",J4-M4-N4-O4)
A5: =IFERROR(INDEX('Etsy Import'!$A:$CZ,5,Settings!$C$20)&"","") | B5: =IFERROR(INDEX('Etsy Import'!$A:$CZ,5,Settings!$C$21)&"","") | C5: =IFERROR(INDEX('Etsy Import'!$A:$CZ,5,Settings!$C$22)&"","") | D5: =IF(A5="","",IFERROR(VALUE(SUBSTITUTE(SUBSTITUTE(INDEX('Etsy Import'!$A:$CZ,5,Settings!$C$23)&"","$",""),",","")),0)) | E5: =IF(A5="","",IFERROR(VALUE(SUBSTITUTE(SUBSTITUTE(INDEX('Etsy Import'!$A:$CZ,5,Settings!$C$24)&"","$",""),",","")),0)) | F5: =IF(A5="","",D5*E5) | G5: =IF(A5="","",IF(C5="",1,COUNTIF($C$2:$C$1501,C5))) | H5: =IF(A5="","",IFERROR(VALUE(SUBSTITUTE(SUBSTITUTE(INDEX('Etsy Import'!$A:$CZ,5,Settings!$C$25)&"","$",""),",","")),0)/IF(Settings!$B$27="Yes",G5,1)) | I5: =IF(A5="","",IFERROR(VALUE(SUBSTITUTE(SUBSTITUTE(INDEX('Etsy Import'!$A:$CZ,5,Settings!$C$26)&"","$",""),",","")),0)/IF(Settings!$B$27="Yes",G5,1)) | J5: =IF(A5="","",F5+H5-I5) | K5: =IF(A5="","",IFERROR(IF(B5="",NA(),MATCH(B5,Products!$B$5:$B$204,0)),IFERROR(MATCH(A5,Products!$A$5:$A$204,0),""))) | L5: =IF(A5="","",IF(K5="","⚠ not in Products",INDEX(Products!$A$5:$A$204,K5))) | M5: =IF(A5="","",J5*(IFERROR(INDEX(Settings!$B$5:$B$9,MATCH("Etsy",Settings!$A$5:$A$9,0)),0)+IFERROR(INDEX(Settings!$E$5:$E$9,MATCH("Etsy",Settings!$A$5:$A$9,0)),0)+IFERROR(INDEX(Settings!$G$5:$G$9,MATCH("Etsy",Settings!$A$5:$A$9,0)),0))+(IFERROR(INDEX(Settings!$C$5:$C$9,MATCH("Etsy",Settings!$A$5:$A$9,0)),0)+IFERROR(INDEX(Settings!$F$5:$F$9,MATCH("Etsy",Settings!$A$5:$A$9,0)),0))/G5+IFERROR(INDEX(Settings!$D$5:$D$9,MATCH("Etsy",Settings!$A$5:$A$9,0)),0)*D5) | N5: =IF(A5="","",IF(K5="",0,D5*INDEX(Products!$I$5:$I$204,K5))) | O5: =IF(A5="","",IF(K5="",0,J5*INDEX(Products!$H$5:$H$204,K5))) | P5: =IF(A5="","",J5-M5-N5-O5)
A6: =IFERROR(INDEX('Etsy Import'!$A:$CZ,6,Settings!$C$20)&"","") | B6: =IFERROR(INDEX('Etsy Import'!$A:$CZ,6,Settings!$C$21)&"","") | C6: =IFERROR(INDEX('Etsy Import'!$A:$CZ,6,Settings!$C$22)&"","") | D6: =IF(A6="","",IFERROR(VALUE(SUBSTITUTE(SUBSTITUTE(INDEX('Etsy Import'!$A:$CZ,6,Settings!$C$23)&"","$",""),",","")),0)) | E6: =IF(A6="","",IFERROR(VALUE(SUBSTITUTE(SUBSTITUTE(INDEX('Etsy Import'!$A:$CZ,6,Settings!$C$24)&"","$",""),",","")),0)) | F6: =IF(A6="","",D6*E6) | G6: =IF(A6="","",IF(C6="",1,COUNTIF($C$2:$C$1501,C6))) | H6: =IF(A6="","",IFERROR(VALUE(SUBSTITUTE(SUBSTITUTE(INDEX('Etsy Import'!$A:$CZ,6,Settings!$C$25)&"","$",""),",","")),0)/IF(Settings!$B$27="Yes",G6,1)) | I6: =IF(A6="","",IFERROR(VALUE(SUBSTITUTE(SUBSTITUTE(INDEX('Etsy Import'!$A:$CZ,6,Settings!$C$26)&"","$",""),",","")),0)/IF(Settings!$B$27="Yes",G6,1)) | J6: =IF(A6="","",F6+H6-I6) | K6: =IF(A6="","",IFERROR(IF(B6="",NA(),MATCH(B6,Products!$B$5:$B$204,0)),IFERROR(MATCH(A6,Products!$A$5:$A$204,0),""))) | L6: =IF(A6="","",IF(K6="","⚠ not in Products",INDEX(Products!$A$5:$A$204,K6))) | M6: =IF(A6="","",J6*(IFERROR(INDEX(Settings!$B$5:$B$9,MATCH("Etsy",Settings!$A$5:$A$9,0)),0)+IFERROR(INDEX(Settings!$E$5:$E$9,MATCH("Etsy",Settings!$A$5:$A$9,0)),0)+IFERROR(INDEX(Settings!$G$5:$G$9,MATCH("Etsy",Settings!$A$5:$A$9,0)),0))+(IFERROR(INDEX(Settings!$C$5:$C$9,MATCH("Etsy",Settings!$A$5:$A$9,0)),0)+IFERROR(INDEX(Settings!$F$5:$F$9,MATCH("Etsy",Settings!$A$5:$A$9,0)),0))/G6+IFERROR(INDEX(Settings!$D$5:$D$9,MATCH("Etsy",Settings!$A$5:$A$9,0)),0)*D6) | N6: =IF(A6="","",IF(K6="",0,D6*INDEX(Products!$I$5:$I$204,K6))) | O6: =IF(A6="","",IF(K6="",0,J6*INDEX(Products!$H$5:$H$204,K6))) | P6: =IF(A6="","",J6-M6-N6-O6)
A7: =IFERROR(INDEX('Etsy Import'!$A:$CZ,7,Settings!$C$20)&"","") | B7: =IFERROR(INDEX('Etsy Import'!$A:$CZ,7,Settings!$C$21)&"","") | C7: =IFERROR(INDEX('Etsy Import'!$A:$CZ,7,Settings!$C$22)&"","") | D7: =IF(A7="","",IFERROR(VALUE(SUBSTITUTE(SUBSTITUTE(INDEX('Etsy Import'!$A:$CZ,7,Settings!$C$23)&"","$",""),",","")),0)) | E7: =IF(A7="","",IFERROR(VALUE(SUBSTITUTE(SUBSTITUTE(INDEX('Etsy Import'!$A:$CZ,7,Settings!$C$24)&"","$",""),",","")),0)) | F7: =IF(A7="","",D7*E7) | G7: =IF(A7="","",IF(C7="",1,COUNTIF($C$2:$C$1501,C7))) | H7: =IF(A7="","",IFERROR(VALUE(SUBSTITUTE(SUBSTITUTE(INDEX('Etsy Import'!$A:$CZ,7,Settings!$C$25)&"","$",""),",","")),0)/IF(Settings!$B$27="Yes",G7,1)) | I7: =IF(A7="","",IFERROR(VALUE(SUBSTITUTE(SUBSTITUTE(INDEX('Etsy Import'!$A:$CZ,7,Settings!$C$26)&"","$",""),",","")),0)/IF(Settings!$B$27="Yes",G7,1)) | J7: =IF(A7="","",F7+H7-I7) | K7: =IF(A7="","",IFERROR(IF(B7="",NA(),MATCH(B7,Products!$B$5:$B$204,0)),IFERROR(MATCH(A7,Products!$A$5:$A$204,0),""))) | L7: =IF(A7="","",IF(K7="","⚠ not in Products",INDEX(Products!$A$5:$A$204,K7))) | M7: =IF(A7="","",J7*(IFERROR(INDEX(Settings!$B$5:$B$9,MATCH("Etsy",Settings!$A$5:$A$9,0)),0)+IFERROR(INDEX(Settings!$E$5:$E$9,MATCH("Etsy",Settings!$A$5:$A$9,0)),0)+IFERROR(INDEX(Settings!$G$5:$G$9,MATCH("Etsy",Settings!$A$5:$A$9,0)),0))+(IFERROR(INDEX(Settings!$C$5:$C$9,MATCH("Etsy",Settings!$A$5:$A$9,0)),0)+IFERROR(INDEX(Settings!$F$5:$F$9,MATCH("Etsy",Settings!$A$5:$A$9,0)),0))/G7+IFERROR(INDEX(Settings!$D$5:$D$9,MATCH("Etsy",Settings!$A$5:$A$9,0)),0)*D7) | N7: =IF(A7="","",IF(K7="",0,D7*INDEX(Products!$I$5:$I$204,K7))) | O7: =IF(A7="","",IF(K7="",0,J7*INDEX(Products!$H$5:$H$204,K7))) | P7: =IF(A7="","",J7-M7-N7-O7)
A8: =IFERROR(INDEX('Etsy Import'!$A:$CZ,8,Settings!$C$20)&"","") | B8: =IFERROR(INDEX('Etsy Import'!$A:$CZ,8,Settings!$C$21)&"","") | C8: =IFERROR(INDEX('Etsy Import'!$A:$CZ,8,Settings!$C$22)&"","") | D8: =IF(A8="","",IFERROR(VALUE(SUBSTITUTE(SUBSTITUTE(INDEX('Etsy Import'!$A:$CZ,8,Settings!$C$23)&"","$",""),",","")),0)) | E8: =IF(A8="","",IFERROR(VALUE(SUBSTITUTE(SUBSTITUTE(INDEX('Etsy Import'!$A:$CZ,8,Settings!$C$24)&"","$",""),",","")),0)) | F8: =IF(A8="","",D8*E8) | G8: =IF(A8="","",IF(C8="",1,COUNTIF($C$2:$C$1501,C8))) | H8: =IF(A8="","",IFERROR(VALUE(SUBSTITUTE(SUBSTITUTE(INDEX('Etsy Import'!$A:$CZ,8,Settings!$C$25)&"","$",""),",","")),0)/IF(Settings!$B$27="Yes",G8,1)) | I8: =IF(A8="","",IFERROR(VALUE(SUBSTITUTE(SUBSTITUTE(INDEX('Etsy Import'!$A:$CZ,8,Settings!$C$26)&"","$",""),",","")),0)/IF(Settings!$B$27="Yes",G8,1)) | J8: =IF(A8="","",F8+H8-I8) | K8: =IF(A8="","",IFERROR(IF(B8="",NA(),MATCH(B8,Products!$B$5:$B$204,0)),IFERROR(MATCH(A8,Products!$A$5:$A$204,0),""))) | L8: =IF(A8="","",IF(K8="","⚠ not in Products",INDEX(Products!$A$5:$A$204,K8))) | M8: =IF(A8="","",J8*(IFERROR(INDEX(Settings!$B$5:$B$9,MATCH("Etsy",Settings!$A$5:$A$9,0)),0)+IFERROR(INDEX(Settings!$E$5:$E$9,MATCH("Etsy",Settings!$A$5:$A$9,0)),0)+IFERROR(INDEX(Settings!$G$5:$G$9,MATCH("Etsy",Settings!$A$5:$A$9,0)),0))+(IFERROR(INDEX(Settings!$C$5:$C$9,MATCH("Etsy",Settings!$A$5:$A$9,0)),0)+IFERROR(INDEX(Settings!$F$5:$F$9,MATCH("Etsy",Settings!$A$5:$A$9,0)),0))/G8+IFERROR(INDEX(Settings!$D$5:$D$9,MATCH("Etsy",Settings!$A$5:$A$9,0)),0)*D8) | N8: =IF(A8="","",IF(K8="",0,D8*INDEX(Products!$I$5:$I$204,K8))) | O8: =IF(A8="","",IF(K8="",0,J8*INDEX(Products!$H$5:$H$204,K8))) | P8: =IF(A8="","",J8-M8-N8-O8)
A9: =IFERROR(INDEX('Etsy Import'!$A:$CZ,9,Settings!$C$20)&"","") | B9: =IFERROR(INDEX('Etsy Import'!$A:$CZ,9,Settings!$C$21)&"","") | C9: =IFERROR(INDEX('Etsy Import'!$A:$CZ,9,Settings!$C$22)&"","") | D9: =IF(A9="","",IFERROR(VALUE(SUBSTITUTE(SUBSTITUTE(INDEX('Etsy Import'!$A:$CZ,9,Settings!$C$23)&"","$",""),",","")),0)) | E9: =IF(A9="","",IFERROR(VALUE(SUBSTITUTE(SUBSTITUTE(INDEX('Etsy Import'!$A:$CZ,9,Settings!$C$24)&"","$",""),",","")),0)) | F9: =IF(A9="","",D9*E9) | G9: =IF(A9="","",IF(C9="",1,COUNTIF($C$2:$C$1501,C9))) | H9: =IF(A9="","",IFERROR(VALUE(SUBSTITUTE(SUBSTITUTE(INDEX('Etsy Import'!$A:$CZ,9,Settings!$C$25)&"","$",""),",","")),0)/IF(Settings!$B$27="Yes",G9,1)) | I9: =IF(A9="","",IFERROR(VALUE(SUBSTITUTE(SUBSTITUTE(INDEX('Etsy Import'!$A:$CZ,9,Settings!$C$26)&"","$",""),",","")),0)/IF(Settings!$B$27="Yes",G9,1)) | J9: =IF(A9="","",F9+H9-I9) | K9: =IF(A9="","",IFERROR(IF(B9="",NA(),MATCH(B9,Products!$B$5:$B$204,0)),IFERROR(MATCH(A9,Products!$A$5:$A$204,0),""))) | L9: =IF(A9="","",IF(K9="","⚠ not in Products",INDEX(Products!$A$5:$A$204,K9))) | M9: =IF(A9="","",J9*(IFERROR(INDEX(Settings!$B$5:$B$9,MATCH("Etsy",Settings!$A$5:$A$9,0)),0)+IFERROR(INDEX(Settings!$E$5:$E$9,MATCH("Etsy",Settings!$A$5:$A$9,0)),0)+IFERROR(INDEX(Settings!$G$5:$G$9,MATCH("Etsy",Settings!$A$5:$A$9,0)),0))+(IFERROR(INDEX(Settings!$C$5:$C$9,MATCH("Etsy",Settings!$A$5:$A$9,0)),0)+IFERROR(INDEX(Settings!$F$5:$F$9,MATCH("Etsy",Settings!$A$5:$A$9,0)),0))/G9+IFERROR(INDEX(Settings!$D$5:$D$9,MATCH("Etsy",Settings!$A$5:$A$9,0)),0)*D9) | N9: =IF(A9="","",IF(K9="",0,D9*INDEX(Products!$I$5:$I$204,K9))) | O9: =IF(A9="","",IF(K9="",0,J9*INDEX(Products!$H$5:$H$204,K9))) | P9: =IF(A9="","",J9-M9-N9-O9)
A10: =IFERROR(INDEX('Etsy Import'!$A:$CZ,10,Settings!$C$20)&"","") | B10: =IFERROR(INDEX('Etsy Import'!$A:$CZ,10,Settings!$C$21)&"","") | C10: =IFERROR(INDEX('Etsy Import'!$A:$CZ,10,Settings!$C$22)&"","") | D10: =IF(A10="","",IFERROR(VALUE(SUBSTITUTE(SUBSTITUTE(INDEX('Etsy Import'!$A:$CZ,10,Settings!$C$23)&"","$",""),",","")),0)) | E10: =IF(A10="","",IFERROR(VALUE(SUBSTITUTE(SUBSTITUTE(INDEX('Etsy Import'!$A:$CZ,10,Settings!$C$24)&"","$",""),",","")),0)) | F10: =IF(A10="","",D10*E10) | G10: =IF(A10="","",IF(C10="",1,COUNTIF($C$2:$C$1501,C10))) | H10: =IF(A10="","",IFERROR(VALUE(SUBSTITUTE(SUBSTITUTE(INDEX('Etsy Import'!$A:$CZ,10,Settings!$C$25)&"","$",""),",","")),0)/IF(Settings!$B$27="Yes",G10,1)) | I10: =IF(A10="","",IFERROR(VALUE(SUBSTITUTE(SUBSTITUTE(INDEX('Etsy Import'!$A:$CZ,10,Settings!$C$26)&"","$",""),",","")),0)/IF(Settings!$B$27="Yes",G10,1)) | J10: =IF(A10="","",F10+H10-I10) | K10: =IF(A10="","",IFERROR(IF(B10="",NA(),MATCH(B10,Products!$B$5:$B$204,0)),IFERROR(MATCH(A10,Products!$A$5:$A$204,0),""))) | L10: =IF(A10="","",IF(K10="","⚠ not in Products",INDEX(Products!$A$5:$A$204,K10))) | M10: =IF(A10="","",J10*(IFERROR(INDEX(Settings!$B$5:$B$9,MATCH("Etsy",Settings!$A$5:$A$9,0)),0)+IFERROR(INDEX(Settings!$E$5:$E$9,MATCH("Etsy",Settings!$A$5:$A$9,0)),0)+IFERROR(INDEX(Settings!$G$5:$G$9,MATCH("Etsy",Settings!$A$5:$A$9,0)),0))+(IFERROR(INDEX(Settings!$C$5:$C$9,MATCH("Etsy",Settings!$A$5:$A$9,0)),0)+IFERROR(INDEX(Settings!$F$5:$F$9,MATCH("Etsy",Settings!$A$5:$A$9,0)),0))/G10+IFERROR(INDEX(Settings!$D$5:$D$9,MATCH("Etsy",Settings!$A$5:$A$9,0)),0)*D10) | N10: =IF(A10="","",IF(K10="",0,D10*INDEX(Products!$I$5:$I$204,K10))) | O10: =IF(A10="","",IF(K10="",0,J10*INDEX(Products!$H$5:$H$204,K10))) | P10: =IF(A10="","",J10-M10-N10-O10)
A11: =IFERROR(INDEX('Etsy Import'!$A:$CZ,11,Settings!$C$20)&"","") | B11: =IFERROR(INDEX('Etsy Import'!$A:$CZ,11,Settings!$C$21)&"","") | C11: =IFERROR(INDEX('Etsy Import'!$A:$CZ,11,Settings!$C$22)&"","") | D11: =IF(A11="","",IFERROR(VALUE(SUBSTITUTE(SUBSTITUTE(INDEX('Etsy Import'!$A:$CZ,11,Settings!$C$23)&"","$",""),",","")),0)) | E11: =IF(A11="","",IFERROR(VALUE(SUBSTITUTE(SUBSTITUTE(INDEX('Etsy Import'!$A:$CZ,11,Settings!$C$24)&"","$",""),",","")),0)) | F11: =IF(A11="","",D11*E11) | G11: =IF(A11="","",IF(C11="",1,COUNTIF($C$2:$C$1501,C11))) | H11: =IF(A11="","",IFERROR(VALUE(SUBSTITUTE(SUBSTITUTE(INDEX('Etsy Import'!$A:$CZ,11,Settings!$C$25)&"","$",""),",","")),0)/IF(Settings!$B$27="Yes",G11,1)) | I11: =IF(A11="","",IFERROR(VALUE(SUBSTITUTE(SUBSTITUTE(INDEX('Etsy Import'!$A:$CZ,11,Settings!$C$26)&"","$",""),",","")),0)/IF(Settings!$B$27="Yes",G11,1)) | J11: =IF(A11="","",F11+H11-I11) | K11: =IF(A11="","",IFERROR(IF(B11="",NA(),MATCH(B11,Products!$B$5:$B$204,0)),IFERROR(MATCH(A11,Products!$A$5:$A$204,0),""))) | L11: =IF(A11="","",IF(K11="","⚠ not in Products",INDEX(Products!$A$5:$A$204,K11))) | M11: =IF(A11="","",J11*(IFERROR(INDEX(Settings!$B$5:$B$9,MATCH("Etsy",Settings!$A$5:$A$9,0)),0)+IFERROR(INDEX(Settings!$E$5:$E$9,MATCH("Etsy",Settings!$A$5:$A$9,0)),0)+IFERROR(INDEX(Settings!$G$5:$G$9,MATCH("Etsy",Settings!$A$5:$A$9,0)),0))+(IFERROR(INDEX(Settings!$C$5:$C$9,MATCH("Etsy",Settings!$A$5:$A$9,0)),0)+IFERROR(INDEX(Settings!$F$5:$F$9,MATCH("Etsy",Settings!$A$5:$A$9,0)),0))/G11+IFERROR(INDEX(Settings!$D$5:$D$9,MATCH("Etsy",Settings!$A$5:$A$9,0)),0)*D11) | N11: =IF(A11="","",IF(K11="",0,D11*INDEX(Products!$I$5:$I$204,K11))) | O11: =IF(A11="","",IF(K11="",0,J11*INDEX(Products!$H$5:$H$204,K11))) | P11: =IF(A11="","",J11-M11-N11-O11)
A12: =IFERROR(INDEX('Etsy Import'!$A:$CZ,12,Settings!$C$20)&"","") | B12: =IFERROR(INDEX('Etsy Import'!$A:$CZ,12,Settings!$C$21)&"","") | C12: =IFERROR(INDEX('Etsy Import'!$A:$CZ,12,Settings!$C$22)&"","") | D12: =IF(A12="","",IFERROR(VALUE(SUBSTITUTE(SUBSTITUTE(INDEX('Etsy Import'!$A:$CZ,12,Settings!$C$23)&"","$",""),",","")),0)) | E12: =IF(A12="","",IFERROR(VALUE(SUBSTITUTE(SUBSTITUTE(INDEX('Etsy Import'!$A:$CZ,12,Settings!$C$24)&"","$",""),",","")),0)) | F12: =IF(A12="","",D12*E12) | G12: =IF(A12="","",IF(C12="",1,COUNTIF($C$2:$C$1501,C12))) | H12: =IF(A12="","",IFERROR(VALUE(SUBSTITUTE(SUBSTITUTE(INDEX('Etsy Import'!$A:$CZ,12,Settings!$C$25)&"","$",""),",","")),0)/IF(Settings!$B$27="Yes",G12,1)) | I12: =IF(A12="","",IFERROR(VALUE(SUBSTITUTE(SUBSTITUTE(INDEX('Etsy Import'!$A:$CZ,12,Settings!$C$26)&"","$",""),",","")),0)/IF(Settings!$B$27="Yes",G12,1)) | J12: =IF(A12="","",F12+H12-I12) | K12: =IF(A12="","",IFERROR(IF(B12="",NA(),MATCH(B12,Products!$B$5:$B$204,0)),IFERROR(MATCH(A12,Products!$A$5:$A$204,0),""))) | L12: =IF(A12="","",IF(K12="","⚠ not in Products",INDEX(Products!$A$5:$A$204,K12))) | M12: =IF(A12="","",J12*(IFERROR(INDEX(Settings!$B$5:$B$9,MATCH("Etsy",Settings!$A$5:$A$9,0)),0)+IFERROR(INDEX(Settings!$E$5:$E$9,MATCH("Etsy",Settings!$A$5:$A$9,0)),0)+IFERROR(INDEX(Settings!$G$5:$G$9,MATCH("Etsy",Settings!$A$5:$A$9,0)),0))+(IFERROR(INDEX(Settings!$C$5:$C$9,MATCH("Etsy",Settings!$A$5:$A$9,0)),0)+IFERROR(INDEX(Settings!$F$5:$F$9,MATCH("Etsy",Settings!$A$5:$A$9,0)),0))/G12+IFERROR(INDEX(Settings!$D$5:$D$9,MATCH("Etsy",Settings!$A$5:$A$9,0)),0)*D12) | N12: =IF(A12="","",IF(K12="",0,D12*INDEX(Products!$I$5:$I$204,K12))) | O12: =IF(A12="","",IF(K12="",0,J12*INDEX(Products!$H$5:$H$204,K12))) | P12: =IF(A12="","",J12-M12-N12-O12)
A13: =IFERROR(INDEX('Etsy Import'!$A:$CZ,13,Settings!$C$20)&"","") | B13: =IFERROR(INDEX('Etsy Import'!$A:$CZ,13,Settings!$C$21)&"","") | C13: =IFERROR(INDEX('Etsy Import'!$A:$CZ,13,Settings!$C$22)&"","") | D13: =IF(A13="","",IFERROR(VALUE(SUBSTITUTE(SUBSTITUTE(INDEX('Etsy Import'!$A:$CZ,13,Settings!$C$23)&"","$",""),",","")),0)) | E13: =IF(A13="","",IFERROR(VALUE(SUBSTITUTE(SUBSTITUTE(INDEX('Etsy Import'!$A:$CZ,13,Settings!$C$24)&"","$",""),",","")),0)) | F13: =IF(A13="","",D13*E13) | G13: =IF(A13="","",IF(C13="",1,COUNTIF($C$2:$C$1501,C13))) | H13: =IF(A13="","",IFERROR(VALUE(SUBSTITUTE(SUBSTITUTE(INDEX('Etsy Import'!$A:$CZ,13,Settings!$C$25)&"","$",""),",","")),0)/IF(Settings!$B$27="Yes",G13,1)) | I13: =IF(A13="","",IFERROR(VALUE(SUBSTITUTE(SUBSTITUTE(INDEX('Etsy Import'!$A:$CZ,13,Settings!$C$26)&"","$",""),",","")),0)/IF(Settings!$B$27="Yes",G13,1)) | J13: =IF(A13="","",F13+H13-I13) | K13: =IF(A13="","",IFERROR(IF(B13="",NA(),MATCH(B13,Products!$B$5:$B$204,0)),IFERROR(MATCH(A13,Products!$A$5:$A$204,0),""))) | L13: =IF(A13="","",IF(K13="","⚠ not in Products",INDEX(Products!$A$5:$A$204,K13))) | M13: =IF(A13="","",J13*(IFERROR(INDEX(Settings!$B$5:$B$9,MATCH("Etsy",Settings!$A$5:$A$9,0)),0)+IFERROR(INDEX(Settings!$E$5:$E$9,MATCH("Etsy",Settings!$A$5:$A$9,0)),0)+IFERROR(INDEX(Settings!$G$5:$G$9,MATCH("Etsy",Settings!$A$5:$A$9,0)),0))+(IFERROR(INDEX(Settings!$C$5:$C$9,MATCH("Etsy",Settings!$A$5:$A$9,0)),0)+IFERROR(INDEX(Settings!$F$5:$F$9,MATCH("Etsy",Settings!$A$5:$A$9,0)),0))/G13+IFERROR(INDEX(Settings!$D$5:$D$9,MATCH("Etsy",Settings!$A$5:$A$9,0)),0)*D13) | N13: =IF(A13="","",IF(K13="",0,D13*INDEX(Products!$I$5:$I$204,K13))) | O13: =IF(A13="","",IF(K13="",0,J13*INDEX(Products!$H$5:$H$204,K13))) | P13: =IF(A13="","",J13-M13-N13-O13)
A14: =IFERROR(INDEX('Etsy Import'!$A:$CZ,14,Settings!$C$20)&"","") | B14: =IFERROR(INDEX('Etsy Import'!$A:$CZ,14,Settings!$C$21)&"","") | C14: =IFERROR(INDEX('Etsy Import'!$A:$CZ,14,Settings!$C$22)&"","") | D14: =IF(A14="","",IFERROR(VALUE(SUBSTITUTE(SUBSTITUTE(INDEX('Etsy Import'!$A:$CZ,14,Settings!$C$23)&"","$",""),",","")),0)) | E14: =IF(A14="","",IFERROR(VALUE(SUBSTITUTE(SUBSTITUTE(INDEX('Etsy Import'!$A:$CZ,14,Settings!$C$24)&"","$",""),",","")),0)) | F14: =IF(A14="","",D14*E14) | G14: =IF(A14="","",IF(C14="",1,COUNTIF($C$2:$C$1501,C14))) | H14: =IF(A14="","",IFERROR(VALUE(SUBSTITUTE(SUBSTITUTE(INDEX('Etsy Import'!$A:$CZ,14,Settings!$C$25)&"","$",""),",","")),0)/IF(Settings!$B$27="Yes",G14,1)) | I14: =IF(A14="","",IFERROR(VALUE(SUBSTITUTE(SUBSTITUTE(INDEX('Etsy Import'!$A:$CZ,14,Settings!$C$26)&"","$",""),",","")),0)/IF(Settings!$B$27="Yes",G14,1)) | J14: =IF(A14="","",F14+H14-I14) | K14: =IF(A14="","",IFERROR(IF(B14="",NA(),MATCH(B14,Products!$B$5:$B$204,0)),IFERROR(MATCH(A14,Products!$A$5:$A$204,0),""))) | L14: =IF(A14="","",IF(K14="","⚠ not in Products",INDEX(Products!$A$5:$A$204,K14))) | M14: =IF(A14="","",J14*(IFERROR(INDEX(Settings!$B$5:$B$9,MATCH("Etsy",Settings!$A$5:$A$9,0)),0)+IFERROR(INDEX(Settings!$E$5:$E$9,MATCH("Etsy",Settings!$A$5:$A$9,0)),0)+IFERROR(INDEX(Settings!$G$5:$G$9,MATCH("Etsy",Settings!$A$5:$A$9,0)),0))+(IFERROR(INDEX(Settings!$C$5:$C$9,MATCH("Etsy",Settings!$A$5:$A$9,0)),0)+IFERROR(INDEX(Settings!$F$5:$F$9,MATCH("Etsy",Settings!$A$5:$A$9,0)),0))/G14+IFERROR(INDEX(Settings!$D$5:$D$9,MATCH("Etsy",Settings!$A$5:$A$9,0)),0)*D14) | N14: =IF(A14="","",IF(K14="",0,D14*INDEX(Products!$I$5:$I$204,K14))) | O14: =IF(A14="","",IF(K14="",0,J14*INDEX(Products!$H$5:$H$204,K14))) | P14: =IF(A14="","",J14-M14-N14-O14)
A15: =IFERROR(INDEX('Etsy Import'!$A:$CZ,15,Settings!$C$20)&"","") | B15: =IFERROR(INDEX('Etsy Import'!$A:$CZ,15,Settings!$C$21)&"","") | C15: =IFERROR(INDEX('Etsy Import'!$A:$CZ,15,Settings!$C$22)&"","") | D15: =IF(A15="","",IFERROR(VALUE(SUBSTITUTE(SUBSTITUTE(INDEX('Etsy Import'!$A:$CZ,15,Settings!$C$23)&"","$",""),",","")),0)) | E15: =IF(A15="","",IFERROR(VALUE(SUBSTITUTE(SUBSTITUTE(INDEX('Etsy Import'!$A:$CZ,15,Settings!$C$24)&"","$",""),",","")),0)) | F15: =IF(A15="","",D15*E15) | G15: =IF(A15="","",IF(C15="",1,COUNTIF($C$2:$C$1501,C15))) | H15: =IF(A15="","",IFERROR(VALUE(SUBSTITUTE(SUBSTITUTE(INDEX('Etsy Import'!$A:$CZ,15,Settings!$C$25)&"","$",""),",","")),0)/IF(Settings!$B$27="Yes",G15,1)) | I15: =IF(A15="","",IFERROR(VALUE(SUBSTITUTE(SUBSTITUTE(INDEX('Etsy Import'!$A:$CZ,15,Settings!$C$26)&"","$",""),",","")),0)/IF(Settings!$B$27="Yes",G15,1)) | J15: =IF(A15="","",F15+H15-I15) | K15: =IF(A15="","",IFERROR(IF(B15="",NA(),MATCH(B15,Products!$B$5:$B$204,0)),IFERROR(MATCH(A15,Products!$A$5:$A$204,0),""))) | L15: =IF(A15="","",IF(K15="","⚠ not in Products",INDEX(Products!$A$5:$A$204,K15))) | M15: =IF(A15="","",J15*(IFERROR(INDEX(Settings!$B$5:$B$9,MATCH("Etsy",Settings!$A$5:$A$9,0)),0)+IFERROR(INDEX(Settings!$E$5:$E$9,MATCH("Etsy",Settings!$A$5:$A$9,0)),0)+IFERROR(INDEX(Settings!$G$5:$G$9,MATCH("Etsy",Settings!$A$5:$A$9,0)),0))+(IFERROR(INDEX(Settings!$C$5:$C$9,MATCH("Etsy",Settings!$A$5:$A$9,0)),0)+IFERROR(INDEX(Settings!$F$5:$F$9,MATCH("Etsy",Settings!$A$5:$A$9,0)),0))/G15+IFERROR(INDEX(Settings!$D$5:$D$9,MATCH("Etsy",Settings!$A$5:$A$9,0)),0)*D15) | N15: =IF(A15="","",IF(K15="",0,D15*INDEX(Products!$I$5:$I$204,K15))) | O15: =IF(A15="","",IF(K15="",0,J15*INDEX(Products!$H$5:$H$204,K15))) | P15: =IF(A15="","",J15-M15-N15-O15)
A16: =IFERROR(INDEX('Etsy Import'!$A:$CZ,16,Settings!$C$20)&"","") | B16: =IFERROR(INDEX('Etsy Import'!$A:$CZ,16,Settings!$C$21)&"","") | C16: =IFERROR(INDEX('Etsy Import'!$A:$CZ,16,Settings!$C$22)&"","") | D16: =IF(A16="","",IFERROR(VALUE(SUBSTITUTE(SUBSTITUTE(INDEX('Etsy Import'!$A:$CZ,16,Settings!$C$23)&"","$",""),",","")),0)) | E16: =IF(A16="","",IFERROR(VALUE(SUBSTITUTE(SUBSTITUTE(INDEX('Etsy Import'!$A:$CZ,16,Settings!$C$24)&"","$",""),",","")),0)) | F16: =IF(A16="","",D16*E16) | G16: =IF(A16="","",IF(C16="",1,COUNTIF($C$2:$C$1501,C16))) | H16: =IF(A16="","",IFERROR(VALUE(SUBSTITUTE(SUBSTITUTE(INDEX('Etsy Import'!$A:$CZ,16,Settings!$C$25)&"","$",""),",","")),0)/IF(Settings!$B$27="Yes",G16,1)) | I16: =IF(A16="","",IFERROR(VALUE(SUBSTITUTE(SUBSTITUTE(INDEX('Etsy Import'!$A:$CZ,16,Settings!$C$26)&"","$",""),",","")),0)/IF(Settings!$B$27="Yes",G16,1)) | J16: =IF(A16="","",F16+H16-I16) | K16: =IF(A16="","",IFERROR(IF(B16="",NA(),MATCH(B16,Products!$B$5:$B$204,0)),IFERROR(MATCH(A16,Products!$A$5:$A$204,0),""))) | L16: =IF(A16="","",IF(K16="","⚠ not in Products",INDEX(Products!$A$5:$A$204,K16))) | M16: =IF(A16="","",J16*(IFERROR(INDEX(Settings!$B$5:$B$9,MATCH("Etsy",Settings!$A$5:$A$9,0)),0)+IFERROR(INDEX(Settings!$E$5:$E$9,MATCH("Etsy",Settings!$A$5:$A$9,0)),0)+IFERROR(INDEX(Settings!$G$5:$G$9,MATCH("Etsy",Settings!$A$5:$A$9,0)),0))+(IFERROR(INDEX(Settings!$C$5:$C$9,MATCH("Etsy",Settings!$A$5:$A$9,0)),0)+IFERROR(INDEX(Settings!$F$5:$F$9,MATCH("Etsy",Settings!$A$5:$A$9,0)),0))/G16+IFERROR(INDEX(Settings!$D$5:$D$9,MATCH("Etsy",Settings!$A$5:$A$9,0)),0)*D16) | N16: =IF(A16="","",IF(K16="",0,D16*INDEX(Products!$I$5:$I$204,K16))) | O16: =IF(A16="","",IF(K16="",0,J16*INDEX(Products!$H$5:$H$204,K16))) | P16: =IF(A16="","",J16-M16-N16-O16)
A17: =IFERROR(INDEX('Etsy Import'!$A:$CZ,17,Settings!$C$20)&"","") | B17: =IFERROR(INDEX('Etsy Import'!$A:$CZ,17,Settings!$C$21)&"","") | C17: =IFERROR(INDEX('Etsy Import'!$A:$CZ,17,Settings!$C$22)&"","") | D17: =IF(A17="","",IFERROR(VALUE(SUBSTITUTE(SUBSTITUTE(INDEX('Etsy Import'!$A:$CZ,17,Settings!$C$23)&"","$",""),",","")),0)) | E17: =IF(A17="","",IFERROR(VALUE(SUBSTITUTE(SUBSTITUTE(INDEX('Etsy Import'!$A:$CZ,17,Settings!$C$24)&"","$",""),",","")),0)) | F17: =IF(A17="","",D17*E17) | G17: =IF(A17="","",IF(C17="",1,COUNTIF($C$2:$C$1501,C17))) | H17: =IF(A17="","",IFERROR(VALUE(SUBSTITUTE(SUBSTITUTE(INDEX('Etsy Import'!$A:$CZ,17,Settings!$C$25)&"","$",""),",","")),0)/IF(Settings!$B$27="Yes",G17,1)) | I17: =IF(A17="","",IFERROR(VALUE(SUBSTITUTE(SUBSTITUTE(INDEX('Etsy Import'!$A:$CZ,17,Settings!$C$26)&"","$",""),",","")),0)/IF(Settings!$B$27="Yes",G17,1)) | J17: =IF(A17="","",F17+H17-I17) | K17: =IF(A17="","",IFERROR(IF(B17="",NA(),MATCH(B17,Products!$B$5:$B$204,0)),IFERROR(MATCH(A17,Products!$A$5:$A$204,0),""))) | L17: =IF(A17="","",IF(K17="","⚠ not in Products",INDEX(Products!$A$5:$A$204,K17))) | M17: =IF(A17="","",J17*(IFERROR(INDEX(Settings!$B$5:$B$9,MATCH("Etsy",Settings!$A$5:$A$9,0)),0)+IFERROR(INDEX(Settings!$E$5:$E$9,MATCH("Etsy",Settings!$A$5:$A$9,0)),0)+IFERROR(INDEX(Settings!$G$5:$G$9,MATCH("Etsy",Settings!$A$5:$A$9,0)),0))+(IFERROR(INDEX(Settings!$C$5:$C$9,MATCH("Etsy",Settings!$A$5:$A$9,0)),0)+IFERROR(INDEX(Settings!$F$5:$F$9,MATCH("Etsy",Settings!$A$5:$A$9,0)),0))/G17+IFERROR(INDEX(Settings!$D$5:$D$9,MATCH("Etsy",Settings!$A$5:$A$9,0)),0)*D17) | N17: =IF(A17="","",IF(K17="",0,D17*INDEX(Products!$I$5:$I$204,K17))) | O17: =IF(A17="","",IF(K17="",0,J17*INDEX(Products!$H$5:$H$204,K17))) | P17: =IF(A17="","",J17-M17-N17-O17)
A18: =IFERROR(INDEX('Etsy Import'!$A:$CZ,18,Settings!$C$20)&"","") | B18: =IFERROR(INDEX('Etsy Import'!$A:$CZ,18,Settings!$C$21)&"","") | C18: =IFERROR(INDEX('Etsy Import'!$A:$CZ,18,Settings!$C$22)&"","") | D18: =IF(A18="","",IFERROR(VALUE(SUBSTITUTE(SUBSTITUTE(INDEX('Etsy Import'!$A:$CZ,18,Settings!$C$23)&"","$",""),",","")),0)) | E18: =IF(A18="","",IFERROR(VALUE(SUBSTITUTE(SUBSTITUTE(INDEX('Etsy Import'!$A:$CZ,18,Settings!$C$24)&"","$",""),",","")),0)) | F18: =IF(A18="","",D18*E18) | G18: =IF(A18="","",IF(C18="",1,COUNTIF($C$2:$C$1501,C18))) | H18: =IF(A18="","",IFERROR(VALUE(SUBSTITUTE(SUBSTITUTE(INDEX('Etsy Import'!$A:$CZ,18,Settings!$C$25)&"","$",""),",","")),0)/IF(Settings!$B$27="Yes",G18,1)) | I18: =IF(A18="","",IFERROR(VALUE(SUBSTITUTE(SUBSTITUTE(INDEX('Etsy Import'!$A:$CZ,18,Settings!$C$26)&"","$",""),",","")),0)/IF(Settings!$B$27="Yes",G18,1)) | J18: =IF(A18="","",F18+H18-I18) | K18: =IF(A18="","",IFERROR(IF(B18="",NA(),MATCH(B18,Products!$B$5:$B$204,0)),IFERROR(MATCH(A18,Products!$A$5:$A$204,0),""))) | L18: =IF(A18="","",IF(K18="","⚠ not in Products",INDEX(Products!$A$5:$A$204,K18))) | M18: =IF(A18="","",J18*(IFERROR(INDEX(Settings!$B$5:$B$9,MATCH("Etsy",Settings!$A$5:$A$9,0)),0)+IFERROR(INDEX(Settings!$E$5:$E$9,MATCH("Etsy",Settings!$A$5:$A$9,0)),0)+IFERROR(INDEX(Settings!$G$5:$G$9,MATCH("Etsy",Settings!$A$5:$A$9,0)),0))+(IFERROR(INDEX(Settings!$C$5:$C$9,MATCH("Etsy",Settings!$A$5:$A$9,0)),0)+IFERROR(INDEX(Settings!$F$5:$F$9,MATCH("Etsy",Settings!$A$5:$A$9,0)),0))/G18+IFERROR(INDEX(Settings!$D$5:$D$9,MATCH("Etsy",Settings!$A$5:$A$9,0)),0)*D18) | N18: =IF(A18="","",IF(K18="",0,D18*INDEX(Products!$I$5:$I$204,K18))) | O18: =IF(A18="","",IF(K18="",0,J18*INDEX(Products!$H$5:$H$204,K18))) | P18: =IF(A18="","",J18-M18-N18-O18)
A19: =IFERROR(INDEX('Etsy Import'!$A:$CZ,19,Settings!$C$20)&"","") | B19: =IFERROR(INDEX('Etsy Import'!$A:$CZ,19,Settings!$C$21)&"","") | C19: =IFERROR(INDEX('Etsy Import'!$A:$CZ,19,Settings!$C$22)&"","") | D19: =IF(A19="","",IFERROR(VALUE(SUBSTITUTE(SUBSTITUTE(INDEX('Etsy Import'!$A:$CZ,19,Settings!$C$23)&"","$",""),",","")),0)) | E19: =IF(A19="","",IFERROR(VALUE(SUBSTITUTE(SUBSTITUTE(INDEX('Etsy Import'!$A:$CZ,19,Settings!$C$24)&"","$",""),",","")),0)) | F19: =IF(A19="","",D19*E19) | G19: =IF(A19="","",IF(C19="",1,COUNTIF($C$2:$C$1501,C19))) | H19: =IF(A19="","",IFERROR(VALUE(SUBSTITUTE(SUBSTITUTE(INDEX('Etsy Import'!$A:$CZ,19,Settings!$C$25)&"","$",""),",","")),0)/IF(Settings!$B$27="Yes",G19,1)) | I19: =IF(A19="","",IFERROR(VALUE(SUBSTITUTE(SUBSTITUTE(INDEX('Etsy Import'!$A:$CZ,19,Settings!$C$26)&"","$",""),",","")),0)/IF(Settings!$B$27="Yes",G19,1)) | J19: =IF(A19="","",F19+H19-I19) | K19: =IF(A19="","",IFERROR(IF(B19="",NA(),MATCH(B19,Products!$B$5:$B$204,0)),IFERROR(MATCH(A19,Products!$A$5:$A$204,0),""))) | L19: =IF(A19="","",IF(K19="","⚠ not in Products",INDEX(Products!$A$5:$A$204,K19))) | M19: =IF(A19="","",J19*(IFERROR(INDEX(Settings!$B$5:$B$9,MATCH("Etsy",Settings!$A$5:$A$9,0)),0)+IFERROR(INDEX(Settings!$E$5:$E$9,MATCH("Etsy",Settings!$A$5:$A$9,0)),0)+IFERROR(INDEX(Settings!$G$5:$G$9,MATCH("Etsy",Settings!$A$5:$A$9,0)),0))+(IFERROR(INDEX(Settings!$C$5:$C$9,MATCH("Etsy",Settings!$A$5:$A$9,0)),0)+IFERROR(INDEX(Settings!$F$5:$F$9,MATCH("Etsy",Settings!$A$5:$A$9,0)),0))/G19+IFERROR(INDEX(Settings!$D$5:$D$9,MATCH("Etsy",Settings!$A$5:$A$9,0)),0)*D19) | N19: =IF(A19="","",IF(K19="",0,D19*INDEX(Products!$I$5:$I$204,K19))) | O19: =IF(A19="","",IF(K19="",0,J19*INDEX(Products!$H$5:$H$204,K19))) | P19: =IF(A19="","",J19-M19-N19-O19)
A20: =IFERROR(INDEX('Etsy Import'!$A:$CZ,20,Settings!$C$20)&"","") | B20: =IFERROR(INDEX('Etsy Import'!$A:$CZ,20,Settings!$C$21)&"","") | C20: =IFERROR(INDEX('Etsy Import'!$A:$CZ,20,Settings!$C$22)&"","") | D20: =IF(A20="","",IFERROR(VALUE(SUBSTITUTE(SUBSTITUTE(INDEX('Etsy Import'!$A:$CZ,20,Settings!$C$23)&"","$",""),",","")),0)) | E20: =IF(A20="","",IFERROR(VALUE(SUBSTITUTE(SUBSTITUTE(INDEX('Etsy Import'!$A:$CZ,20,Settings!$C$24)&"","$",""),",","")),0)) | F20: =IF(A20="","",D20*E20) | G20: =IF(A20="","",IF(C20="",1,COUNTIF($C$2:$C$1501,C20))) | H20: =IF(A20="","",IFERROR(VALUE(SUBSTITUTE(SUBSTITUTE(INDEX('Etsy Import'!$A:$CZ,20,Settings!$C$25)&"","$",""),",","")),0)/IF(Settings!$B$27="Yes",G20,1)) | I20: =IF(A20="","",IFERROR(VALUE(SUBSTITUTE(SUBSTITUTE(INDEX('Etsy Import'!$A:$CZ,20,Settings!$C$26)&"","$",""),",","")),0)/IF(Settings!$B$27="Yes",G20,1)) | J20: =IF(A20="","",F20+H20-I20) | K20: =IF(A20="","",IFERROR(IF(B20="",NA(),MATCH(B20,Products!$B$5:$B$204,0)),IFERROR(MATCH(A20,Products!$A$5:$A$204,0),""))) | L20: =IF(A20="","",IF(K20="","⚠ not in Products",INDEX(Products!$A$5:$A$204,K20))) | M20: =IF(A20="","",J20*(IFERROR(INDEX(Settings!$B$5:$B$9,MATCH("Etsy",Settings!$A$5:$A$9,0)),0)+IFERROR(INDEX(Settings!$E$5:$E$9,MATCH("Etsy",Settings!$A$5:$A$9,0)),0)+IFERROR(INDEX(Settings!$G$5:$G$9,MATCH("Etsy",Settings!$A$5:$A$9,0)),0))+(IFERROR(INDEX(Settings!$C$5:$C$9,MATCH("Etsy",Settings!$A$5:$A$9,0)),0)+IFERROR(INDEX(Settings!$F$5:$F$9,MATCH("Etsy",Settings!$A$5:$A$9,0)),0))/G20+IFERROR(INDEX(Settings!$D$5:$D$9,MATCH("Etsy",Settings!$A$5:$A$9,0)),0)*D20) | N20: =IF(A20="","",IF(K20="",0,D20*INDEX(Products!$I$5:$I$204,K20))) | O20: =IF(A20="","",IF(K20="",0,J20*INDEX(Products!$H$5:$H$204,K20))) | P20: =IF(A20="","",J20-M20-N20-O20)
A21: =IFERROR(INDEX('Etsy Import'!$A:$CZ,21,Settings!$C$20)&"","") | B21: =IFERROR(INDEX('Etsy Import'!$A:$CZ,21,Settings!$C$21)&"","") | C21: =IFERROR(INDEX('Etsy Import'!$A:$CZ,21,Settings!$C$22)&"","") | D21: =IF(A21="","",IFERROR(VALUE(SUBSTITUTE(SUBSTITUTE(INDEX('Etsy Import'!$A:$CZ,21,Settings!$C$23)&"","$",""),",","")),0)) | E21: =IF(A21="","",IFERROR(VALUE(SUBSTITUTE(SUBSTITUTE(INDEX('Etsy Import'!$A:$CZ,21,Settings!$C$24)&"","$",""),",","")),0)) | F21: =IF(A21="","",D21*E21) | G21: =IF(A21="","",IF(C21="",1,COUNTIF($C$2:$C$1501,C21))) | H21: =IF(A21="","",IFERROR(VALUE(SUBSTITUTE(SUBSTITUTE(INDEX('Etsy Import'!$A:$CZ,21,Settings!$C$25)&"","$",""),",","")),0)/IF(Settings!$B$27="Yes",G21,1)) | I21: =IF(A21="","",IFERROR(VALUE(SUBSTITUTE(SUBSTITUTE(INDEX('Etsy Import'!$A:$CZ,21,Settings!$C$26)&"","$",""),",","")),0)/IF(Settings!$B$27="Yes",G21,1)) | J21: =IF(A21="","",F21+H21-I21) | K21: =IF(A21="","",IFERROR(IF(B21="",NA(),MATCH(B21,Products!$B$5:$B$204,0)),IFERROR(MATCH(A21,Products!$A$5:$A$204,0),""))) | L21: =IF(A21="","",IF(K21="","⚠ not in Products",INDEX(Products!$A$5:$A$204,K21))) | M21: =IF(A21="","",J21*(IFERROR(INDEX(Settings!$B$5:$B$9,MATCH("Etsy",Settings!$A$5:$A$9,0)),0)+IFERROR(INDEX(Settings!$E$5:$E$9,MATCH("Etsy",Settings!$A$5:$A$9,0)),0)+IFERROR(INDEX(Settings!$G$5:$G$9,MATCH("Etsy",Settings!$A$5:$A$9,0)),0))+(IFERROR(INDEX(Settings!$C$5:$C$9,MATCH("Etsy",Settings!$A$5:$A$9,0)),0)+IFERROR(INDEX(Settings!$F$5:$F$9,MATCH("Etsy",Settings!$A$5:$A$9,0)),0))/G21+IFERROR(INDEX(Settings!$D$5:$D$9,MATCH("Etsy",Settings!$A$5:$A$9,0)),0)*D21) | N21: =IF(A21="","",IF(K21="",0,D21*INDEX(Products!$I$5:$I$204,K21))) | O21: =IF(A21="","",IF(K21="",0,J21*INDEX(Products!$H$5:$H$204,K21))) | P21: =IF(A21="","",J21-M21-N21-O21)
A22: =IFERROR(INDEX('Etsy Import'!$A:$CZ,22,Settings!$C$20)&"","") | B22: =IFERROR(INDEX('Etsy Import'!$A:$CZ,22,Settings!$C$21)&"","") | C22: =IFERROR(INDEX('Etsy Import'!$A:$CZ,22,Settings!$C$22)&"","") | D22: =IF(A22="","",IFERROR(VALUE(SUBSTITUTE(SUBSTITUTE(INDEX('Etsy Import'!$A:$CZ,22,Settings!$C$23)&"","$",""),",","")),0)) | E22: =IF(A22="","",IFERROR(VALUE(SUBSTITUTE(SUBSTITUTE(INDEX('Etsy Import'!$A:$CZ,22,Settings!$C$24)&"","$",""),",","")),0)) | F22: =IF(A22="","",D22*E22) | G22: =IF(A22="","",IF(C22="",1,COUNTIF($C$2:$C$1501,C22))) | H22: =IF(A22="","",IFERROR(VALUE(SUBSTITUTE(SUBSTITUTE(INDEX('Etsy Import'!$A:$CZ,22,Settings!$C$25)&"","$",""),",","")),0)/IF(Settings!$B$27="Yes",G22,1)) | I22: =IF(A22="","",IFERROR(VALUE(SUBSTITUTE(SUBSTITUTE(INDEX('Etsy Import'!$A:$CZ,22,Settings!$C$26)&"","$",""),",","")),0)/IF(Settings!$B$27="Yes",G22,1)) | J22: =IF(A22="","",F22+H22-I22) | K22: =IF(A22="","",IFERROR(IF(B22="",NA(),MATCH(B22,Products!$B$5:$B$204,0)),IFERROR(MATCH(A22,Products!$A$5:$A$204,0),""))) | L22: =IF(A22="","",IF(K22="","⚠ not in Products",INDEX(Products!$A$5:$A$204,K22))) | M22: =IF(A22="","",J22*(IFERROR(INDEX(Settings!$B$5:$B$9,MATCH("Etsy",Settings!$A$5:$A$9,0)),0)+IFERROR(INDEX(Settings!$E$5:$E$9,MATCH("Etsy",Settings!$A$5:$A$9,0)),0)+IFERROR(INDEX(Settings!$G$5:$G$9,MATCH("Etsy",Settings!$A$5:$A$9,0)),0))+(IFERROR(INDEX(Settings!$C$5:$C$9,MATCH("Etsy",Settings!$A$5:$A$9,0)),0)+IFERROR(INDEX(Settings!$F$5:$F$9,MATCH("Etsy",Settings!$A$5:$A$9,0)),0))/G22+IFERROR(INDEX(Settings!$D$5:$D$9,MATCH("Etsy",Settings!$A$5:$A$9,0)),0)*D22) | N22: =IF(A22="","",IF(K22="",0,D22*INDEX(Products!$I$5:$I$204,K22))) | O22: =IF(A22="","",IF(K22="",0,J22*INDEX(Products!$H$5:$H$204,K22))) | P22: =IF(A22="","",J22-M22-N22-O22)
A23: =IFERROR(INDEX('Etsy Import'!$A:$CZ,23,Settings!$C$20)&"","") | B23: =IFERROR(INDEX('Etsy Import'!$A:$CZ,23,Settings!$C$21)&"","") | C23: =IFERROR(INDEX('Etsy Import'!$A:$CZ,23,Settings!$C$22)&"","") | D23: =IF(A23="","",IFERROR(VALUE(SUBSTITUTE(SUBSTITUTE(INDEX('Etsy Import'!$A:$CZ,23,Settings!$C$23)&"","$",""),",","")),0)) | E23: =IF(A23="","",IFERROR(VALUE(SUBSTITUTE(SUBSTITUTE(INDEX('Etsy Import'!$A:$CZ,23,Settings!$C$24)&"","$",""),",","")),0)) | F23: =IF(A23="","",D23*E23) | G23: =IF(A23="","",IF(C23="",1,COUNTIF($C$2:$C$1501,C23))) | H23: =IF(A23="","",IFERROR(VALUE(SUBSTITUTE(SUBSTITUTE(INDEX('Etsy Import'!$A:$CZ,23,Settings!$C$25)&"","$",""),",","")),0)/IF(Settings!$B$27="Yes",G23,1)) | I23: =IF(A23="","",IFERROR(VALUE(SUBSTITUTE(SUBSTITUTE(INDEX('Etsy Import'!$A:$CZ,23,Settings!$C$26)&"","$",""),",","")),0)/IF(Settings!$B$27="Yes",G23,1)) | J23: =IF(A23="","",F23+H23-I23) | K23: =IF(A23="","",IFERROR(IF(B23="",NA(),MATCH(B23,Products!$B$5:$B$204,0)),IFERROR(MATCH(A23,Products!$A$5:$A$204,0),""))) | L23: =IF(A23="","",IF(K23="","⚠ not in Products",INDEX(Products!$A$5:$A$204,K23))) | M23: =IF(A23="","",J23*(IFERROR(INDEX(Settings!$B$5:$B$9,MATCH("Etsy",Settings!$A$5:$A$9,0)),0)+IFERROR(INDEX(Settings!$E$5:$E$9,MATCH("Etsy",Settings!$A$5:$A$9,0)),0)+IFERROR(INDEX(Settings!$G$5:$G$9,MATCH("Etsy",Settings!$A$5:$A$9,0)),0))+(IFERROR(INDEX(Settings!$C$5:$C$9,MATCH("Etsy",Settings!$A$5:$A$9,0)),0)+IFERROR(INDEX(Settings!$F$5:$F$9,MATCH("Etsy",Settings!$A$5:$A$9,0)),0))/G23+IFERROR(INDEX(Settings!$D$5:$D$9,MATCH("Etsy",Settings!$A$5:$A$9,0)),0)*D23) | N23: =IF(A23="","",IF(K23="",0,D23*INDEX(Products!$I$5:$I$204,K23))) | O23: =IF(A23="","",IF(K23="",0,J23*INDEX(Products!$H$5:$H$204,K23))) | P23: =IF(A23="","",J23-M23-N23-O23)
A24: =IFERROR(INDEX('Etsy Import'!$A:$CZ,24,Settings!$C$20)&"","") | B24: =IFERROR(INDEX('Etsy Import'!$A:$CZ,24,Settings!$C$21)&"","") | C24: =IFERROR(INDEX('Etsy Import'!$A:$CZ,24,Settings!$C$22)&"","") | D24: =IF(A24="","",IFERROR(VALUE(SUBSTITUTE(SUBSTITUTE(INDEX('Etsy Import'!$A:$CZ,24,Settings!$C$23)&"","$",""),",","")),0)) | E24: =IF(A24="","",IFERROR(VALUE(SUBSTITUTE(SUBSTITUTE(INDEX('Etsy Import'!$A:$CZ,24,Settings!$C$24)&"","$",""),",","")),0)) | F24: =IF(A24="","",D24*E24) | G24: =IF(A24="","",IF(C24="",1,COUNTIF($C$2:$C$1501,C24))) | H24: =IF(A24="","",IFERROR(VALUE(SUBSTITUTE(SUBSTITUTE(INDEX('Etsy Import'!$A:$CZ,24,Settings!$C$25)&"","$",""),",","")),0)/IF(Settings!$B$27="Yes",G24,1)) | I24: =IF(A24="","",IFERROR(VALUE(SUBSTITUTE(SUBSTITUTE(INDEX('Etsy Import'!$A:$CZ,24,Settings!$C$26)&"","$",""),",","")),0)/IF(Settings!$B$27="Yes",G24,1)) | J24: =IF(A24="","",F24+H24-I24) | K24: =IF(A24="","",IFERROR(IF(B24="",NA(),MATCH(B24,Products!$B$5:$B$204,0)),IFERROR(MATCH(A24,Products!$A$5:$A$204,0),""))) | L24: =IF(A24="","",IF(K24="","⚠ not in Products",INDEX(Products!$A$5:$A$204,K24))) | M24: =IF(A24="","",J24*(IFERROR(INDEX(Settings!$B$5:$B$9,MATCH("Etsy",Settings!$A$5:$A$9,0)),0)+IFERROR(INDEX(Settings!$E$5:$E$9,MATCH("Etsy",Settings!$A$5:$A$9,0)),0)+IFERROR(INDEX(Settings!$G$5:$G$9,MATCH("Etsy",Settings!$A$5:$A$9,0)),0))+(IFERROR(INDEX(Settings!$C$5:$C$9,MATCH("Etsy",Settings!$A$5:$A$9,0)),0)+IFERROR(INDEX(Settings!$F$5:$F$9,MATCH("Etsy",Settings!$A$5:$A$9,0)),0))/G24+IFERROR(INDEX(Settings!$D$5:$D$9,MATCH("Etsy",Settings!$A$5:$A$9,0)),0)*D24) | N24: =IF(A24="","",IF(K24="",0,D24*INDEX(Products!$I$5:$I$204,K24))) | O24: =IF(A24="","",IF(K24="",0,J24*INDEX(Products!$H$5:$H$204,K24))) | P24: =IF(A24="","",J24-M24-N24-O24)
A25: =IFERROR(INDEX('Etsy Import'!$A:$CZ,25,Settings!$C$20)&"","") | B25: =IFERROR(INDEX('Etsy Import'!$A:$CZ,25,Settings!$C$21)&"","") | C25: =IFERROR(INDEX('Etsy Import'!$A:$CZ,25,Settings!$C$22)&"","") | D25: =IF(A25="","",IFERROR(VALUE(SUBSTITUTE(SUBSTITUTE(INDEX('Etsy Import'!$A:$CZ,25,Settings!$C$23)&"","$",""),",","")),0)) | E25: =IF(A25="","",IFERROR(VALUE(SUBSTITUTE(SUBSTITUTE(INDEX('Etsy Import'!$A:$CZ,25,Settings!$C$24)&"","$",""),",","")),0)) | F25: =IF(A25="","",D25*E25) | G25: =IF(A25="","",IF(C25="",1,COUNTIF($C$2:$C$1501,C25))) | H25: =IF(A25="","",IFERROR(VALUE(SUBSTITUTE(SUBSTITUTE(INDEX('Etsy Import'!$A:$CZ,25,Settings!$C$25)&"","$",""),",","")),0)/IF(Settings!$B$27="Yes",G25,1)) | I25: =IF(A25="","",IFERROR(VALUE(SUBSTITUTE(SUBSTITUTE(INDEX('Etsy Import'!$A:$CZ,25,Settings!$C$26)&"","$",""),",","")),0)/IF(Settings!$B$27="Yes",G25,1)) | J25: =IF(A25="","",F25+H25-I25) | K25: =IF(A25="","",IFERROR(IF(B25="",NA(),MATCH(B25,Products!$B$5:$B$204,0)),IFERROR(MATCH(A25,Products!$A$5:$A$204,0),""))) | L25: =IF(A25="","",IF(K25="","⚠ not in Products",INDEX(Products!$A$5:$A$204,K25))) | M25: =IF(A25="","",J25*(IFERROR(INDEX(Settings!$B$5:$B$9,MATCH("Etsy",Settings!$A$5:$A$9,0)),0)+IFERROR(INDEX(Settings!$E$5:$E$9,MATCH("Etsy",Settings!$A$5:$A$9,0)),0)+IFERROR(INDEX(Settings!$G$5:$G$9,MATCH("Etsy",Settings!$A$5:$A$9,0)),0))+(IFERROR(INDEX(Settings!$C$5:$C$9,MATCH("Etsy",Settings!$A$5:$A$9,0)),0)+IFERROR(INDEX(Settings!$F$5:$F$9,MATCH("Etsy",Settings!$A$5:$A$9,0)),0))/G25+IFERROR(INDEX(Settings!$D$5:$D$9,MATCH("Etsy",Settings!$A$5:$A$9,0)),0)*D25) | N25: =IF(A25="","",IF(K25="",0,D25*INDEX(Products!$I$5:$I$204,K25))) | O25: =IF(A25="","",IF(K25="",0,J25*INDEX(Products!$H$5:$H$204,K25))) | P25: =IF(A25="","",J25-M25-N25-O25)
A26: =IFERROR(INDEX('Etsy Import'!$A:$CZ,26,Settings!$C$20)&"","") | B26: =IFERROR(INDEX('Etsy Import'!$A:$CZ,26,Settings!$C$21)&"","") | C26: =IFERROR(INDEX('Etsy Import'!$A:$CZ,26,Settings!$C$22)&"","") | D26: =IF(A26="","",IFERROR(VALUE(SUBSTITUTE(SUBSTITUTE(INDEX('Etsy Import'!$A:$CZ,26,Settings!$C$23)&"","$",""),",","")),0)) | E26: =IF(A26="","",IFERROR(VALUE(SUBSTITUTE(SUBSTITUTE(INDEX('Etsy Import'!$A:$CZ,26,Settings!$C$24)&"","$",""),",","")),0)) | F26: =IF(A26="","",D26*E26) | G26: =IF(A26="","",IF(C26="",1,COUNTIF($C$2:$C$1501,C26))) | H26: =IF(A26="","",IFERROR(VALUE(SUBSTITUTE(SUBSTITUTE(INDEX('Etsy Import'!$A:$CZ,26,Settings!$C$25)&"","$",""),",","")),0)/IF(Settings!$B$27="Yes",G26,1)) | I26: =IF(A26="","",IFERROR(VALUE(SUBSTITUTE(SUBSTITUTE(INDEX('Etsy Import'!$A:$CZ,26,Settings!$C$26)&"","$",""),",","")),0)/IF(Settings!$B$27="Yes",G26,1)) | J26: =IF(A26="","",F26+H26-I26) | K26: =IF(A26="","",IFERROR(IF(B26="",NA(),MATCH(B26,Products!$B$5:$B$204,0)),IFERROR(MATCH(A26,Products!$A$5:$A$204,0),""))) | L26: =IF(A26="","",IF(K26="","⚠ not in Products",INDEX(Products!$A$5:$A$204,K26))) | M26: =IF(A26="","",J26*(IFERROR(INDEX(Settings!$B$5:$B$9,MATCH("Etsy",Settings!$A$5:$A$9,0)),0)+IFERROR(INDEX(Settings!$E$5:$E$9,MATCH("Etsy",Settings!$A$5:$A$9,0)),0)+IFERROR(INDEX(Settings!$G$5:$G$9,MATCH("Etsy",Settings!$A$5:$A$9,0)),0))+(IFERROR(INDEX(Settings!$C$5:$C$9,MATCH("Etsy",Settings!$A$5:$A$9,0)),0)+IFERROR(INDEX(Settings!$F$5:$F$9,MATCH("Etsy",Settings!$A$5:$A$9,0)),0))/G26+IFERROR(INDEX(Settings!$D$5:$D$9,MATCH("Etsy",Settings!$A$5:$A$9,0)),0)*D26) | N26: =IF(A26="","",IF(K26="",0,D26*INDEX(Products!$I$5:$I$204,K26))) | O26: =IF(A26="","",IF(K26="",0,J26*INDEX(Products!$H$5:$H$204,K26))) | P26: =IF(A26="","",J26-M26-N26-O26)
A27: =IFERROR(INDEX('Etsy Import'!$A:$CZ,27,Settings!$C$20)&"","") | B27: =IFERROR(INDEX('Etsy Import'!$A:$CZ,27,Settings!$C$21)&"","") | C27: =IFERROR(INDEX('Etsy Import'!$A:$CZ,27,Settings!$C$22)&"","") | D27: =IF(A27="","",IFERROR(VALUE(SUBSTITUTE(SUBSTITUTE(INDEX('Etsy Import'!$A:$CZ,27,Settings!$C$23)&"","$",""),",","")),0)) | E27: =IF(A27="","",IFERROR(VALUE(SUBSTITUTE(SUBSTITUTE(INDEX('Etsy Import'!$A:$CZ,27,Settings!$C$24)&"","$",""),",","")),0)) | F27: =IF(A27="","",D27*E27) | G27: =IF(A27="","",IF(C27="",1,COUNTIF($C$2:$C$1501,C27))) | H27: =IF(A27="","",IFERROR(VALUE(SUBSTITUTE(SUBSTITUTE(INDEX('Etsy Import'!$A:$CZ,27,Settings!$C$25)&"","$",""),",","")),0)/IF(Settings!$B$27="Yes",G27,1)) | I27: =IF(A27="","",IFERROR(VALUE(SUBSTITUTE(SUBSTITUTE(INDEX('Etsy Import'!$A:$CZ,27,Settings!$C$26)&"","$",""),",","")),0)/IF(Settings!$B$27="Yes",G27,1)) | J27: =IF(A27="","",F27+H27-I27) | K27: =IF(A27="","",IFERROR(IF(B27="",NA(),MATCH(B27,Products!$B$5:$B$204,0)),IFERROR(MATCH(A27,Products!$A$5:$A$204,0),""))) | L27: =IF(A27="","",IF(K27="","⚠ not in Products",INDEX(Products!$A$5:$A$204,K27))) | M27: =IF(A27="","",J27*(IFERROR(INDEX(Settings!$B$5:$B$9,MATCH("Etsy",Settings!$A$5:$A$9,0)),0)+IFERROR(INDEX(Settings!$E$5:$E$9,MATCH("Etsy",Settings!$A$5:$A$9,0)),0)+IFERROR(INDEX(Settings!$G$5:$G$9,MATCH("Etsy",Settings!$A$5:$A$9,0)),0))+(IFERROR(INDEX(Settings!$C$5:$C$9,MATCH("Etsy",Settings!$A$5:$A$9,0)),0)+IFERROR(INDEX(Settings!$F$5:$F$9,MATCH("Etsy",Settings!$A$5:$A$9,0)),0))/G27+IFERROR(INDEX(Settings!$D$5:$D$9,MATCH("Etsy",Settings!$A$5:$A$9,0)),0)*D27) | N27: =IF(A27="","",IF(K27="",0,D27*INDEX(Products!$I$5:$I$204,K27))) | O27: =IF(A27="","",IF(K27="",0,J27*INDEX(Products!$H$5:$H$204,K27))) | P27: =IF(A27="","",J27-M27-N27-O27)
A28: =IFERROR(INDEX('Etsy Import'!$A:$CZ,28,Settings!$C$20)&"","") | B28: =IFERROR(INDEX('Etsy Import'!$A:$CZ,28,Settings!$C$21)&"","") | C28: =IFERROR(INDEX('Etsy Import'!$A:$CZ,28,Settings!$C$22)&"","") | D28: =IF(A28="","",IFERROR(VALUE(SUBSTITUTE(SUBSTITUTE(INDEX('Etsy Import'!$A:$CZ,28,Settings!$C$23)&"","$",""),",","")),0)) | E28: =IF(A28="","",IFERROR(VALUE(SUBSTITUTE(SUBSTITUTE(INDEX('Etsy Import'!$A:$CZ,28,Settings!$C$24)&"","$",""),",","")),0)) | F28: =IF(A28="","",D28*E28) | G28: =IF(A28="","",IF(C28="",1,COUNTIF($C$2:$C$1501,C28))) | H28: =IF(A28="","",IFERROR(VALUE(SUBSTITUTE(SUBSTITUTE(INDEX('Etsy Import'!$A:$CZ,28,Settings!$C$25)&"","$",""),",","")),0)/IF(Settings!$B$27="Yes",G28,1)) | I28: =IF(A28="","",IFERROR(VALUE(SUBSTITUTE(SUBSTITUTE(INDEX('Etsy Import'!$A:$CZ,28,Settings!$C$26)&"","$",""),",","")),0)/IF(Settings!$B$27="Yes",G28,1)) | J28: =IF(A28="","",F28+H28-I28) | K28: =IF(A28="","",IFERROR(IF(B28="",NA(),MATCH(B28,Products!$B$5:$B$204,0)),IFERROR(MATCH(A28,Products!$A$5:$A$204,0),""))) | L28: =IF(A28="","",IF(K28="","⚠ not in Products",INDEX(Products!$A$5:$A$204,K28))) | M28: =IF(A28="","",J28*(IFERROR(INDEX(Settings!$B$5:$B$9,MATCH("Etsy",Settings!$A$5:$A$9,0)),0)+IFERROR(INDEX(Settings!$E$5:$E$9,MATCH("Etsy",Settings!$A$5:$A$9,0)),0)+IFERROR(INDEX(Settings!$G$5:$G$9,MATCH("Etsy",Settings!$A$5:$A$9,0)),0))+(IFERROR(INDEX(Settings!$C$5:$C$9,MATCH("Etsy",Settings!$A$5:$A$9,0)),0)+IFERROR(INDEX(Settings!$F$5:$F$9,MATCH("Etsy",Settings!$A$5:$A$9,0)),0))/G28+IFERROR(INDEX(Settings!$D$5:$D$9,MATCH("Etsy",Settings!$A$5:$A$9,0)),0)*D28) | N28: =IF(A28="","",IF(K28="",0,D28*INDEX(Products!$I$5:$I$204,K28))) | O28: =IF(A28="","",IF(K28="",0,J28*INDEX(Products!$H$5:$H$204,K28))) | P28: =IF(A28="","",J28-M28-N28-O28)
A29: =IFERROR(INDEX('Etsy Import'!$A:$CZ,29,Settings!$C$20)&"","") | B29: =IFERROR(INDEX('Etsy Import'!$A:$CZ,29,Settings!$C$21)&"","") | C29: =IFERROR(INDEX('Etsy Import'!$A:$CZ,29,Settings!$C$22)&"","") | D29: =IF(A29="","",IFERROR(VALUE(SUBSTITUTE(SUBSTITUTE(INDEX('Etsy Import'!$A:$CZ,29,Settings!$C$23)&"","$",""),",","")),0)) | E29: =IF(A29="","",IFERROR(VALUE(SUBSTITUTE(SUBSTITUTE(INDEX('Etsy Import'!$A:$CZ,29,Settings!$C$24)&"","$",""),",","")),0)) | F29: =IF(A29="","",D29*E29) | G29: =IF(A29="","",IF(C29="",1,COUNTIF($C$2:$C$1501,C29))) | H29: =IF(A29="","",IFERROR(VALUE(SUBSTITUTE(SUBSTITUTE(INDEX('Etsy Import'!$A:$CZ,29,Settings!$C$25)&"","$",""),",","")),0)/IF(Settings!$B$27="Yes",G29,1)) | I29: =IF(A29="","",IFERROR(VALUE(SUBSTITUTE(SUBSTITUTE(INDEX('Etsy Import'!$A:$CZ,29,Settings!$C$26)&"","$",""),",","")),0)/IF(Settings!$B$27="Yes",G29,1)) | J29: =IF(A29="","",F29+H29-I29) | K29: =IF(A29="","",IFERROR(IF(B29="",NA(),MATCH(B29,Products!$B$5:$B$204,0)),IFERROR(MATCH(A29,Products!$A$5:$A$204,0),""))) | L29: =IF(A29="","",IF(K29="","⚠ not in Products",INDEX(Products!$A$5:$A$204,K29))) | M29: =IF(A29="","",J29*(IFERROR(INDEX(Settings!$B$5:$B$9,MATCH("Etsy",Settings!$A$5:$A$9,0)),0)+IFERROR(INDEX(Settings!$E$5:$E$9,MATCH("Etsy",Settings!$A$5:$A$9,0)),0)+IFERROR(INDEX(Settings!$G$5:$G$9,MATCH("Etsy",Settings!$A$5:$A$9,0)),0))+(IFERROR(INDEX(Settings!$C$5:$C$9,MATCH("Etsy",Settings!$A$5:$A$9,0)),0)+IFERROR(INDEX(Settings!$F$5:$F$9,MATCH("Etsy",Settings!$A$5:$A$9,0)),0))/G29+IFERROR(INDEX(Settings!$D$5:$D$9,MATCH("Etsy",Settings!$A$5:$A$9,0)),0)*D29) | N29: =IF(A29="","",IF(K29="",0,D29*INDEX(Products!$I$5:$I$204,K29))) | O29: =IF(A29="","",IF(K29="",0,J29*INDEX(Products!$H$5:$H$204,K29))) | P29: =IF(A29="","",J29-M29-N29-O29)
A30: =IFERROR(INDEX('Etsy Import'!$A:$CZ,30,Settings!$C$20)&"","") | B30: =IFERROR(INDEX('Etsy Import'!$A:$CZ,30,Settings!$C$21)&"","") | C30: =IFERROR(INDEX('Etsy Import'!$A:$CZ,30,Settings!$C$22)&"","") | D30: =IF(A30="","",IFERROR(VALUE(SUBSTITUTE(SUBSTITUTE(INDEX('Etsy Import'!$A:$CZ,30,Settings!$C$23)&"","$",""),",","")),0)) | E30: =IF(A30="","",IFERROR(VALUE(SUBSTITUTE(SUBSTITUTE(INDEX('Etsy Import'!$A:$CZ,30,Settings!$C$24)&"","$",""),",","")),0)) | F30: =IF(A30="","",D30*E30) | G30: =IF(A30="","",IF(C30="",1,COUNTIF($C$2:$C$1501,C30))) | H30: =IF(A30="","",IFERROR(VALUE(SUBSTITUTE(SUBSTITUTE(INDEX('Etsy Import'!$A:$CZ,30,Settings!$C$25)&"","$",""),",","")),0)/IF(Settings!$B$27="Yes",G30,1)) | I30: =IF(A30="","",IFERROR(VALUE(SUBSTITUTE(SUBSTITUTE(INDEX('Etsy Import'!$A:$CZ,30,Settings!$C$26)&"","$",""),",","")),0)/IF(Settings!$B$27="Yes",G30,1)) | J30: =IF(A30="","",F30+H30-I30) | K30: =IF(A30="","",IFERROR(IF(B30="",NA(),MATCH(B30,Products!$B$5:$B$204,0)),IFERROR(MATCH(A30,Products!$A$5:$A$204,0),""))) | L30: =IF(A30="","",IF(K30="","⚠ not in Products",INDEX(Products!$A$5:$A$204,K30))) | M30: =IF(A30="","",J30*(IFERROR(INDEX(Settings!$B$5:$B$9,MATCH("Etsy",Settings!$A$5:$A$9,0)),0)+IFERROR(INDEX(Settings!$E$5:$E$9,MATCH("Etsy",Settings!$A$5:$A$9,0)),0)+IFERROR(INDEX(Settings!$G$5:$G$9,MATCH("Etsy",Settings!$A$5:$A$9,0)),0))+(IFERROR(INDEX(Settings!$C$5:$C$9,MATCH("Etsy",Settings!$A$5:$A$9,0)),0)+IFERROR(INDEX(Settings!$F$5:$F$9,MATCH("Etsy",Settings!$A$5:$A$9,0)),0))/G30+IFERROR(INDEX(Settings!$D$5:$D$9,MATCH("Etsy",Settings!$A$5:$A$9,0)),0)*D30) | N30: =IF(A30="","",IF(K30="",0,D30*INDEX(Products!$I$5:$I$204,K30))) | O30: =IF(A30="","",IF(K30="",0,J30*INDEX(Products!$H$5:$H$204,K30))) | P30: =IF(A30="","",J30-M30-N30-O30)
A31: =IFERROR(INDEX('Etsy Import'!$A:$CZ,31,Settings!$C$20)&"","") | B31: =IFERROR(INDEX('Etsy Import'!$A:$CZ,31,Settings!$C$21)&"","") | C31: =IFERROR(INDEX('Etsy Import'!$A:$CZ,31,Settings!$C$22)&"","") | D31: =IF(A31="","",IFERROR(VALUE(SUBSTITUTE(SUBSTITUTE(INDEX('Etsy Import'!$A:$CZ,31,Settings!$C$23)&"","$",""),",","")),0)) | E31: =IF(A31="","",IFERROR(VALUE(SUBSTITUTE(SUBSTITUTE(INDEX('Etsy Import'!$A:$CZ,31,Settings!$C$24)&"","$",""),",","")),0)) | F31: =IF(A31="","",D31*E31) | G31: =IF(A31="","",IF(C31="",1,COUNTIF($C$2:$C$1501,C31))) | H31: =IF(A31="","",IFERROR(VALUE(SUBSTITUTE(SUBSTITUTE(INDEX('Etsy Import'!$A:$CZ,31,Settings!$C$25)&"","$",""),",","")),0)/IF(Settings!$B$27="Yes",G31,1)) | I31: =IF(A31="","",IFERROR(VALUE(SUBSTITUTE(SUBSTITUTE(INDEX('Etsy Import'!$A:$CZ,31,Settings!$C$26)&"","$",""),",","")),0)/IF(Settings!$B$27="Yes",G31,1)) | J31: =IF(A31="","",F31+H31-I31) | K31: =IF(A31="","",IFERROR(IF(B31="",NA(),MATCH(B31,Products!$B$5:$B$204,0)),IFERROR(MATCH(A31,Products!$A$5:$A$204,0),""))) | L31: =IF(A31="","",IF(K31="","⚠ not in Products",INDEX(Products!$A$5:$A$204,K31))) | M31: =IF(A31="","",J31*(IFERROR(INDEX(Settings!$B$5:$B$9,MATCH("Etsy",Settings!$A$5:$A$9,0)),0)+IFERROR(INDEX(Settings!$E$5:$E$9,MATCH("Etsy",Settings!$A$5:$A$9,0)),0)+IFERROR(INDEX(Settings!$G$5:$G$9,MATCH("Etsy",Settings!$A$5:$A$9,0)),0))+(IFERROR(INDEX(Settings!$C$5:$C$9,MATCH("Etsy",Settings!$A$5:$A$9,0)),0)+IFERROR(INDEX(Settings!$F$5:$F$9,MATCH("Etsy",Settings!$A$5:$A$9,0)),0))/G31+IFERROR(INDEX(Settings!$D$5:$D$9,MATCH("Etsy",Settings!$A$5:$A$9,0)),0)*D31) | N31: =IF(A31="","",IF(K31="",0,D31*INDEX(Products!$I$5:$I$204,K31))) | O31: =IF(A31="","",IF(K31="",0,J31*INDEX(Products!$H$5:$H$204,K31))) | P31: =IF(A31="","",J31-M31-N31-O31)
A32: =IFERROR(INDEX('Etsy Import'!$A:$CZ,32,Settings!$C$20)&"","") | B32: =IFERROR(INDEX('Etsy Import'!$A:$CZ,32,Settings!$C$21)&"","") | C32: =IFERROR(INDEX('Etsy Import'!$A:$CZ,32,Settings!$C$22)&"","") | D32: =IF(A32="","",IFERROR(VALUE(SUBSTITUTE(SUBSTITUTE(INDEX('Etsy Import'!$A:$CZ,32,Settings!$C$23)&"","$",""),",","")),0)) | E32: =IF(A32="","",IFERROR(VALUE(SUBSTITUTE(SUBSTITUTE(INDEX('Etsy Import'!$A:$CZ,32,Settings!$C$24)&"","$",""),",","")),0)) | F32: =IF(A32="","",D32*E32) | G32: =IF(A32="","",IF(C32="",1,COUNTIF($C$2:$C$1501,C32))) | H32: =IF(A32="","",IFERROR(VALUE(SUBSTITUTE(SUBSTITUTE(INDEX('Etsy Import'!$A:$CZ,32,Settings!$C$25)&"","$",""),",","")),0)/IF(Settings!$B$27="Yes",G32,1)) | I32: =IF(A32="","",IFERROR(VALUE(SUBSTITUTE(SUBSTITUTE(INDEX('Etsy Import'!$A:$CZ,32,Settings!$C$26)&"","$",""),",","")),0)/IF(Settings!$B$27="Yes",G32,1)) | J32: =IF(A32="","",F32+H32-I32) | K32: =IF(A32="","",IFERROR(IF(B32="",NA(),MATCH(B32,Products!$B$5:$B$204,0)),IFERROR(MATCH(A32,Products!$A$5:$A$204,0),""))) | L32: =IF(A32="","",IF(K32="","⚠ not in Products",INDEX(Products!$A$5:$A$204,K32))) | M32: =IF(A32="","",J32*(IFERROR(INDEX(Settings!$B$5:$B$9,MATCH("Etsy",Settings!$A$5:$A$9,0)),0)+IFERROR(INDEX(Settings!$E$5:$E$9,MATCH("Etsy",Settings!$A$5:$A$9,0)),0)+IFERROR(INDEX(Settings!$G$5:$G$9,MATCH("Etsy",Settings!$A$5:$A$9,0)),0))+(IFERROR(INDEX(Settings!$C$5:$C$9,MATCH("Etsy",Settings!$A$5:$A$9,0)),0)+IFERROR(INDEX(Settings!$F$5:$F$9,MATCH("Etsy",Settings!$A$5:$A$9,0)),0))/G32+IFERROR(INDEX(Settings!$D$5:$D$9,MATCH("Etsy",Settings!$A$5:$A$9,0)),0)*D32) | N32: =IF(A32="","",IF(K32="",0,D32*INDEX(Products!$I$5:$I$204,K32))) | O32: =IF(A32="","",IF(K32="",0,J32*INDEX(Products!$H$5:$H$204,K32))) | P32: =IF(A32="","",J32-M32-N32-O32)
A33: =IFERROR(INDEX('Etsy Import'!$A:$CZ,33,Settings!$C$20)&"","") | B33: =IFERROR(INDEX('Etsy Import'!$A:$CZ,33,Settings!$C$21)&"","") | C33: =IFERROR(INDEX('Etsy Import'!$A:$CZ,33,Settings!$C$22)&"","") | D33: =IF(A33="","",IFERROR(VALUE(SUBSTITUTE(SUBSTITUTE(INDEX('Etsy Import'!$A:$CZ,33,Settings!$C$23)&"","$",""),",","")),0)) | E33: =IF(A33="","",IFERROR(VALUE(SUBSTITUTE(SUBSTITUTE(INDEX('Etsy Import'!$A:$CZ,33,Settings!$C$24)&"","$",""),",","")),0)) | F33: =IF(A33="","",D33*E33) | G33: =IF(A33="","",IF(C33="",1,COUNTIF($C$2:$C$1501,C33))) | H33: =IF(A33="","",IFERROR(VALUE(SUBSTITUTE(SUBSTITUTE(INDEX('Etsy Import'!$A:$CZ,33,Settings!$C$25)&"","$",""),",","")),0)/IF(Settings!$B$27="Yes",G33,1)) | I33: =IF(A33="","",IFERROR(VALUE(SUBSTITUTE(SUBSTITUTE(INDEX('Etsy Import'!$A:$CZ,33,Settings!$C$26)&"","$",""),",","")),0)/IF(Settings!$B$27="Yes",G33,1)) | J33: =IF(A33="","",F33+H33-I33) | K33: =IF(A33="","",IFERROR(IF(B33="",NA(),MATCH(B33,Products!$B$5:$B$204,0)),IFERROR(MATCH(A33,Products!$A$5:$A$204,0),""))) | L33: =IF(A33="","",IF(K33="","⚠ not in Products",INDEX(Products!$A$5:$A$204,K33))) | M33: =IF(A33="","",J33*(IFERROR(INDEX(Settings!$B$5:$B$9,MATCH("Etsy",Settings!$A$5:$A$9,0)),0)+IFERROR(INDEX(Settings!$E$5:$E$9,MATCH("Etsy",Settings!$A$5:$A$9,0)),0)+IFERROR(INDEX(Settings!$G$5:$G$9,MATCH("Etsy",Settings!$A$5:$A$9,0)),0))+(IFERROR(INDEX(Settings!$C$5:$C$9,MATCH("Etsy",Settings!$A$5:$A$9,0)),0)+IFERROR(INDEX(Settings!$F$5:$F$9,MATCH("Etsy",Settings!$A$5:$A$9,0)),0))/G33+IFERROR(INDEX(Settings!$D$5:$D$9,MATCH("Etsy",Settings!$A$5:$A$9,0)),0)*D33) | N33: =IF(A33="","",IF(K33="",0,D33*INDEX(Products!$I$5:$I$204,K33))) | O33: =IF(A33="","",IF(K33="",0,J33*INDEX(Products!$H$5:$H$204,K33))) | P33: =IF(A33="","",J33-M33-N33-O33)
A34: =IFERROR(INDEX('Etsy Import'!$A:$CZ,34,Settings!$C$20)&"","") | B34: =IFERROR(INDEX('Etsy Import'!$A:$CZ,34,Settings!$C$21)&"","") | C34: =IFERROR(INDEX('Etsy Import'!$A:$CZ,34,Settings!$C$22)&"","") | D34: =IF(A34="","",IFERROR(VALUE(SUBSTITUTE(SUBSTITUTE(INDEX('Etsy Import'!$A:$CZ,34,Settings!$C$23)&"","$",""),",","")),0)) | E34: =IF(A34="","",IFERROR(VALUE(SUBSTITUTE(SUBSTITUTE(INDEX('Etsy Import'!$A:$CZ,34,Settings!$C$24)&"","$",""),",","")),0)) | F34: =IF(A34="","",D34*E34) | G34: =IF(A34="","",IF(C34="",1,COUNTIF($C$2:$C$1501,C34))) | H34: =IF(A34="","",IFERROR(VALUE(SUBSTITUTE(SUBSTITUTE(INDEX('Etsy Import'!$A:$CZ,34,Settings!$C$25)&"","$",""),",","")),0)/IF(Settings!$B$27="Yes",G34,1)) | I34: =IF(A34="","",IFERROR(VALUE(SUBSTITUTE(SUBSTITUTE(INDEX('Etsy Import'!$A:$CZ,34,Settings!$C$26)&"","$",""),",","")),0)/IF(Settings!$B$27="Yes",G34,1)) | J34: =IF(A34="","",F34+H34-I34) | K34: =IF(A34="","",IFERROR(IF(B34="",NA(),MATCH(B34,Products!$B$5:$B$204,0)),IFERROR(MATCH(A34,Products!$A$5:$A$204,0),""))) | L34: =IF(A34="","",IF(K34="","⚠ not in Products",INDEX(Products!$A$5:$A$204,K34))) | M34: =IF(A34="","",J34*(IFERROR(INDEX(Settings!$B$5:$B$9,MATCH("Etsy",Settings!$A$5:$A$9,0)),0)+IFERROR(INDEX(Settings!$E$5:$E$9,MATCH("Etsy",Settings!$A$5:$A$9,0)),0)+IFERROR(INDEX(Settings!$G$5:$G$9,MATCH("Etsy",Settings!$A$5:$A$9,0)),0))+(IFERROR(INDEX(Settings!$C$5:$C$9,MATCH("Etsy",Settings!$A$5:$A$9,0)),0)+IFERROR(INDEX(Settings!$F$5:$F$9,MATCH("Etsy",Settings!$A$5:$A$9,0)),0))/G34+IFERROR(INDEX(Settings!$D$5:$D$9,MATCH("Etsy",Settings!$A$5:$A$9,0)),0)*D34) | N34: =IF(A34="","",IF(K34="",0,D34*INDEX(Products!$I$5:$I$204,K34))) | O34: =IF(A34="","",IF(K34="",0,J34*INDEX(Products!$H$5:$H$204,K34))) | P34: =IF(A34="","",J34-M34-N34-O34)
A35: =IFERROR(INDEX('Etsy Import'!$A:$CZ,35,Settings!$C$20)&"","") | B35: =IFERROR(INDEX('Etsy Import'!$A:$CZ,35,Settings!$C$21)&"","") | C35: =IFERROR(INDEX('Etsy Import'!$A:$CZ,35,Settings!$C$22)&"","") | D35: =IF(A35="","",IFERROR(VALUE(SUBSTITUTE(SUBSTITUTE(INDEX('Etsy Import'!$A:$CZ,35,Settings!$C$23)&"","$",""),",","")),0)) | E35: =IF(A35="","",IFERROR(VALUE(SUBSTITUTE(SUBSTITUTE(INDEX('Etsy Import'!$A:$CZ,35,Settings!$C$24)&"","$",""),",","")),0)) | F35: =IF(A35="","",D35*E35) | G35: =IF(A35="","",IF(C35="",1,COUNTIF($C$2:$C$1501,C35))) | H35: =IF(A35="","",IFERROR(VALUE(SUBSTITUTE(SUBSTITUTE(INDEX('Etsy Import'!$A:$CZ,35,Settings!$C$25)&"","$",""),",","")),0)/IF(Settings!$B$27="Yes",G35,1)) | I35: =IF(A35="","",IFERROR(VALUE(SUBSTITUTE(SUBSTITUTE(INDEX('Etsy Import'!$A:$CZ,35,Settings!$C$26)&"","$",""),",","")),0)/IF(Settings!$B$27="Yes",G35,1)) | J35: =IF(A35="","",F35+H35-I35) | K35: =IF(A35="","",IFERROR(IF(B35="",NA(),MATCH(B35,Products!$B$5:$B$204,0)),IFERROR(MATCH(A35,Products!$A$5:$A$204,0),""))) | L35: =IF(A35="","",IF(K35="","⚠ not in Products",INDEX(Products!$A$5:$A$204,K35))) | M35: =IF(A35="","",J35*(IFERROR(INDEX(Settings!$B$5:$B$9,MATCH("Etsy",Settings!$A$5:$A$9,0)),0)+IFERROR(INDEX(Settings!$E$5:$E$9,MATCH("Etsy",Settings!$A$5:$A$9,0)),0)+IFERROR(INDEX(Settings!$G$5:$G$9,MATCH("Etsy",Settings!$A$5:$A$9,0)),0))+(IFERROR(INDEX(Settings!$C$5:$C$9,MATCH("Etsy",Settings!$A$5:$A$9,0)),0)+IFERROR(INDEX(Settings!$F$5:$F$9,MATCH("Etsy",Settings!$A$5:$A$9,0)),0))/G35+IFERROR(INDEX(Settings!$D$5:$D$9,MATCH("Etsy",Settings!$A$5:$A$9,0)),0)*D35) | N35: =IF(A35="","",IF(K35="",0,D35*INDEX(Products!$I$5:$I$204,K35))) | O35: =IF(A35="","",IF(K35="",0,J35*INDEX(Products!$H$5:$H$204,K35))) | P35: =IF(A35="","",J35-M35-N35-O35)
A36: =IFERROR(INDEX('Etsy Import'!$A:$CZ,36,Settings!$C$20)&"","") | B36: =IFERROR(INDEX('Etsy Import'!$A:$CZ,36,Settings!$C$21)&"","") | C36: =IFERROR(INDEX('Etsy Import'!$A:$CZ,36,Settings!$C$22)&"","") | D36: =IF(A36="","",IFERROR(VALUE(SUBSTITUTE(SUBSTITUTE(INDEX('Etsy Import'!$A:$CZ,36,Settings!$C$23)&"","$",""),",","")),0)) | E36: =IF(A36="","",IFERROR(VALUE(SUBSTITUTE(SUBSTITUTE(INDEX('Etsy Import'!$A:$CZ,36,Settings!$C$24)&"","$",""),",","")),0)) | F36: =IF(A36="","",D36*E36) | G36: =IF(A36="","",IF(C36="",1,COUNTIF($C$2:$C$1501,C36))) | H36: =IF(A36="","",IFERROR(VALUE(SUBSTITUTE(SUBSTITUTE(INDEX('Etsy Import'!$A:$CZ,36,Settings!$C$25)&"","$",""),",","")),0)/IF(Settings!$B$27="Yes",G36,1)) | I36: =IF(A36="","",IFERROR(VALUE(SUBSTITUTE(SUBSTITUTE(INDEX('Etsy Import'!$A:$CZ,36,Settings!$C$26)&"","$",""),",","")),0)/IF(Settings!$B$27="Yes",G36,1)) | J36: =IF(A36="","",F36+H36-I36) | K36: =IF(A36="","",IFERROR(IF(B36="",NA(),MATCH(B36,Products!$B$5:$B$204,0)),IFERROR(MATCH(A36,Products!$A$5:$A$204,0),""))) | L36: =IF(A36="","",IF(K36="","⚠ not in Products",INDEX(Products!$A$5:$A$204,K36))) | M36: =IF(A36="","",J36*(IFERROR(INDEX(Settings!$B$5:$B$9,MATCH("Etsy",Settings!$A$5:$A$9,0)),0)+IFERROR(INDEX(Settings!$E$5:$E$9,MATCH("Etsy",Settings!$A$5:$A$9,0)),0)+IFERROR(INDEX(Settings!$G$5:$G$9,MATCH("Etsy",Settings!$A$5:$A$9,0)),0))+(IFERROR(INDEX(Settings!$C$5:$C$9,MATCH("Etsy",Settings!$A$5:$A$9,0)),0)+IFERROR(INDEX(Settings!$F$5:$F$9,MATCH("Etsy",Settings!$A$5:$A$9,0)),0))/G36+IFERROR(INDEX(Settings!$D$5:$D$9,MATCH("Etsy",Settings!$A$5:$A$9,0)),0)*D36) | N36: =IF(A36="","",IF(K36="",0,D36*INDEX(Products!$I$5:$I$204,K36))) | O36: =IF(A36="","",IF(K36="",0,J36*INDEX(Products!$H$5:$H$204,K36))) | P36: =IF(A36="","",J36-M36-N36-O36)
A37: =IFERROR(INDEX('Etsy Import'!$A:$CZ,37,Settings!$C$20)&"","") | B37: =IFERROR(INDEX('Etsy Import'!$A:$CZ,37,Settings!$C$21)&"","") | C37: =IFERROR(INDEX('Etsy Import'!$A:$CZ,37,Settings!$C$22)&"","") | D37: =IF(A37="","",IFERROR(VALUE(SUBSTITUTE(SUBSTITUTE(INDEX('Etsy Import'!$A:$CZ,37,Settings!$C$23)&"","$",""),",","")),0)) | E37: =IF(A37="","",IFERROR(VALUE(SUBSTITUTE(SUBSTITUTE(INDEX('Etsy Import'!$A:$CZ,37,Settings!$C$24)&"","$",""),",","")),0)) | F37: =IF(A37="","",D37*E37) | G37: =IF(A37="","",IF(C37="",1,COUNTIF($C$2:$C$1501,C37))) | H37: =IF(A37="","",IFERROR(VALUE(SUBSTITUTE(SUBSTITUTE(INDEX('Etsy Import'!$A:$CZ,37,Settings!$C$25)&"","$",""),",","")),0)/IF(Settings!$B$27="Yes",G37,1)) | I37: =IF(A37="","",IFERROR(VALUE(SUBSTITUTE(SUBSTITUTE(INDEX('Etsy Import'!$A:$CZ,37,Settings!$C$26)&"","$",""),",","")),0)/IF(Settings!$B$27="Yes",G37,1)) | J37: =IF(A37="","",F37+H37-I37) | K37: =IF(A37="","",IFERROR(IF(B37="",NA(),MATCH(B37,Products!$B$5:$B$204,0)),IFERROR(MATCH(A37,Products!$A$5:$A$204,0),""))) | L37: =IF(A37="","",IF(K37="","⚠ not in Products",INDEX(Products!$A$5:$A$204,K37))) | M37: =IF(A37="","",J37*(IFERROR(INDEX(Settings!$B$5:$B$9,MATCH("Etsy",Settings!$A$5:$A$9,0)),0)+IFERROR(INDEX(Settings!$E$5:$E$9,MATCH("Etsy",Settings!$A$5:$A$9,0)),0)+IFERROR(INDEX(Settings!$G$5:$G$9,MATCH("Etsy",Settings!$A$5:$A$9,0)),0))+(IFERROR(INDEX(Settings!$C$5:$C$9,MATCH("Etsy",Settings!$A$5:$A$9,0)),0)+IFERROR(INDEX(Settings!$F$5:$F$9,MATCH("Etsy",Settings!$A$5:$A$9,0)),0))/G37+IFERROR(INDEX(Settings!$D$5:$D$9,MATCH("Etsy",Settings!$A$5:$A$9,0)),0)*D37) | N37: =IF(A37="","",IF(K37="",0,D37*INDEX(Products!$I$5:$I$204,K37))) | O37: =IF(A37="","",IF(K37="",0,J37*INDEX(Products!$H$5:$H$204,K37))) | P37: =IF(A37="","",J37-M37-N37-O37)
A38: =IFERROR(INDEX('Etsy Import'!$A:$CZ,38,Settings!$C$20)&"","") | B38: =IFERROR(INDEX('Etsy Import'!$A:$CZ,38,Settings!$C$21)&"","") | C38: =IFERROR(INDEX('Etsy Import'!$A:$CZ,38,Settings!$C$22)&"","") | D38: =IF(A38="","",IFERROR(VALUE(SUBSTITUTE(SUBSTITUTE(INDEX('Etsy Import'!$A:$CZ,38,Settings!$C$23)&"","$",""),",","")),0)) | E38: =IF(A38="","",IFERROR(VALUE(SUBSTITUTE(SUBSTITUTE(INDEX('Etsy Import'!$A:$CZ,38,Settings!$C$24)&"","$",""),",","")),0)) | F38: =IF(A38="","",D38*E38) | G38: =IF(A38="","",IF(C38="",1,COUNTIF($C$2:$C$1501,C38))) | H38: =IF(A38="","",IFERROR(VALUE(SUBSTITUTE(SUBSTITUTE(INDEX('Etsy Import'!$A:$CZ,38,Settings!$C$25)&"","$",""),",","")),0)/IF(Settings!$B$27="Yes",G38,1)) | I38: =IF(A38="","",IFERROR(VALUE(SUBSTITUTE(SUBSTITUTE(INDEX('Etsy Import'!$A:$CZ,38,Settings!$C$26)&"","$",""),",","")),0)/IF(Settings!$B$27="Yes",G38,1)) | J38: =IF(A38="","",F38+H38-I38) | K38: =IF(A38="","",IFERROR(IF(B38="",NA(),MATCH(B38,Products!$B$5:$B$204,0)),IFERROR(MATCH(A38,Products!$A$5:$A$204,0),""))) | L38: =IF(A38="","",IF(K38="","⚠ not in Products",INDEX(Products!$A$5:$A$204,K38))) | M38: =IF(A38="","",J38*(IFERROR(INDEX(Settings!$B$5:$B$9,MATCH("Etsy",Settings!$A$5:$A$9,0)),0)+IFERROR(INDEX(Settings!$E$5:$E$9,MATCH("Etsy",Settings!$A$5:$A$9,0)),0)+IFERROR(INDEX(Settings!$G$5:$G$9,MATCH("Etsy",Settings!$A$5:$A$9,0)),0))+(IFERROR(INDEX(Settings!$C$5:$C$9,MATCH("Etsy",Settings!$A$5:$A$9,0)),0)+IFERROR(INDEX(Settings!$F$5:$F$9,MATCH("Etsy",Settings!$A$5:$A$9,0)),0))/G38+IFERROR(INDEX(Settings!$D$5:$D$9,MATCH("Etsy",Settings!$A$5:$A$9,0)),0)*D38) | N38: =IF(A38="","",IF(K38="",0,D38*INDEX(Products!$I$5:$I$204,K38))) | O38: =IF(A38="","",IF(K38="",0,J38*INDEX(Products!$H$5:$H$204,K38))) | P38: =IF(A38="","",J38-M38-N38-O38)
A39: =IFERROR(INDEX('Etsy Import'!$A:$CZ,39,Settings!$C$20)&"","") | B39: =IFERROR(INDEX('Etsy Import'!$A:$CZ,39,Settings!$C$21)&"","") | C39: =IFERROR(INDEX('Etsy Import'!$A:$CZ,39,Settings!$C$22)&"","") | D39: =IF(A39="","",IFERROR(VALUE(SUBSTITUTE(SUBSTITUTE(INDEX('Etsy Import'!$A:$CZ,39,Settings!$C$23)&"","$",""),",","")),0)) | E39: =IF(A39="","",IFERROR(VALUE(SUBSTITUTE(SUBSTITUTE(INDEX('Etsy Import'!$A:$CZ,39,Settings!$C$24)&"","$",""),",","")),0)) | F39: =IF(A39="","",D39*E39) | G39: =IF(A39="","",IF(C39="",1,COUNTIF($C$2:$C$1501,C39))) | H39: =IF(A39="","",IFERROR(VALUE(SUBSTITUTE(SUBSTITUTE(INDEX('Etsy Import'!$A:$CZ,39,Settings!$C$25)&"","$",""),",","")),0)/IF(Settings!$B$27="Yes",G39,1)) | I39: =IF(A39="","",IFERROR(VALUE(SUBSTITUTE(SUBSTITUTE(INDEX('Etsy Import'!$A:$CZ,39,Settings!$C$26)&"","$",""),",","")),0)/IF(Settings!$B$27="Yes",G39,1)) | J39: =IF(A39="","",F39+H39-I39) | K39: =IF(A39="","",IFERROR(IF(B39="",NA(),MATCH(B39,Products!$B$5:$B$204,0)),IFERROR(MATCH(A39,Products!$A$5:$A$204,0),""))) | L39: =IF(A39="","",IF(K39="","⚠ not in Products",INDEX(Products!$A$5:$A$204,K39))) | M39: =IF(A39="","",J39*(IFERROR(INDEX(Settings!$B$5:$B$9,MATCH("Etsy",Settings!$A$5:$A$9,0)),0)+IFERROR(INDEX(Settings!$E$5:$E$9,MATCH("Etsy",Settings!$A$5:$A$9,0)),0)+IFERROR(INDEX(Settings!$G$5:$G$9,MATCH("Etsy",Settings!$A$5:$A$9,0)),0))+(IFERROR(INDEX(Settings!$C$5:$C$9,MATCH("Etsy",Settings!$A$5:$A$9,0)),0)+IFERROR(INDEX(Settings!$F$5:$F$9,MATCH("Etsy",Settings!$A$5:$A$9,0)),0))/G39+IFERROR(INDEX(Settings!$D$5:$D$9,MATCH("Etsy",Settings!$A$5:$A$9,0)),0)*D39) | N39: =IF(A39="","",IF(K39="",0,D39*INDEX(Products!$I$5:$I$204,K39))) | O39: =IF(A39="","",IF(K39="",0,J39*INDEX(Products!$H$5:$H$204,K39))) | P39: =IF(A39="","",J39-M39-N39-O39)
A40: =IFERROR(INDEX('Etsy Import'!$A:$CZ,40,Settings!$C$20)&"","") | B40: =IFERROR(INDEX('Etsy Import'!$A:$CZ,40,Settings!$C$21)&"","") | C40: =IFERROR(INDEX('Etsy Import'!$A:$CZ,40,Settings!$C$22)&"","") | D40: =IF(A40="","",IFERROR(VALUE(SUBSTITUTE(SUBSTITUTE(INDEX('Etsy Import'!$A:$CZ,40,Settings!$C$23)&"","$",""),",","")),0)) | E40: =IF(A40="","",IFERROR(VALUE(SUBSTITUTE(SUBSTITUTE(INDEX('Etsy Import'!$A:$CZ,40,Settings!$C$24)&"","$",""),",","")),0)) | F40: =IF(A40="","",D40*E40) | G40: =IF(A40="","",IF(C40="",1,COUNTIF($C$2:$C$1501,C40))) | H40: =IF(A40="","",IFERROR(VALUE(SUBSTITUTE(SUBSTITUTE(INDEX('Etsy Import'!$A:$CZ,40,Settings!$C$25)&"","$",""),",","")),0)/IF(Settings!$B$27="Yes",G40,1)) | I40: =IF(A40="","",IFERROR(VALUE(SUBSTITUTE(SUBSTITUTE(INDEX('Etsy Import'!$A:$CZ,40,Settings!$C$26)&"","$",""),",","")),0)/IF(Settings!$B$27="Yes",G40,1)) | J40: =IF(A40="","",F40+H40-I40) | K40: =IF(A40="","",IFERROR(IF(B40="",NA(),MATCH(B40,Products!$B$5:$B$204,0)),IFERROR(MATCH(A40,Products!$A$5:$A$204,0),""))) | L40: =IF(A40="","",IF(K40="","⚠ not in Products",INDEX(Products!$A$5:$A$204,K40))) | M40: =IF(A40="","",J40*(IFERROR(INDEX(Settings!$B$5:$B$9,MATCH("Etsy",Settings!$A$5:$A$9,0)),0)+IFERROR(INDEX(Settings!$E$5:$E$9,MATCH("Etsy",Settings!$A$5:$A$9,0)),0)+IFERROR(INDEX(Settings!$G$5:$G$9,MATCH("Etsy",Settings!$A$5:$A$9,0)),0))+(IFERROR(INDEX(Settings!$C$5:$C$9,MATCH("Etsy",Settings!$A$5:$A$9,0)),0)+IFERROR(INDEX(Settings!$F$5:$F$9,MATCH("Etsy",Settings!$A$5:$A$9,0)),0))/G40+IFERROR(INDEX(Settings!$D$5:$D$9,MATCH("Etsy",Settings!$A$5:$A$9,0)),0)*D40) | N40: =IF(A40="","",IF(K40="",0,D40*INDEX(Products!$I$5:$I$204,K40))) | O40: =IF(A40="","",IF(K40="",0,J40*INDEX(Products!$H$5:$H$204,K40))) | P40: =IF(A40="","",J40-M40-N40-O40)
A41: =IFERROR(INDEX('Etsy Import'!$A:$CZ,41,Settings!$C$20)&"","") | B41: =IFERROR(INDEX('Etsy Import'!$A:$CZ,41,Settings!$C$21)&"","") | C41: =IFERROR(INDEX('Etsy Import'!$A:$CZ,41,Settings!$C$22)&"","") | D41: =IF(A41="","",IFERROR(VALUE(SUBSTITUTE(SUBSTITUTE(INDEX('Etsy Import'!$A:$CZ,41,Settings!$C$23)&"","$",""),",","")),0)) | E41: =IF(A41="","",IFERROR(VALUE(SUBSTITUTE(SUBSTITUTE(INDEX('Etsy Import'!$A:$CZ,41,Settings!$C$24)&"","$",""),",","")),0)) | F41: =IF(A41="","",D41*E41) | G41: =IF(A41="","",IF(C41="",1,COUNTIF($C$2:$C$1501,C41))) | H41: =IF(A41="","",IFERROR(VALUE(SUBSTITUTE(SUBSTITUTE(INDEX('Etsy Import'!$A:$CZ,41,Settings!$C$25)&"","$",""),",","")),0)/IF(Settings!$B$27="Yes",G41,1)) | I41: =IF(A41="","",IFERROR(VALUE(SUBSTITUTE(SUBSTITUTE(INDEX('Etsy Import'!$A:$CZ,41,Settings!$C$26)&"","$",""),",","")),0)/IF(Settings!$B$27="Yes",G41,1)) | J41: =IF(A41="","",F41+H41-I41) | K41: =IF(A41="","",IFERROR(IF(B41="",NA(),MATCH(B41,Products!$B$5:$B$204,0)),IFERROR(MATCH(A41,Products!$A$5:$A$204,0),""))) | L41: =IF(A41="","",IF(K41="","⚠ not in Products",INDEX(Products!$A$5:$A$204,K41))) | M41: =IF(A41="","",J41*(IFERROR(INDEX(Settings!$B$5:$B$9,MATCH("Etsy",Settings!$A$5:$A$9,0)),0)+IFERROR(INDEX(Settings!$E$5:$E$9,MATCH("Etsy",Settings!$A$5:$A$9,0)),0)+IFERROR(INDEX(Settings!$G$5:$G$9,MATCH("Etsy",Settings!$A$5:$A$9,0)),0))+(IFERROR(INDEX(Settings!$C$5:$C$9,MATCH("Etsy",Settings!$A$5:$A$9,0)),0)+IFERROR(INDEX(Settings!$F$5:$F$9,MATCH("Etsy",Settings!$A$5:$A$9,0)),0))/G41+IFERROR(INDEX(Settings!$D$5:$D$9,MATCH("Etsy",Settings!$A$5:$A$9,0)),0)*D41) | N41: =IF(A41="","",IF(K41="",0,D41*INDEX(Products!$I$5:$I$204,K41))) | O41: =IF(A41="","",IF(K41="",0,J41*INDEX(Products!$H$5:$H$204,K41))) | P41: =IF(A41="","",J41-M41-N41-O41)
A42: =IFERROR(INDEX('Etsy Import'!$A:$CZ,42,Settings!$C$20)&"","") | B42: =IFERROR(INDEX('Etsy Import'!$A:$CZ,42,Settings!$C$21)&"","") | C42: =IFERROR(INDEX('Etsy Import'!$A:$CZ,42,Settings!$C$22)&"","") | D42: =IF(A42="","",IFERROR(VALUE(SUBSTITUTE(SUBSTITUTE(INDEX('Etsy Import'!$A:$CZ,42,Settings!$C$23)&"","$",""),",","")),0)) | E42: =IF(A42="","",IFERROR(VALUE(SUBSTITUTE(SUBSTITUTE(INDEX('Etsy Import'!$A:$CZ,42,Settings!$C$24)&"","$",""),",","")),0)) | F42: =IF(A42="","",D42*E42) | G42: =IF(A42="","",IF(C42="",1,COUNTIF($C$2:$C$1501,C42))) | H42: =IF(A42="","",IFERROR(VALUE(SUBSTITUTE(SUBSTITUTE(INDEX('Etsy Import'!$A:$CZ,42,Settings!$C$25)&"","$",""),",","")),0)/IF(Settings!$B$27="Yes",G42,1)) | I42: =IF(A42="","",IFERROR(VALUE(SUBSTITUTE(SUBSTITUTE(INDEX('Etsy Import'!$A:$CZ,42,Settings!$C$26)&"","$",""),",","")),0)/IF(Settings!$B$27="Yes",G42,1)) | J42: =IF(A42="","",F42+H42-I42) | K42: =IF(A42="","",IFERROR(IF(B42="",NA(),MATCH(B42,Products!$B$5:$B$204,0)),IFERROR(MATCH(A42,Products!$A$5:$A$204,0),""))) | L42: =IF(A42="","",IF(K42="","⚠ not in Products",INDEX(Products!$A$5:$A$204,K42))) | M42: =IF(A42="","",J42*(IFERROR(INDEX(Settings!$B$5:$B$9,MATCH("Etsy",Settings!$A$5:$A$9,0)),0)+IFERROR(INDEX(Settings!$E$5:$E$9,MATCH("Etsy",Settings!$A$5:$A$9,0)),0)+IFERROR(INDEX(Settings!$G$5:$G$9,MATCH("Etsy",Settings!$A$5:$A$9,0)),0))+(IFERROR(INDEX(Settings!$C$5:$C$9,MATCH("Etsy",Settings!$A$5:$A$9,0)),0)+IFERROR(INDEX(Settings!$F$5:$F$9,MATCH("Etsy",Settings!$A$5:$A$9,0)),0))/G42+IFERROR(INDEX(Settings!$D$5:$D$9,MATCH("Etsy",Settings!$A$5:$A$9,0)),0)*D42) | N42: =IF(A42="","",IF(K42="",0,D42*INDEX(Products!$I$5:$I$204,K42))) | O42: =IF(A42="","",IF(K42="",0,J42*INDEX(Products!$H$5:$H$204,K42))) | P42: =IF(A42="","",J42-M42-N42-O42)
A43: =IFERROR(INDEX('Etsy Import'!$A:$CZ,43,Settings!$C$20)&"","") | B43: =IFERROR(INDEX('Etsy Import'!$A:$CZ,43,Settings!$C$21)&"","") | C43: =IFERROR(INDEX('Etsy Import'!$A:$CZ,43,Settings!$C$22)&"","") | D43: =IF(A43="","",IFERROR(VALUE(SUBSTITUTE(SUBSTITUTE(INDEX('Etsy Import'!$A:$CZ,43,Settings!$C$23)&"","$",""),",","")),0)) | E43: =IF(A43="","",IFERROR(VALUE(SUBSTITUTE(SUBSTITUTE(INDEX('Etsy Import'!$A:$CZ,43,Settings!$C$24)&"","$",""),",","")),0)) | F43: =IF(A43="","",D43*E43) | G43: =IF(A43="","",IF(C43="",1,COUNTIF($C$2:$C$1501,C43))) | H43: =IF(A43="","",IFERROR(VALUE(SUBSTITUTE(SUBSTITUTE(INDEX('Etsy Import'!$A:$CZ,43,Settings!$C$25)&"","$",""),",","")),0)/IF(Settings!$B$27="Yes",G43,1)) | I43: =IF(A43="","",IFERROR(VALUE(SUBSTITUTE(SUBSTITUTE(INDEX('Etsy Import'!$A:$CZ,43,Settings!$C$26)&"","$",""),",","")),0)/IF(Settings!$B$27="Yes",G43,1)) | J43: =IF(A43="","",F43+H43-I43) | K43: =IF(A43="","",IFERROR(IF(B43="",NA(),MATCH(B43,Products!$B$5:$B$204,0)),IFERROR(MATCH(A43,Products!$A$5:$A$204,0),""))) | L43: =IF(A43="","",IF(K43="","⚠ not in Products",INDEX(Products!$A$5:$A$204,K43))) | M43: =IF(A43="","",J43*(IFERROR(INDEX(Settings!$B$5:$B$9,MATCH("Etsy",Settings!$A$5:$A$9,0)),0)+IFERROR(INDEX(Settings!$E$5:$E$9,MATCH("Etsy",Settings!$A$5:$A$9,0)),0)+IFERROR(INDEX(Settings!$G$5:$G$9,MATCH("Etsy",Settings!$A$5:$A$9,0)),0))+(IFERROR(INDEX(Settings!$C$5:$C$9,MATCH("Etsy",Settings!$A$5:$A$9,0)),0)+IFERROR(INDEX(Settings!$F$5:$F$9,MATCH("Etsy",Settings!$A$5:$A$9,0)),0))/G43+IFERROR(INDEX(Settings!$D$5:$D$9,MATCH("Etsy",Settings!$A$5:$A$9,0)),0)*D43) | N43: =IF(A43="","",IF(K43="",0,D43*INDEX(Products!$I$5:$I$204,K43))) | O43: =IF(A43="","",IF(K43="",0,J43*INDEX(Products!$H$5:$H$204,K43))) | P43: =IF(A43="","",J43-M43-N43-O43)
A44: =IFERROR(INDEX('Etsy Import'!$A:$CZ,44,Settings!$C$20)&"","") | B44: =IFERROR(INDEX('Etsy Import'!$A:$CZ,44,Settings!$C$21)&"","") | C44: =IFERROR(INDEX('Etsy Import'!$A:$CZ,44,Settings!$C$22)&"","") | D44: =IF(A44="","",IFERROR(VALUE(SUBSTITUTE(SUBSTITUTE(INDEX('Etsy Import'!$A:$CZ,44,Settings!$C$23)&"","$",""),",","")),0)) | E44: =IF(A44="","",IFERROR(VALUE(SUBSTITUTE(SUBSTITUTE(INDEX('Etsy Import'!$A:$CZ,44,Settings!$C$24)&"","$",""),",","")),0)) | F44: =IF(A44="","",D44*E44) | G44: =IF(A44="","",IF(C44="",1,COUNTIF($C$2:$C$1501,C44))) | H44: =IF(A44="","",IFERROR(VALUE(SUBSTITUTE(SUBSTITUTE(INDEX('Etsy Import'!$A:$CZ,44,Settings!$C$25)&"","$",""),",","")),0)/IF(Settings!$B$27="Yes",G44,1)) | I44: =IF(A44="","",IFERROR(VALUE(SUBSTITUTE(SUBSTITUTE(INDEX('Etsy Import'!$A:$CZ,44,Settings!$C$26)&"","$",""),",","")),0)/IF(Settings!$B$27="Yes",G44,1)) | J44: =IF(A44="","",F44+H44-I44) | K44: =IF(A44="","",IFERROR(IF(B44="",NA(),MATCH(B44,Products!$B$5:$B$204,0)),IFERROR(MATCH(A44,Products!$A$5:$A$204,0),""))) | L44: =IF(A44="","",IF(K44="","⚠ not in Products",INDEX(Products!$A$5:$A$204,K44))) | M44: =IF(A44="","",J44*(IFERROR(INDEX(Settings!$B$5:$B$9,MATCH("Etsy",Settings!$A$5:$A$9,0)),0)+IFERROR(INDEX(Settings!$E$5:$E$9,MATCH("Etsy",Settings!$A$5:$A$9,0)),0)+IFERROR(INDEX(Settings!$G$5:$G$9,MATCH("Etsy",Settings!$A$5:$A$9,0)),0))+(IFERROR(INDEX(Settings!$C$5:$C$9,MATCH("Etsy",Settings!$A$5:$A$9,0)),0)+IFERROR(INDEX(Settings!$F$5:$F$9,MATCH("Etsy",Settings!$A$5:$A$9,0)),0))/G44+IFERROR(INDEX(Settings!$D$5:$D$9,MATCH("Etsy",Settings!$A$5:$A$9,0)),0)*D44) | N44: =IF(A44="","",IF(K44="",0,D44*INDEX(Products!$I$5:$I$204,K44))) | O44: =IF(A44="","",IF(K44="",0,J44*INDEX(Products!$H$5:$H$204,K44))) | P44: =IF(A44="","",J44-M44-N44-O44)
A45: =IFERROR(INDEX('Etsy Import'!$A:$CZ,45,Settings!$C$20)&"","") | B45: =IFERROR(INDEX('Etsy Import'!$A:$CZ,45,Settings!$C$21)&"","") | C45: =IFERROR(INDEX('Etsy Import'!$A:$CZ,45,Settings!$C$22)&"","") | D45: =IF(A45="","",IFERROR(VALUE(SUBSTITUTE(SUBSTITUTE(INDEX('Etsy Import'!$A:$CZ,45,Settings!$C$23)&"","$",""),",","")),0)) | E45: =IF(A45="","",IFERROR(VALUE(SUBSTITUTE(SUBSTITUTE(INDEX('Etsy Import'!$A:$CZ,45,Settings!$C$24)&"","$",""),",","")),0)) | F45: =IF(A45="","",D45*E45) | G45: =IF(A45="","",IF(C45="",1,COUNTIF($C$2:$C$1501,C45))) | H45: =IF(A45="","",IFERROR(VALUE(SUBSTITUTE(SUBSTITUTE(INDEX('Etsy Import'!$A:$CZ,45,Settings!$C$25)&"","$",""),",","")),0)/IF(Settings!$B$27="Yes",G45,1)) | I45: =IF(A45="","",IFERROR(VALUE(SUBSTITUTE(SUBSTITUTE(INDEX('Etsy Import'!$A:$CZ,45,Settings!$C$26)&"","$",""),",","")),0)/IF(Settings!$B$27="Yes",G45,1)) | J45: =IF(A45="","",F45+H45-I45) | K45: =IF(A45="","",IFERROR(IF(B45="",NA(),MATCH(B45,Products!$B$5:$B$204,0)),IFERROR(MATCH(A45,Products!$A$5:$A$204,0),""))) | L45: =IF(A45="","",IF(K45="","⚠ not in Products",INDEX(Products!$A$5:$A$204,K45))) | M45: =IF(A45="","",J45*(IFERROR(INDEX(Settings!$B$5:$B$9,MATCH("Etsy",Settings!$A$5:$A$9,0)),0)+IFERROR(INDEX(Settings!$E$5:$E$9,MATCH("Etsy",Settings!$A$5:$A$9,0)),0)+IFERROR(INDEX(Settings!$G$5:$G$9,MATCH("Etsy",Settings!$A$5:$A$9,0)),0))+(IFERROR(INDEX(Settings!$C$5:$C$9,MATCH("Etsy",Settings!$A$5:$A$9,0)),0)+IFERROR(INDEX(Settings!$F$5:$F$9,MATCH("Etsy",Settings!$A$5:$A$9,0)),0))/G45+IFERROR(INDEX(Settings!$D$5:$D$9,MATCH("Etsy",Settings!$A$5:$A$9,0)),0)*D45) | N45: =IF(A45="","",IF(K45="",0,D45*INDEX(Products!$I$5:$I$204,K45))) | O45: =IF(A45="","",IF(K45="",0,J45*INDEX(Products!$H$5:$H$204,K45))) | P45: =IF(A45="","",J45-M45-N45-O45)
A46: =IFERROR(INDEX('Etsy Import'!$A:$CZ,46,Settings!$C$20)&"","") | B46: =IFERROR(INDEX('Etsy Import'!$A:$CZ,46,Settings!$C$21)&"","") | C46: =IFERROR(INDEX('Etsy Import'!$A:$CZ,46,Settings!$C$22)&"","") | D46: =IF(A46="","",IFERROR(VALUE(SUBSTITUTE(SUBSTITUTE(INDEX('Etsy Import'!$A:$CZ,46,Settings!$C$23)&"","$",""),",","")),0)) | E46: =IF(A46="","",IFERROR(VALUE(SUBSTITUTE(SUBSTITUTE(INDEX('Etsy Import'!$A:$CZ,46,Settings!$C$24)&"","$",""),",","")),0)) | F46: =IF(A46="","",D46*E46) | G46: =IF(A46="","",IF(C46="",1,COUNTIF($C$2:$C$1501,C46))) | H46: =IF(A46="","",IFERROR(VALUE(SUBSTITUTE(SUBSTITUTE(INDEX('Etsy Import'!$A:$CZ,46,Settings!$C$25)&"","$",""),",","")),0)/IF(Settings!$B$27="Yes",G46,1)) | I46: =IF(A46="","",IFERROR(VALUE(SUBSTITUTE(SUBSTITUTE(INDEX('Etsy Import'!$A:$CZ,46,Settings!$C$26)&"","$",""),",","")),0)/IF(Settings!$B$27="Yes",G46,1)) | J46: =IF(A46="","",F46+H46-I46) | K46: =IF(A46="","",IFERROR(IF(B46="",NA(),MATCH(B46,Products!$B$5:$B$204,0)),IFERROR(MATCH(A46,Products!$A$5:$A$204,0),""))) | L46: =IF(A46="","",IF(K46="","⚠ not in Products",INDEX(Products!$A$5:$A$204,K46))) | M46: =IF(A46="","",J46*(IFERROR(INDEX(Settings!$B$5:$B$9,MATCH("Etsy",Settings!$A$5:$A$9,0)),0)+IFERROR(INDEX(Settings!$E$5:$E$9,MATCH("Etsy",Settings!$A$5:$A$9,0)),0)+IFERROR(INDEX(Settings!$G$5:$G$9,MATCH("Etsy",Settings!$A$5:$A$9,0)),0))+(IFERROR(INDEX(Settings!$C$5:$C$9,MATCH("Etsy",Settings!$A$5:$A$9,0)),0)+IFERROR(INDEX(Settings!$F$5:$F$9,MATCH("Etsy",Settings!$A$5:$A$9,0)),0))/G46+IFERROR(INDEX(Settings!$D$5:$D$9,MATCH("Etsy",Settings!$A$5:$A$9,0)),0)*D46) | N46: =IF(A46="","",IF(K46="",0,D46*INDEX(Products!$I$5:$I$204,K46))) | O46: =IF(A46="","",IF(K46="",0,J46*INDEX(Products!$H$5:$H$204,K46))) | P46: =IF(A46="","",J46-M46-N46-O46)
A47: =IFERROR(INDEX('Etsy Import'!$A:$CZ,47,Settings!$C$20)&"","") | B47: =IFERROR(INDEX('Etsy Import'!$A:$CZ,47,Settings!$C$21)&"","") | C47: =IFERROR(INDEX('Etsy Import'!$A:$CZ,47,Settings!$C$22)&"","") | D47: =IF(A47="","",IFERROR(VALUE(SUBSTITUTE(SUBSTITUTE(INDEX('Etsy Import'!$A:$CZ,47,Settings!$C$23)&"","$",""),",","")),0)) | E47: =IF(A47="","",IFERROR(VALUE(SUBSTITUTE(SUBSTITUTE(INDEX('Etsy Import'!$A:$CZ,47,Settings!$C$24)&"","$",""),",","")),0)) | F47: =IF(A47="","",D47*E47) | G47: =IF(A47="","",IF(C47="",1,COUNTIF($C$2:$C$1501,C47))) | H47: =IF(A47="","",IFERROR(VALUE(SUBSTITUTE(SUBSTITUTE(INDEX('Etsy Import'!$A:$CZ,47,Settings!$C$25)&"","$",""),",","")),0)/IF(Settings!$B$27="Yes",G47,1)) | I47: =IF(A47="","",IFERROR(VALUE(SUBSTITUTE(SUBSTITUTE(INDEX('Etsy Import'!$A:$CZ,47,Settings!$C$26)&"","$",""),",","")),0)/IF(Settings!$B$27="Yes",G47,1)) | J47: =IF(A47="","",F47+H47-I47) | K47: =IF(A47="","",IFERROR(IF(B47="",NA(),MATCH(B47,Products!$B$5:$B$204,0)),IFERROR(MATCH(A47,Products!$A$5:$A$204,0),""))) | L47: =IF(A47="","",IF(K47="","⚠ not in Products",INDEX(Products!$A$5:$A$204,K47))) | M47: =IF(A47="","",J47*(IFERROR(INDEX(Settings!$B$5:$B$9,MATCH("Etsy",Settings!$A$5:$A$9,0)),0)+IFERROR(INDEX(Settings!$E$5:$E$9,MATCH("Etsy",Settings!$A$5:$A$9,0)),0)+IFERROR(INDEX(Settings!$G$5:$G$9,MATCH("Etsy",Settings!$A$5:$A$9,0)),0))+(IFERROR(INDEX(Settings!$C$5:$C$9,MATCH("Etsy",Settings!$A$5:$A$9,0)),0)+IFERROR(INDEX(Settings!$F$5:$F$9,MATCH("Etsy",Settings!$A$5:$A$9,0)),0))/G47+IFERROR(INDEX(Settings!$D$5:$D$9,MATCH("Etsy",Settings!$A$5:$A$9,0)),0)*D47) | N47: =IF(A47="","",IF(K47="",0,D47*INDEX(Products!$I$5:$I$204,K47))) | O47: =IF(A47="","",IF(K47="",0,J47*INDEX(Products!$H$5:$H$204,K47))) | P47: =IF(A47="","",J47-M47-N47-O47)
A48: =IFERROR(INDEX('Etsy Import'!$A:$CZ,48,Settings!$C$20)&"","") | B48: =IFERROR(INDEX('Etsy Import'!$A:$CZ,48,Settings!$C$21)&"","") | C48: =IFERROR(INDEX('Etsy Import'!$A:$CZ,48,Settings!$C$22)&"","") | D48: =IF(A48="","",IFERROR(VALUE(SUBSTITUTE(SUBSTITUTE(INDEX('Etsy Import'!$A:$CZ,48,Settings!$C$23)&"","$",""),",","")),0)) | E48: =IF(A48="","",IFERROR(VALUE(SUBSTITUTE(SUBSTITUTE(INDEX('Etsy Import'!$A:$CZ,48,Settings!$C$24)&"","$",""),",","")),0)) | F48: =IF(A48="","",D48*E48) | G48: =IF(A48="","",IF(C48="",1,COUNTIF($C$2:$C$1501,C48))) | H48: =IF(A48="","",IFERROR(VALUE(SUBSTITUTE(SUBSTITUTE(INDEX('Etsy Import'!$A:$CZ,48,Settings!$C$25)&"","$",""),",","")),0)/IF(Settings!$B$27="Yes",G48,1)) | I48: =IF(A48="","",IFERROR(VALUE(SUBSTITUTE(SUBSTITUTE(INDEX('Etsy Import'!$A:$CZ,48,Settings!$C$26)&"","$",""),",","")),0)/IF(Settings!$B$27="Yes",G48,1)) | J48: =IF(A48="","",F48+H48-I48) | K48: =IF(A48="","",IFERROR(IF(B48="",NA(),MATCH(B48,Products!$B$5:$B$204,0)),IFERROR(MATCH(A48,Products!$A$5:$A$204,0),""))) | L48: =IF(A48="","",IF(K48="","⚠ not in Products",INDEX(Products!$A$5:$A$204,K48))) | M48: =IF(A48="","",J48*(IFERROR(INDEX(Settings!$B$5:$B$9,MATCH("Etsy",Settings!$A$5:$A$9,0)),0)+IFERROR(INDEX(Settings!$E$5:$E$9,MATCH("Etsy",Settings!$A$5:$A$9,0)),0)+IFERROR(INDEX(Settings!$G$5:$G$9,MATCH("Etsy",Settings!$A$5:$A$9,0)),0))+(IFERROR(INDEX(Settings!$C$5:$C$9,MATCH("Etsy",Settings!$A$5:$A$9,0)),0)+IFERROR(INDEX(Settings!$F$5:$F$9,MATCH("Etsy",Settings!$A$5:$A$9,0)),0))/G48+IFERROR(INDEX(Settings!$D$5:$D$9,MATCH("Etsy",Settings!$A$5:$A$9,0)),0)*D48) | N48: =IF(A48="","",IF(K48="",0,D48*INDEX(Products!$I$5:$I$204,K48))) | O48: =IF(A48="","",IF(K48="",0,J48*INDEX(Products!$H$5:$H$204,K48))) | P48: =IF(A48="","",J48-M48-N48-O48)
A49: =IFERROR(INDEX('Etsy Import'!$A:$CZ,49,Settings!$C$20)&"","") | B49: =IFERROR(INDEX('Etsy Import'!$A:$CZ,49,Settings!$C$21)&"","") | C49: =IFERROR(INDEX('Etsy Import'!$A:$CZ,49,Settings!$C$22)&"","") | D49: =IF(A49="","",IFERROR(VALUE(SUBSTITUTE(SUBSTITUTE(INDEX('Etsy Import'!$A:$CZ,49,Settings!$C$23)&"","$",""),",","")),0)) | E49: =IF(A49="","",IFERROR(VALUE(SUBSTITUTE(SUBSTITUTE(INDEX('Etsy Import'!$A:$CZ,49,Settings!$C$24)&"","$",""),",","")),0)) | F49: =IF(A49="","",D49*E49) | G49: =IF(A49="","",IF(C49="",1,COUNTIF($C$2:$C$1501,C49))) | H49: =IF(A49="","",IFERROR(VALUE(SUBSTITUTE(SUBSTITUTE(INDEX('Etsy Import'!$A:$CZ,49,Settings!$C$25)&"","$",""),",","")),0)/IF(Settings!$B$27="Yes",G49,1)) | I49: =IF(A49="","",IFERROR(VALUE(SUBSTITUTE(SUBSTITUTE(INDEX('Etsy Import'!$A:$CZ,49,Settings!$C$26)&"","$",""),",","")),0)/IF(Settings!$B$27="Yes",G49,1)) | J49: =IF(A49="","",F49+H49-I49) | K49: =IF(A49="","",IFERROR(IF(B49="",NA(),MATCH(B49,Products!$B$5:$B$204,0)),IFERROR(MATCH(A49,Products!$A$5:$A$204,0),""))) | L49: =IF(A49="","",IF(K49="","⚠ not in Products",INDEX(Products!$A$5:$A$204,K49))) | M49: =IF(A49="","",J49*(IFERROR(INDEX(Settings!$B$5:$B$9,MATCH("Etsy",Settings!$A$5:$A$9,0)),0)+IFERROR(INDEX(Settings!$E$5:$E$9,MATCH("Etsy",Settings!$A$5:$A$9,0)),0)+IFERROR(INDEX(Settings!$G$5:$G$9,MATCH("Etsy",Settings!$A$5:$A$9,0)),0))+(IFERROR(INDEX(Settings!$C$5:$C$9,MATCH("Etsy",Settings!$A$5:$A$9,0)),0)+IFERROR(INDEX(Settings!$F$5:$F$9,MATCH("Etsy",Settings!$A$5:$A$9,0)),0))/G49+IFERROR(INDEX(Settings!$D$5:$D$9,MATCH("Etsy",Settings!$A$5:$A$9,0)),0)*D49) | N49: =IF(A49="","",IF(K49="",0,D49*INDEX(Products!$I$5:$I$204,K49))) | O49: =IF(A49="","",IF(K49="",0,J49*INDEX(Products!$H$5:$H$204,K49))) | P49: =IF(A49="","",J49-M49-N49-O49)
A50: =IFERROR(INDEX('Etsy Import'!$A:$CZ,50,Settings!$C$20)&"","") | B50: =IFERROR(INDEX('Etsy Import'!$A:$CZ,50,Settings!$C$21)&"","") | C50: =IFERROR(INDEX('Etsy Import'!$A:$CZ,50,Settings!$C$22)&"","") | D50: =IF(A50="","",IFERROR(VALUE(SUBSTITUTE(SUBSTITUTE(INDEX('Etsy Import'!$A:$CZ,50,Settings!$C$23)&"","$",""),",","")),0)) | E50: =IF(A50="","",IFERROR(VALUE(SUBSTITUTE(SUBSTITUTE(INDEX('Etsy Import'!$A:$CZ,50,Settings!$C$24)&"","$",""),",","")),0)) | F50: =IF(A50="","",D50*E50) | G50: =IF(A50="","",IF(C50="",1,COUNTIF($C$2:$C$1501,C50))) | H50: =IF(A50="","",IFERROR(VALUE(SUBSTITUTE(SUBSTITUTE(INDEX('Etsy Import'!$A:$CZ,50,Settings!$C$25)&"","$",""),",","")),0)/IF(Settings!$B$27="Yes",G50,1)) | I50: =IF(A50="","",IFERROR(VALUE(SUBSTITUTE(SUBSTITUTE(INDEX('Etsy Import'!$A:$CZ,50,Settings!$C$26)&"","$",""),",","")),0)/IF(Settings!$B$27="Yes",G50,1)) | J50: =IF(A50="","",F50+H50-I50) | K50: =IF(A50="","",IFERROR(IF(B50="",NA(),MATCH(B50,Products!$B$5:$B$204,0)),IFERROR(MATCH(A50,Products!$A$5:$A$204,0),""))) | L50: =IF(A50="","",IF(K50="","⚠ not in Products",INDEX(Products!$A$5:$A$204,K50))) | M50: =IF(A50="","",J50*(IFERROR(INDEX(Settings!$B$5:$B$9,MATCH("Etsy",Settings!$A$5:$A$9,0)),0)+IFERROR(INDEX(Settings!$E$5:$E$9,MATCH("Etsy",Settings!$A$5:$A$9,0)),0)+IFERROR(INDEX(Settings!$G$5:$G$9,MATCH("Etsy",Settings!$A$5:$A$9,0)),0))+(IFERROR(INDEX(Settings!$C$5:$C$9,MATCH("Etsy",Settings!$A$5:$A$9,0)),0)+IFERROR(INDEX(Settings!$F$5:$F$9,MATCH("Etsy",Settings!$A$5:$A$9,0)),0))/G50+IFERROR(INDEX(Settings!$D$5:$D$9,MATCH("Etsy",Settings!$A$5:$A$9,0)),0)*D50) | N50: =IF(A50="","",IF(K50="",0,D50*INDEX(Products!$I$5:$I$204,K50))) | O50: =IF(A50="","",IF(K50="",0,J50*INDEX(Products!$H$5:$H$204,K50))) | P50: =IF(A50="","",J50-M50-N50-O50)
A51: =IFERROR(INDEX('Etsy Import'!$A:$CZ,51,Settings!$C$20)&"","") | B51: =IFERROR(INDEX('Etsy Import'!$A:$CZ,51,Settings!$C$21)&"","") | C51: =IFERROR(INDEX('Etsy Import'!$A:$CZ,51,Settings!$C$22)&"","") | D51: =IF(A51="","",IFERROR(VALUE(SUBSTITUTE(SUBSTITUTE(INDEX('Etsy Import'!$A:$CZ,51,Settings!$C$23)&"","$",""),",","")),0)) | E51: =IF(A51="","",IFERROR(VALUE(SUBSTITUTE(SUBSTITUTE(INDEX('Etsy Import'!$A:$CZ,51,Settings!$C$24)&"","$",""),",","")),0)) | F51: =IF(A51="","",D51*E51) | G51: =IF(A51="","",IF(C51="",1,COUNTIF($C$2:$C$1501,C51))) | H51: =IF(A51="","",IFERROR(VALUE(SUBSTITUTE(SUBSTITUTE(INDEX('Etsy Import'!$A:$CZ,51,Settings!$C$25)&"","$",""),",","")),0)/IF(Settings!$B$27="Yes",G51,1)) | I51: =IF(A51="","",IFERROR(VALUE(SUBSTITUTE(SUBSTITUTE(INDEX('Etsy Import'!$A:$CZ,51,Settings!$C$26)&"","$",""),",","")),0)/IF(Settings!$B$27="Yes",G51,1)) | J51: =IF(A51="","",F51+H51-I51) | K51: =IF(A51="","",IFERROR(IF(B51="",NA(),MATCH(B51,Products!$B$5:$B$204,0)),IFERROR(MATCH(A51,Products!$A$5:$A$204,0),""))) | L51: =IF(A51="","",IF(K51="","⚠ not in Products",INDEX(Products!$A$5:$A$204,K51))) | M51: =IF(A51="","",J51*(IFERROR(INDEX(Settings!$B$5:$B$9,MATCH("Etsy",Settings!$A$5:$A$9,0)),0)+IFERROR(INDEX(Settings!$E$5:$E$9,MATCH("Etsy",Settings!$A$5:$A$9,0)),0)+IFERROR(INDEX(Settings!$G$5:$G$9,MATCH("Etsy",Settings!$A$5:$A$9,0)),0))+(IFERROR(INDEX(Settings!$C$5:$C$9,MATCH("Etsy",Settings!$A$5:$A$9,0)),0)+IFERROR(INDEX(Settings!$F$5:$F$9,MATCH("Etsy",Settings!$A$5:$A$9,0)),0))/G51+IFERROR(INDEX(Settings!$D$5:$D$9,MATCH("Etsy",Settings!$A$5:$A$9,0)),0)*D51) | N51: =IF(A51="","",IF(K51="",0,D51*INDEX(Products!$I$5:$I$204,K51))) | O51: =IF(A51="","",IF(K51="",0,J51*INDEX(Products!$H$5:$H$204,K51))) | P51: =IF(A51="","",J51-M51-N51-O51)
A52: =IFERROR(INDEX('Etsy Import'!$A:$CZ,52,Settings!$C$20)&"","") | B52: =IFERROR(INDEX('Etsy Import'!$A:$CZ,52,Settings!$C$21)&"","") | C52: =IFERROR(INDEX('Etsy Import'!$A:$CZ,52,Settings!$C$22)&"","") | D52: =IF(A52="","",IFERROR(VALUE(SUBSTITUTE(SUBSTITUTE(INDEX('Etsy Import'!$A:$CZ,52,Settings!$C$23)&"","$",""),",","")),0)) | E52: =IF(A52="","",IFERROR(VALUE(SUBSTITUTE(SUBSTITUTE(INDEX('Etsy Import'!$A:$CZ,52,Settings!$C$24)&"","$",""),",","")),0)) | F52: =IF(A52="","",D52*E52) | G52: =IF(A52="","",IF(C52="",1,COUNTIF($C$2:$C$1501,C52))) | H52: =IF(A52="","",IFERROR(VALUE(SUBSTITUTE(SUBSTITUTE(INDEX('Etsy Import'!$A:$CZ,52,Settings!$C$25)&"","$",""),",","")),0)/IF(Settings!$B$27="Yes",G52,1)) | I52: =IF(A52="","",IFERROR(VALUE(SUBSTITUTE(SUBSTITUTE(INDEX('Etsy Import'!$A:$CZ,52,Settings!$C$26)&"","$",""),",","")),0)/IF(Settings!$B$27="Yes",G52,1)) | J52: =IF(A52="","",F52+H52-I52) | K52: =IF(A52="","",IFERROR(IF(B52="",NA(),MATCH(B52,Products!$B$5:$B$204,0)),IFERROR(MATCH(A52,Products!$A$5:$A$204,0),""))) | L52: =IF(A52="","",IF(K52="","⚠ not in Products",INDEX(Products!$A$5:$A$204,K52))) | M52: =IF(A52="","",J52*(IFERROR(INDEX(Settings!$B$5:$B$9,MATCH("Etsy",Settings!$A$5:$A$9,0)),0)+IFERROR(INDEX(Settings!$E$5:$E$9,MATCH("Etsy",Settings!$A$5:$A$9,0)),0)+IFERROR(INDEX(Settings!$G$5:$G$9,MATCH("Etsy",Settings!$A$5:$A$9,0)),0))+(IFERROR(INDEX(Settings!$C$5:$C$9,MATCH("Etsy",Settings!$A$5:$A$9,0)),0)+IFERROR(INDEX(Settings!$F$5:$F$9,MATCH("Etsy",Settings!$A$5:$A$9,0)),0))/G52+IFERROR(INDEX(Settings!$D$5:$D$9,MATCH("Etsy",Settings!$A$5:$A$9,0)),0)*D52) | N52: =IF(A52="","",IF(K52="",0,D52*INDEX(Products!$I$5:$I$204,K52))) | O52: =IF(A52="","",IF(K52="",0,J52*INDEX(Products!$H$5:$H$204,K52))) | P52: =IF(A52="","",J52-M52-N52-O52)
A53: =IFERROR(INDEX('Etsy Import'!$A:$CZ,53,Settings!$C$20)&"","") | B53: =IFERROR(INDEX('Etsy Import'!$A:$CZ,53,Settings!$C$21)&"","") | C53: =IFERROR(INDEX('Etsy Import'!$A:$CZ,53,Settings!$C$22)&"","") | D53: =IF(A53="","",IFERROR(VALUE(SUBSTITUTE(SUBSTITUTE(INDEX('Etsy Import'!$A:$CZ,53,Settings!$C$23)&"","$",""),",","")),0)) | E53: =IF(A53="","",IFERROR(VALUE(SUBSTITUTE(SUBSTITUTE(INDEX('Etsy Import'!$A:$CZ,53,Settings!$C$24)&"","$",""),",","")),0)) | F53: =IF(A53="","",D53*E53) | G53: =IF(A53="","",IF(C53="",1,COUNTIF($C$2:$C$1501,C53))) | H53: =IF(A53="","",IFERROR(VALUE(SUBSTITUTE(SUBSTITUTE(INDEX('Etsy Import'!$A:$CZ,53,Settings!$C$25)&"","$",""),",","")),0)/IF(Settings!$B$27="Yes",G53,1)) | I53: =IF(A53="","",IFERROR(VALUE(SUBSTITUTE(SUBSTITUTE(INDEX('Etsy Import'!$A:$CZ,53,Settings!$C$26)&"","$",""),",","")),0)/IF(Settings!$B$27="Yes",G53,1)) | J53: =IF(A53="","",F53+H53-I53) | K53: =IF(A53="","",IFERROR(IF(B53="",NA(),MATCH(B53,Products!$B$5:$B$204,0)),IFERROR(MATCH(A53,Products!$A$5:$A$204,0),""))) | L53: =IF(A53="","",IF(K53="","⚠ not in Products",INDEX(Products!$A$5:$A$204,K53))) | M53: =IF(A53="","",J53*(IFERROR(INDEX(Settings!$B$5:$B$9,MATCH("Etsy",Settings!$A$5:$A$9,0)),0)+IFERROR(INDEX(Settings!$E$5:$E$9,MATCH("Etsy",Settings!$A$5:$A$9,0)),0)+IFERROR(INDEX(Settings!$G$5:$G$9,MATCH("Etsy",Settings!$A$5:$A$9,0)),0))+(IFERROR(INDEX(Settings!$C$5:$C$9,MATCH("Etsy",Settings!$A$5:$A$9,0)),0)+IFERROR(INDEX(Settings!$F$5:$F$9,MATCH("Etsy",Settings!$A$5:$A$9,0)),0))/G53+IFERROR(INDEX(Settings!$D$5:$D$9,MATCH("Etsy",Settings!$A$5:$A$9,0)),0)*D53) | N53: =IF(A53="","",IF(K53="",0,D53*INDEX(Products!$I$5:$I$204,K53))) | O53: =IF(A53="","",IF(K53="",0,J53*INDEX(Products!$H$5:$H$204,K53))) | P53: =IF(A53="","",J53-M53-N53-O53)
A54: =IFERROR(INDEX('Etsy Import'!$A:$CZ,54,Settings!$C$20)&"","") | B54: =IFERROR(INDEX('Etsy Import'!$A:$CZ,54,Settings!$C$21)&"","") | C54: =IFERROR(INDEX('Etsy Import'!$A:$CZ,54,Settings!$C$22)&"","") | D54: =IF(A54="","",IFERROR(VALUE(SUBSTITUTE(SUBSTITUTE(INDEX('Etsy Import'!$A:$CZ,54,Settings!$C$23)&"","$",""),",","")),0)) | E54: =IF(A54="","",IFERROR(VALUE(SUBSTITUTE(SUBSTITUTE(INDEX('Etsy Import'!$A:$CZ,54,Settings!$C$24)&"","$",""),",","")),0)) | F54: =IF(A54="","",D54*E54) | G54: =IF(A54="","",IF(C54="",1,COUNTIF($C$2:$C$1501,C54))) | H54: =IF(A54="","",IFERROR(VALUE(SUBSTITUTE(SUBSTITUTE(INDEX('Etsy Import'!$A:$CZ,54,Settings!$C$25)&"","$",""),",","")),0)/IF(Settings!$B$27="Yes",G54,1)) | I54: =IF(A54="","",IFERROR(VALUE(SUBSTITUTE(SUBSTITUTE(INDEX('Etsy Import'!$A:$CZ,54,Settings!$C$26)&"","$",""),",","")),0)/IF(Settings!$B$27="Yes",G54,1)) | J54: =IF(A54="","",F54+H54-I54) | K54: =IF(A54="","",IFERROR(IF(B54="",NA(),MATCH(B54,Products!$B$5:$B$204,0)),IFERROR(MATCH(A54,Products!$A$5:$A$204,0),""))) | L54: =IF(A54="","",IF(K54="","⚠ not in Products",INDEX(Products!$A$5:$A$204,K54))) | M54: =IF(A54="","",J54*(IFERROR(INDEX(Settings!$B$5:$B$9,MATCH("Etsy",Settings!$A$5:$A$9,0)),0)+IFERROR(INDEX(Settings!$E$5:$E$9,MATCH("Etsy",Settings!$A$5:$A$9,0)),0)+IFERROR(INDEX(Settings!$G$5:$G$9,MATCH("Etsy",Settings!$A$5:$A$9,0)),0))+(IFERROR(INDEX(Settings!$C$5:$C$9,MATCH("Etsy",Settings!$A$5:$A$9,0)),0)+IFERROR(INDEX(Settings!$F$5:$F$9,MATCH("Etsy",Settings!$A$5:$A$9,0)),0))/G54+IFERROR(INDEX(Settings!$D$5:$D$9,MATCH("Etsy",Settings!$A$5:$A$9,0)),0)*D54) | N54: =IF(A54="","",IF(K54="",0,D54*INDEX(Products!$I$5:$I$204,K54))) | O54: =IF(A54="","",IF(K54="",0,J54*INDEX(Products!$H$5:$H$204,K54))) | P54: =IF(A54="","",J54-M54-N54-O54)
A55: =IFERROR(INDEX('Etsy Import'!$A:$CZ,55,Settings!$C$20)&"","") | B55: =IFERROR(INDEX('Etsy Import'!$A:$CZ,55,Settings!$C$21)&"","") | C55: =IFERROR(INDEX('Etsy Import'!$A:$CZ,55,Settings!$C$22)&"","") | D55: =IF(A55="","",IFERROR(VALUE(SUBSTITUTE(SUBSTITUTE(INDEX('Etsy Import'!$A:$CZ,55,Settings!$C$23)&"","$",""),",","")),0)) | E55: =IF(A55="","",IFERROR(VALUE(SUBSTITUTE(SUBSTITUTE(INDEX('Etsy Import'!$A:$CZ,55,Settings!$C$24)&"","$",""),",","")),0)) | F55: =IF(A55="","",D55*E55) | G55: =IF(A55="","",IF(C55="",1,COUNTIF($C$2:$C$1501,C55))) | H55: =IF(A55="","",IFERROR(VALUE(SUBSTITUTE(SUBSTITUTE(INDEX('Etsy Import'!$A:$CZ,55,Settings!$C$25)&"","$",""),",","")),0)/IF(Settings!$B$27="Yes",G55,1)) | I55: =IF(A55="","",IFERROR(VALUE(SUBSTITUTE(SUBSTITUTE(INDEX('Etsy Import'!$A:$CZ,55,Settings!$C$26)&"","$",""),",","")),0)/IF(Settings!$B$27="Yes",G55,1)) | J55: =IF(A55="","",F55+H55-I55) | K55: =IF(A55="","",IFERROR(IF(B55="",NA(),MATCH(B55,Products!$B$5:$B$204,0)),IFERROR(MATCH(A55,Products!$A$5:$A$204,0),""))) | L55: =IF(A55="","",IF(K55="","⚠ not in Products",INDEX(Products!$A$5:$A$204,K55))) | M55: =IF(A55="","",J55*(IFERROR(INDEX(Settings!$B$5:$B$9,MATCH("Etsy",Settings!$A$5:$A$9,0)),0)+IFERROR(INDEX(Settings!$E$5:$E$9,MATCH("Etsy",Settings!$A$5:$A$9,0)),0)+IFERROR(INDEX(Settings!$G$5:$G$9,MATCH("Etsy",Settings!$A$5:$A$9,0)),0))+(IFERROR(INDEX(Settings!$C$5:$C$9,MATCH("Etsy",Settings!$A$5:$A$9,0)),0)+IFERROR(INDEX(Settings!$F$5:$F$9,MATCH("Etsy",Settings!$A$5:$A$9,0)),0))/G55+IFERROR(INDEX(Settings!$D$5:$D$9,MATCH("Etsy",Settings!$A$5:$A$9,0)),0)*D55) | N55: =IF(A55="","",IF(K55="",0,D55*INDEX(Products!$I$5:$I$204,K55))) | O55: =IF(A55="","",IF(K55="",0,J55*INDEX(Products!$H$5:$H$204,K55))) | P55: =IF(A55="","",J55-M55-N55-O55)
A56: =IFERROR(INDEX('Etsy Import'!$A:$CZ,56,Settings!$C$20)&"","") | B56: =IFERROR(INDEX('Etsy Import'!$A:$CZ,56,Settings!$C$21)&"","") | C56: =IFERROR(INDEX('Etsy Import'!$A:$CZ,56,Settings!$C$22)&"","") | D56: =IF(A56="","",IFERROR(VALUE(SUBSTITUTE(SUBSTITUTE(INDEX('Etsy Import'!$A:$CZ,56,Settings!$C$23)&"","$",""),",","")),0)) | E56: =IF(A56="","",IFERROR(VALUE(SUBSTITUTE(SUBSTITUTE(INDEX('Etsy Import'!$A:$CZ,56,Settings!$C$24)&"","$",""),",","")),0)) | F56: =IF(A56="","",D56*E56) | G56: =IF(A56="","",IF(C56="",1,COUNTIF($C$2:$C$1501,C56))) | H56: =IF(A56="","",IFERROR(VALUE(SUBSTITUTE(SUBSTITUTE(INDEX('Etsy Import'!$A:$CZ,56,Settings!$C$25)&"","$",""),",","")),0)/IF(Settings!$B$27="Yes",G56,1)) | I56: =IF(A56="","",IFERROR(VALUE(SUBSTITUTE(SUBSTITUTE(INDEX('Etsy Import'!$A:$CZ,56,Settings!$C$26)&"","$",""),",","")),0)/IF(Settings!$B$27="Yes",G56,1)) | J56: =IF(A56="","",F56+H56-I56) | K56: =IF(A56="","",IFERROR(IF(B56="",NA(),MATCH(B56,Products!$B$5:$B$204,0)),IFERROR(MATCH(A56,Products!$A$5:$A$204,0),""))) | L56: =IF(A56="","",IF(K56="","⚠ not in Products",INDEX(Products!$A$5:$A$204,K56))) | M56: =IF(A56="","",J56*(IFERROR(INDEX(Settings!$B$5:$B$9,MATCH("Etsy",Settings!$A$5:$A$9,0)),0)+IFERROR(INDEX(Settings!$E$5:$E$9,MATCH("Etsy",Settings!$A$5:$A$9,0)),0)+IFERROR(INDEX(Settings!$G$5:$G$9,MATCH("Etsy",Settings!$A$5:$A$9,0)),0))+(IFERROR(INDEX(Settings!$C$5:$C$9,MATCH("Etsy",Settings!$A$5:$A$9,0)),0)+IFERROR(INDEX(Settings!$F$5:$F$9,MATCH("Etsy",Settings!$A$5:$A$9,0)),0))/G56+IFERROR(INDEX(Settings!$D$5:$D$9,MATCH("Etsy",Settings!$A$5:$A$9,0)),0)*D56) | N56: =IF(A56="","",IF(K56="",0,D56*INDEX(Products!$I$5:$I$204,K56))) | O56: =IF(A56="","",IF(K56="",0,J56*INDEX(Products!$H$5:$H$204,K56))) | P56: =IF(A56="","",J56-M56-N56-O56)
A57: =IFERROR(INDEX('Etsy Import'!$A:$CZ,57,Settings!$C$20)&"","") | B57: =IFERROR(INDEX('Etsy Import'!$A:$CZ,57,Settings!$C$21)&"","") | C57: =IFERROR(INDEX('Etsy Import'!$A:$CZ,57,Settings!$C$22)&"","") | D57: =IF(A57="","",IFERROR(VALUE(SUBSTITUTE(SUBSTITUTE(INDEX('Etsy Import'!$A:$CZ,57,Settings!$C$23)&"","$",""),",","")),0)) | E57: =IF(A57="","",IFERROR(VALUE(SUBSTITUTE(SUBSTITUTE(INDEX('Etsy Import'!$A:$CZ,57,Settings!$C$24)&"","$",""),",","")),0)) | F57: =IF(A57="","",D57*E57) | G57: =IF(A57="","",IF(C57="",1,COUNTIF($C$2:$C$1501,C57))) | H57: =IF(A57="","",IFERROR(VALUE(SUBSTITUTE(SUBSTITUTE(INDEX('Etsy Import'!$A:$CZ,57,Settings!$C$25)&"","$",""),",","")),0)/IF(Settings!$B$27="Yes",G57,1)) | I57: =IF(A57="","",IFERROR(VALUE(SUBSTITUTE(SUBSTITUTE(INDEX('Etsy Import'!$A:$CZ,57,Settings!$C$26)&"","$",""),",","")),0)/IF(Settings!$B$27="Yes",G57,1)) | J57: =IF(A57="","",F57+H57-I57) | K57: =IF(A57="","",IFERROR(IF(B57="",NA(),MATCH(B57,Products!$B$5:$B$204,0)),IFERROR(MATCH(A57,Products!$A$5:$A$204,0),""))) | L57: =IF(A57="","",IF(K57="","⚠ not in Products",INDEX(Products!$A$5:$A$204,K57))) | M57: =IF(A57="","",J57*(IFERROR(INDEX(Settings!$B$5:$B$9,MATCH("Etsy",Settings!$A$5:$A$9,0)),0)+IFERROR(INDEX(Settings!$E$5:$E$9,MATCH("Etsy",Settings!$A$5:$A$9,0)),0)+IFERROR(INDEX(Settings!$G$5:$G$9,MATCH("Etsy",Settings!$A$5:$A$9,0)),0))+(IFERROR(INDEX(Settings!$C$5:$C$9,MATCH("Etsy",Settings!$A$5:$A$9,0)),0)+IFERROR(INDEX(Settings!$F$5:$F$9,MATCH("Etsy",Settings!$A$5:$A$9,0)),0))/G57+IFERROR(INDEX(Settings!$D$5:$D$9,MATCH("Etsy",Settings!$A$5:$A$9,0)),0)*D57) | N57: =IF(A57="","",IF(K57="",0,D57*INDEX(Products!$I$5:$I$204,K57))) | O57: =IF(A57="","",IF(K57="",0,J57*INDEX(Products!$H$5:$H$204,K57))) | P57: =IF(A57="","",J57-M57-N57-O57)
A58: =IFERROR(INDEX('Etsy Import'!$A:$CZ,58,Settings!$C$20)&"","") | B58: =IFERROR(INDEX('Etsy Import'!$A:$CZ,58,Settings!$C$21)&"","") | C58: =IFERROR(INDEX('Etsy Import'!$A:$CZ,58,Settings!$C$22)&"","") | D58: =IF(A58="","",IFERROR(VALUE(SUBSTITUTE(SUBSTITUTE(INDEX('Etsy Import'!$A:$CZ,58,Settings!$C$23)&"","$",""),",","")),0)) | E58: =IF(A58="","",IFERROR(VALUE(SUBSTITUTE(SUBSTITUTE(INDEX('Etsy Import'!$A:$CZ,58,Settings!$C$24)&"","$",""),",","")),0)) | F58: =IF(A58="","",D58*E58) | G58: =IF(A58="","",IF(C58="",1,COUNTIF($C$2:$C$1501,C58))) | H58: =IF(A58="","",IFERROR(VALUE(SUBSTITUTE(SUBSTITUTE(INDEX('Etsy Import'!$A:$CZ,58,Settings!$C$25)&"","$",""),",","")),0)/IF(Settings!$B$27="Yes",G58,1)) | I58: =IF(A58="","",IFERROR(VALUE(SUBSTITUTE(SUBSTITUTE(INDEX('Etsy Import'!$A:$CZ,58,Settings!$C$26)&"","$",""),",","")),0)/IF(Settings!$B$27="Yes",G58,1)) | J58: =IF(A58="","",F58+H58-I58) | K58: =IF(A58="","",IFERROR(IF(B58="",NA(),MATCH(B58,Products!$B$5:$B$204,0)),IFERROR(MATCH(A58,Products!$A$5:$A$204,0),""))) | L58: =IF(A58="","",IF(K58="","⚠ not in Products",INDEX(Products!$A$5:$A$204,K58))) | M58: =IF(A58="","",J58*(IFERROR(INDEX(Settings!$B$5:$B$9,MATCH("Etsy",Settings!$A$5:$A$9,0)),0)+IFERROR(INDEX(Settings!$E$5:$E$9,MATCH("Etsy",Settings!$A$5:$A$9,0)),0)+IFERROR(INDEX(Settings!$G$5:$G$9,MATCH("Etsy",Settings!$A$5:$A$9,0)),0))+(IFERROR(INDEX(Settings!$C$5:$C$9,MATCH("Etsy",Settings!$A$5:$A$9,0)),0)+IFERROR(INDEX(Settings!$F$5:$F$9,MATCH("Etsy",Settings!$A$5:$A$9,0)),0))/G58+IFERROR(INDEX(Settings!$D$5:$D$9,MATCH("Etsy",Settings!$A$5:$A$9,0)),0)*D58) | N58: =IF(A58="","",IF(K58="",0,D58*INDEX(Products!$I$5:$I$204,K58))) | O58: =IF(A58="","",IF(K58="",0,J58*INDEX(Products!$H$5:$H$204,K58))) | P58: =IF(A58="","",J58-M58-N58-O58)
A59: =IFERROR(INDEX('Etsy Import'!$A:$CZ,59,Settings!$C$20)&"","") | B59: =IFERROR(INDEX('Etsy Import'!$A:$CZ,59,Settings!$C$21)&"","") | C59: =IFERROR(INDEX('Etsy Import'!$A:$CZ,59,Settings!$C$22)&"","") | D59: =IF(A59="","",IFERROR(VALUE(SUBSTITUTE(SUBSTITUTE(INDEX('Etsy Import'!$A:$CZ,59,Settings!$C$23)&"","$",""),",","")),0)) | E59: =IF(A59="","",IFERROR(VALUE(SUBSTITUTE(SUBSTITUTE(INDEX('Etsy Import'!$A:$CZ,59,Settings!$C$24)&"","$",""),",","")),0)) | F59: =IF(A59="","",D59*E59) | G59: =IF(A59="","",IF(C59="",1,COUNTIF($C$2:$C$1501,C59))) | H59: =IF(A59="","",IFERROR(VALUE(SUBSTITUTE(SUBSTITUTE(INDEX('Etsy Import'!$A:$CZ,59,Settings!$C$25)&"","$",""),",","")),0)/IF(Settings!$B$27="Yes",G59,1)) | I59: =IF(A59="","",IFERROR(VALUE(SUBSTITUTE(SUBSTITUTE(INDEX('Etsy Import'!$A:$CZ,59,Settings!$C$26)&"","$",""),",","")),0)/IF(Settings!$B$27="Yes",G59,1)) | J59: =IF(A59="","",F59+H59-I59) | K59: =IF(A59="","",IFERROR(IF(B59="",NA(),MATCH(B59,Products!$B$5:$B$204,0)),IFERROR(MATCH(A59,Products!$A$5:$A$204,0),""))) | L59: =IF(A59="","",IF(K59="","⚠ not in Products",INDEX(Products!$A$5:$A$204,K59))) | M59: =IF(A59="","",J59*(IFERROR(INDEX(Settings!$B$5:$B$9,MATCH("Etsy",Settings!$A$5:$A$9,0)),0)+IFERROR(INDEX(Settings!$E$5:$E$9,MATCH("Etsy",Settings!$A$5:$A$9,0)),0)+IFERROR(INDEX(Settings!$G$5:$G$9,MATCH("Etsy",Settings!$A$5:$A$9,0)),0))+(IFERROR(INDEX(Settings!$C$5:$C$9,MATCH("Etsy",Settings!$A$5:$A$9,0)),0)+IFERROR(INDEX(Settings!$F$5:$F$9,MATCH("Etsy",Settings!$A$5:$A$9,0)),0))/G59+IFERROR(INDEX(Settings!$D$5:$D$9,MATCH("Etsy",Settings!$A$5:$A$9,0)),0)*D59) | N59: =IF(A59="","",IF(K59="",0,D59*INDEX(Products!$I$5:$I$204,K59))) | O59: =IF(A59="","",IF(K59="",0,J59*INDEX(Products!$H$5:$H$204,K59))) | P59: =IF(A59="","",J59-M59-N59-O59)
A60: =IFERROR(INDEX('Etsy Import'!$A:$CZ,60,Settings!$C$20)&"","") | B60: =IFERROR(INDEX('Etsy Import'!$A:$CZ,60,Settings!$C$21)&"","") | C60: =IFERROR(INDEX('Etsy Import'!$A:$CZ,60,Settings!$C$22)&"","") | D60: =IF(A60="","",IFERROR(VALUE(SUBSTITUTE(SUBSTITUTE(INDEX('Etsy Import'!$A:$CZ,60,Settings!$C$23)&"","$",""),",","")),0)) | E60: =IF(A60="","",IFERROR(VALUE(SUBSTITUTE(SUBSTITUTE(INDEX('Etsy Import'!$A:$CZ,60,Settings!$C$24)&"","$",""),",","")),0)) | F60: =IF(A60="","",D60*E60) | G60: =IF(A60="","",IF(C60="",1,COUNTIF($C$2:$C$1501,C60))) | H60: =IF(A60="","",IFERROR(VALUE(SUBSTITUTE(SUBSTITUTE(INDEX('Etsy Import'!$A:$CZ,60,Settings!$C$25)&"","$",""),",","")),0)/IF(Settings!$B$27="Yes",G60,1)) | I60: =IF(A60="","",IFERROR(VALUE(SUBSTITUTE(SUBSTITUTE(INDEX('Etsy Import'!$A:$CZ,60,Settings!$C$26)&"","$",""),",","")),0)/IF(Settings!$B$27="Yes",G60,1)) | J60: =IF(A60="","",F60+H60-I60) | K60: =IF(A60="","",IFERROR(IF(B60="",NA(),MATCH(B60,Products!$B$5:$B$204,0)),IFERROR(MATCH(A60,Products!$A$5:$A$204,0),""))) | L60: =IF(A60="","",IF(K60="","⚠ not in Products",INDEX(Products!$A$5:$A$204,K60))) | M60: =IF(A60="","",J60*(IFERROR(INDEX(Settings!$B$5:$B$9,MATCH("Etsy",Settings!$A$5:$A$9,0)),0)+IFERROR(INDEX(Settings!$E$5:$E$9,MATCH("Etsy",Settings!$A$5:$A$9,0)),0)+IFERROR(INDEX(Settings!$G$5:$G$9,MATCH("Etsy",Settings!$A$5:$A$9,0)),0))+(IFERROR(INDEX(Settings!$C$5:$C$9,MATCH("Etsy",Settings!$A$5:$A$9,0)),0)+IFERROR(INDEX(Settings!$F$5:$F$9,MATCH("Etsy",Settings!$A$5:$A$9,0)),0))/G60+IFERROR(INDEX(Settings!$D$5:$D$9,MATCH("Etsy",Settings!$A$5:$A$9,0)),0)*D60) | N60: =IF(A60="","",IF(K60="",0,D60*INDEX(Products!$I$5:$I$204,K60))) | O60: =IF(A60="","",IF(K60="",0,J60*INDEX(Products!$H$5:$H$204,K60))) | P60: =IF(A60="","",J60-M60-N60-O60)
A61: =IFERROR(INDEX('Etsy Import'!$A:$CZ,61,Settings!$C$20)&"","") | B61: =IFERROR(INDEX('Etsy Import'!$A:$CZ,61,Settings!$C$21)&"","") | C61: =IFERROR(INDEX('Etsy Import'!$A:$CZ,61,Settings!$C$22)&"","") | D61: =IF(A61="","",IFERROR(VALUE(SUBSTITUTE(SUBSTITUTE(INDEX('Etsy Import'!$A:$CZ,61,Settings!$C$23)&"","$",""),",","")),0)) | E61: =IF(A61="","",IFERROR(VALUE(SUBSTITUTE(SUBSTITUTE(INDEX('Etsy Import'!$A:$CZ,61,Settings!$C$24)&"","$",""),",","")),0)) | F61: =IF(A61="","",D61*E61) | G61: =IF(A61="","",IF(C61="",1,COUNTIF($C$2:$C$1501,C61))) | H61: =IF(A61="","",IFERROR(VALUE(SUBSTITUTE(SUBSTITUTE(INDEX('Etsy Import'!$A:$CZ,61,Settings!$C$25)&"","$",""),",","")),0)/IF(Settings!$B$27="Yes",G61,1)) | I61: =IF(A61="","",IFERROR(VALUE(SUBSTITUTE(SUBSTITUTE(INDEX('Etsy Import'!$A:$CZ,61,Settings!$C$26)&"","$",""),",","")),0)/IF(Settings!$B$27="Yes",G61,1)) | J61: =IF(A61="","",F61+H61-I61) | K61: =IF(A61="","",IFERROR(IF(B61="",NA(),MATCH(B61,Products!$B$5:$B$204,0)),IFERROR(MATCH(A61,Products!$A$5:$A$204,0),""))) | L61: =IF(A61="","",IF(K61="","⚠ not in Products",INDEX(Products!$A$5:$A$204,K61))) | M61: =IF(A61="","",J61*(IFERROR(INDEX(Settings!$B$5:$B$9,MATCH("Etsy",Settings!$A$5:$A$9,0)),0)+IFERROR(INDEX(Settings!$E$5:$E$9,MATCH("Etsy",Settings!$A$5:$A$9,0)),0)+IFERROR(INDEX(Settings!$G$5:$G$9,MATCH("Etsy",Settings!$A$5:$A$9,0)),0))+(IFERROR(INDEX(Settings!$C$5:$C$9,MATCH("Etsy",Settings!$A$5:$A$9,0)),0)+IFERROR(INDEX(Settings!$F$5:$F$9,MATCH("Etsy",Settings!$A$5:$A$9,0)),0))/G61+IFERROR(INDEX(Settings!$D$5:$D$9,MATCH("Etsy",Settings!$A$5:$A$9,0)),0)*D61) | N61: =IF(A61="","",IF(K61="",0,D61*INDEX(Products!$I$5:$I$204,K61))) | O61: =IF(A61="","",IF(K61="",0,J61*INDEX(Products!$H$5:$H$204,K61))) | P61: =IF(A61="","",J61-M61-N61-O61)
A62: =IFERROR(INDEX('Etsy Import'!$A:$CZ,62,Settings!$C$20)&"","") | B62: =IFERROR(INDEX('Etsy Import'!$A:$CZ,62,Settings!$C$21)&"","") | C62: =IFERROR(INDEX('Etsy Import'!$A:$CZ,62,Settings!$C$22)&"","") | D62: =IF(A62="","",IFERROR(VALUE(SUBSTITUTE(SUBSTITUTE(INDEX('Etsy Import'!$A:$CZ,62,Settings!$C$23)&"","$",""),",","")),0)) | E62: =IF(A62="","",IFERROR(VALUE(SUBSTITUTE(SUBSTITUTE(INDEX('Etsy Import'!$A:$CZ,62,Settings!$C$24)&"","$",""),",","")),0)) | F62: =IF(A62="","",D62*E62) | G62: =IF(A62="","",IF(C62="",1,COUNTIF($C$2:$C$1501,C62))) | H62: =IF(A62="","",IFERROR(VALUE(SUBSTITUTE(SUBSTITUTE(INDEX('Etsy Import'!$A:$CZ,62,Settings!$C$25)&"","$",""),",","")),0)/IF(Settings!$B$27="Yes",G62,1)) | I62: =IF(A62="","",IFERROR(VALUE(SUBSTITUTE(SUBSTITUTE(INDEX('Etsy Import'!$A:$CZ,62,Settings!$C$26)&"","$",""),",","")),0)/IF(Settings!$B$27="Yes",G62,1)) | J62: =IF(A62="","",F62+H62-I62) | K62: =IF(A62="","",IFERROR(IF(B62="",NA(),MATCH(B62,Products!$B$5:$B$204,0)),IFERROR(MATCH(A62,Products!$A$5:$A$204,0),""))) | L62: =IF(A62="","",IF(K62="","⚠ not in Products",INDEX(Products!$A$5:$A$204,K62))) | M62: =IF(A62="","",J62*(IFERROR(INDEX(Settings!$B$5:$B$9,MATCH("Etsy",Settings!$A$5:$A$9,0)),0)+IFERROR(INDEX(Settings!$E$5:$E$9,MATCH("Etsy",Settings!$A$5:$A$9,0)),0)+IFERROR(INDEX(Settings!$G$5:$G$9,MATCH("Etsy",Settings!$A$5:$A$9,0)),0))+(IFERROR(INDEX(Settings!$C$5:$C$9,MATCH("Etsy",Settings!$A$5:$A$9,0)),0)+IFERROR(INDEX(Settings!$F$5:$F$9,MATCH("Etsy",Settings!$A$5:$A$9,0)),0))/G62+IFERROR(INDEX(Settings!$D$5:$D$9,MATCH("Etsy",Settings!$A$5:$A$9,0)),0)*D62) | N62: =IF(A62="","",IF(K62="",0,D62*INDEX(Products!$I$5:$I$204,K62))) | O62: =IF(A62="","",IF(K62="",0,J62*INDEX(Products!$H$5:$H$204,K62))) | P62: =IF(A62="","",J62-M62-N62-O62)
A63: =IFERROR(INDEX('Etsy Import'!$A:$CZ,63,Settings!$C$20)&"","") | B63: =IFERROR(INDEX('Etsy Import'!$A:$CZ,63,Settings!$C$21)&"","") | C63: =IFERROR(INDEX('Etsy Import'!$A:$CZ,63,Settings!$C$22)&"","") | D63: =IF(A63="","",IFERROR(VALUE(SUBSTITUTE(SUBSTITUTE(INDEX('Etsy Import'!$A:$CZ,63,Settings!$C$23)&"","$",""),",","")),0)) | E63: =IF(A63="","",IFERROR(VALUE(SUBSTITUTE(SUBSTITUTE(INDEX('Etsy Import'!$A:$CZ,63,Settings!$C$24)&"","$",""),",","")),0)) | F63: =IF(A63="","",D63*E63) | G63: =IF(A63="","",IF(C63="",1,COUNTIF($C$2:$C$1501,C63))) | H63: =IF(A63="","",IFERROR(VALUE(SUBSTITUTE(SUBSTITUTE(INDEX('Etsy Import'!$A:$CZ,63,Settings!$C$25)&"","$",""),",","")),0)/IF(Settings!$B$27="Yes",G63,1)) | I63: =IF(A63="","",IFERROR(VALUE(SUBSTITUTE(SUBSTITUTE(INDEX('Etsy Import'!$A:$CZ,63,Settings!$C$26)&"","$",""),",","")),0)/IF(Settings!$B$27="Yes",G63,1)) | J63: =IF(A63="","",F63+H63-I63) | K63: =IF(A63="","",IFERROR(IF(B63="",NA(),MATCH(B63,Products!$B$5:$B$204,0)),IFERROR(MATCH(A63,Products!$A$5:$A$204,0),""))) | L63: =IF(A63="","",IF(K63="","⚠ not in Products",INDEX(Products!$A$5:$A$204,K63))) | M63: =IF(A63="","",J63*(IFERROR(INDEX(Settings!$B$5:$B$9,MATCH("Etsy",Settings!$A$5:$A$9,0)),0)+IFERROR(INDEX(Settings!$E$5:$E$9,MATCH("Etsy",Settings!$A$5:$A$9,0)),0)+IFERROR(INDEX(Settings!$G$5:$G$9,MATCH("Etsy",Settings!$A$5:$A$9,0)),0))+(IFERROR(INDEX(Settings!$C$5:$C$9,MATCH("Etsy",Settings!$A$5:$A$9,0)),0)+IFERROR(INDEX(Settings!$F$5:$F$9,MATCH("Etsy",Settings!$A$5:$A$9,0)),0))/G63+IFERROR(INDEX(Settings!$D$5:$D$9,MATCH("Etsy",Settings!$A$5:$A$9,0)),0)*D63) | N63: =IF(A63="","",IF(K63="",0,D63*INDEX(Products!$I$5:$I$204,K63))) | O63: =IF(A63="","",IF(K63="",0,J63*INDEX(Products!$H$5:$H$204,K63))) | P63: =IF(A63="","",J63-M63-N63-O63)
A64: =IFERROR(INDEX('Etsy Import'!$A:$CZ,64,Settings!$C$20)&"","") | B64: =IFERROR(INDEX('Etsy Import'!$A:$CZ,64,Settings!$C$21)&"","") | C64: =IFERROR(INDEX('Etsy Import'!$A:$CZ,64,Settings!$C$22)&"","") | D64: =IF(A64="","",IFERROR(VALUE(SUBSTITUTE(SUBSTITUTE(INDEX('Etsy Import'!$A:$CZ,64,Settings!$C$23)&"","$",""),",","")),0)) | E64: =IF(A64="","",IFERROR(VALUE(SUBSTITUTE(SUBSTITUTE(INDEX('Etsy Import'!$A:$CZ,64,Settings!$C$24)&"","$",""),",","")),0)) | F64: =IF(A64="","",D64*E64) | G64: =IF(A64="","",IF(C64="",1,COUNTIF($C$2:$C$1501,C64))) | H64: =IF(A64="","",IFERROR(VALUE(SUBSTITUTE(SUBSTITUTE(INDEX('Etsy Import'!$A:$CZ,64,Settings!$C$25)&"","$",""),",","")),0)/IF(Settings!$B$27="Yes",G64,1)) | I64: =IF(A64="","",IFERROR(VALUE(SUBSTITUTE(SUBSTITUTE(INDEX('Etsy Import'!$A:$CZ,64,Settings!$C$26)&"","$",""),",","")),0)/IF(Settings!$B$27="Yes",G64,1)) | J64: =IF(A64="","",F64+H64-I64) | K64: =IF(A64="","",IFERROR(IF(B64="",NA(),MATCH(B64,Products!$B$5:$B$204,0)),IFERROR(MATCH(A64,Products!$A$5:$A$204,0),""))) | L64: =IF(A64="","",IF(K64="","⚠ not in Products",INDEX(Products!$A$5:$A$204,K64))) | M64: =IF(A64="","",J64*(IFERROR(INDEX(Settings!$B$5:$B$9,MATCH("Etsy",Settings!$A$5:$A$9,0)),0)+IFERROR(INDEX(Settings!$E$5:$E$9,MATCH("Etsy",Settings!$A$5:$A$9,0)),0)+IFERROR(INDEX(Settings!$G$5:$G$9,MATCH("Etsy",Settings!$A$5:$A$9,0)),0))+(IFERROR(INDEX(Settings!$C$5:$C$9,MATCH("Etsy",Settings!$A$5:$A$9,0)),0)+IFERROR(INDEX(Settings!$F$5:$F$9,MATCH("Etsy",Settings!$A$5:$A$9,0)),0))/G64+IFERROR(INDEX(Settings!$D$5:$D$9,MATCH("Etsy",Settings!$A$5:$A$9,0)),0)*D64) | N64: =IF(A64="","",IF(K64="",0,D64*INDEX(Products!$I$5:$I$204,K64))) | O64: =IF(A64="","",IF(K64="",0,J64*INDEX(Products!$H$5:$H$204,K64))) | P64: =IF(A64="","",J64-M64-N64-O64)
A65: =IFERROR(INDEX('Etsy Import'!$A:$CZ,65,Settings!$C$20)&"","") | B65: =IFERROR(INDEX('Etsy Import'!$A:$CZ,65,Settings!$C$21)&"","") | C65: =IFERROR(INDEX('Etsy Import'!$A:$CZ,65,Settings!$C$22)&"","") | D65: =IF(A65="","",IFERROR(VALUE(SUBSTITUTE(SUBSTITUTE(INDEX('Etsy Import'!$A:$CZ,65,Settings!$C$23)&"","$",""),",","")),0)) | E65: =IF(A65="","",IFERROR(VALUE(SUBSTITUTE(SUBSTITUTE(INDEX('Etsy Import'!$A:$CZ,65,Settings!$C$24)&"","$",""),",","")),0)) | F65: =IF(A65="","",D65*E65) | G65: =IF(A65="","",IF(C65="",1,COUNTIF($C$2:$C$1501,C65))) | H65: =IF(A65="","",IFERROR(VALUE(SUBSTITUTE(SUBSTITUTE(INDEX('Etsy Import'!$A:$CZ,65,Settings!$C$25)&"","$",""),",","")),0)/IF(Settings!$B$27="Yes",G65,1)) | I65: =IF(A65="","",IFERROR(VALUE(SUBSTITUTE(SUBSTITUTE(INDEX('Etsy Import'!$A:$CZ,65,Settings!$C$26)&"","$",""),",","")),0)/IF(Settings!$B$27="Yes",G65,1)) | J65: =IF(A65="","",F65+H65-I65) | K65: =IF(A65="","",IFERROR(IF(B65="",NA(),MATCH(B65,Products!$B$5:$B$204,0)),IFERROR(MATCH(A65,Products!$A$5:$A$204,0),""))) | L65: =IF(A65="","",IF(K65="","⚠ not in Products",INDEX(Products!$A$5:$A$204,K65))) | M65: =IF(A65="","",J65*(IFERROR(INDEX(Settings!$B$5:$B$9,MATCH("Etsy",Settings!$A$5:$A$9,0)),0)+IFERROR(INDEX(Settings!$E$5:$E$9,MATCH("Etsy",Settings!$A$5:$A$9,0)),0)+IFERROR(INDEX(Settings!$G$5:$G$9,MATCH("Etsy",Settings!$A$5:$A$9,0)),0))+(IFERROR(INDEX(Settings!$C$5:$C$9,MATCH("Etsy",Settings!$A$5:$A$9,0)),0)+IFERROR(INDEX(Settings!$F$5:$F$9,MATCH("Etsy",Settings!$A$5:$A$9,0)),0))/G65+IFERROR(INDEX(Settings!$D$5:$D$9,MATCH("Etsy",Settings!$A$5:$A$9,0)),0)*D65) | N65: =IF(A65="","",IF(K65="",0,D65*INDEX(Products!$I$5:$I$204,K65))) | O65: =IF(A65="","",IF(K65="",0,J65*INDEX(Products!$H$5:$H$204,K65))) | P65: =IF(A65="","",J65-M65-N65-O65)
A66: =IFERROR(INDEX('Etsy Import'!$A:$CZ,66,Settings!$C$20)&"","") | B66: =IFERROR(INDEX('Etsy Import'!$A:$CZ,66,Settings!$C$21)&"","") | C66: =IFERROR(INDEX('Etsy Import'!$A:$CZ,66,Settings!$C$22)&"","") | D66: =IF(A66="","",IFERROR(VALUE(SUBSTITUTE(SUBSTITUTE(INDEX('Etsy Import'!$A:$CZ,66,Settings!$C$23)&"","$",""),",","")),0)) | E66: =IF(A66="","",IFERROR(VALUE(SUBSTITUTE(SUBSTITUTE(INDEX('Etsy Import'!$A:$CZ,66,Settings!$C$24)&"","$",""),",","")),0)) | F66: =IF(A66="","",D66*E66) | G66: =IF(A66="","",IF(C66="",1,COUNTIF($C$2:$C$1501,C66))) | H66: =IF(A66="","",IFERROR(VALUE(SUBSTITUTE(SUBSTITUTE(INDEX('Etsy Import'!$A:$CZ,66,Settings!$C$25)&"","$",""),",","")),0)/IF(Settings!$B$27="Yes",G66,1)) | I66: =IF(A66="","",IFERROR(VALUE(SUBSTITUTE(SUBSTITUTE(INDEX('Etsy Import'!$A:$CZ,66,Settings!$C$26)&"","$",""),",","")),0)/IF(Settings!$B$27="Yes",G66,1)) | J66: =IF(A66="","",F66+H66-I66) | K66: =IF(A66="","",IFERROR(IF(B66="",NA(),MATCH(B66,Products!$B$5:$B$204,0)),IFERROR(MATCH(A66,Products!$A$5:$A$204,0),""))) | L66: =IF(A66="","",IF(K66="","⚠ not in Products",INDEX(Products!$A$5:$A$204,K66))) | M66: =IF(A66="","",J66*(IFERROR(INDEX(Settings!$B$5:$B$9,MATCH("Etsy",Settings!$A$5:$A$9,0)),0)+IFERROR(INDEX(Settings!$E$5:$E$9,MATCH("Etsy",Settings!$A$5:$A$9,0)),0)+IFERROR(INDEX(Settings!$G$5:$G$9,MATCH("Etsy",Settings!$A$5:$A$9,0)),0))+(IFERROR(INDEX(Settings!$C$5:$C$9,MATCH("Etsy",Settings!$A$5:$A$9,0)),0)+IFERROR(INDEX(Settings!$F$5:$F$9,MATCH("Etsy",Settings!$A$5:$A$9,0)),0))/G66+IFERROR(INDEX(Settings!$D$5:$D$9,MATCH("Etsy",Settings!$A$5:$A$9,0)),0)*D66) | N66: =IF(A66="","",IF(K66="",0,D66*INDEX(Products!$I$5:$I$204,K66))) | O66: =IF(A66="","",IF(K66="",0,J66*INDEX(Products!$H$5:$H$204,K66))) | P66: =IF(A66="","",J66-M66-N66-O66)
A67: =IFERROR(INDEX('Etsy Import'!$A:$CZ,67,Settings!$C$20)&"","") | B67: =IFERROR(INDEX('Etsy Import'!$A:$CZ,67,Settings!$C$21)&"","") | C67: =IFERROR(INDEX('Etsy Import'!$A:$CZ,67,Settings!$C$22)&"","") | D67: =IF(A67="","",IFERROR(VALUE(SUBSTITUTE(SUBSTITUTE(INDEX('Etsy Import'!$A:$CZ,67,Settings!$C$23)&"","$",""),",","")),0)) | E67: =IF(A67="","",IFERROR(VALUE(SUBSTITUTE(SUBSTITUTE(INDEX('Etsy Import'!$A:$CZ,67,Settings!$C$24)&"","$",""),",","")),0)) | F67: =IF(A67="","",D67*E67) | G67: =IF(A67="","",IF(C67="",1,COUNTIF($C$2:$C$1501,C67))) | H67: =IF(A67="","",IFERROR(VALUE(SUBSTITUTE(SUBSTITUTE(INDEX('Etsy Import'!$A:$CZ,67,Settings!$C$25)&"","$",""),",","")),0)/IF(Settings!$B$27="Yes",G67,1)) | I67: =IF(A67="","",IFERROR(VALUE(SUBSTITUTE(SUBSTITUTE(INDEX('Etsy Import'!$A:$CZ,67,Settings!$C$26)&"","$",""),",","")),0)/IF(Settings!$B$27="Yes",G67,1)) | J67: =IF(A67="","",F67+H67-I67) | K67: =IF(A67="","",IFERROR(IF(B67="",NA(),MATCH(B67,Products!$B$5:$B$204,0)),IFERROR(MATCH(A67,Products!$A$5:$A$204,0),""))) | L67: =IF(A67="","",IF(K67="","⚠ not in Products",INDEX(Products!$A$5:$A$204,K67))) | M67: =IF(A67="","",J67*(IFERROR(INDEX(Settings!$B$5:$B$9,MATCH("Etsy",Settings!$A$5:$A$9,0)),0)+IFERROR(INDEX(Settings!$E$5:$E$9,MATCH("Etsy",Settings!$A$5:$A$9,0)),0)+IFERROR(INDEX(Settings!$G$5:$G$9,MATCH("Etsy",Settings!$A$5:$A$9,0)),0))+(IFERROR(INDEX(Settings!$C$5:$C$9,MATCH("Etsy",Settings!$A$5:$A$9,0)),0)+IFERROR(INDEX(Settings!$F$5:$F$9,MATCH("Etsy",Settings!$A$5:$A$9,0)),0))/G67+IFERROR(INDEX(Settings!$D$5:$D$9,MATCH("Etsy",Settings!$A$5:$A$9,0)),0)*D67) | N67: =IF(A67="","",IF(K67="",0,D67*INDEX(Products!$I$5:$I$204,K67))) | O67: =IF(A67="","",IF(K67="",0,J67*INDEX(Products!$H$5:$H$204,K67))) | P67: =IF(A67="","",J67-M67-N67-O67)
A68: =IFERROR(INDEX('Etsy Import'!$A:$CZ,68,Settings!$C$20)&"","") | B68: =IFERROR(INDEX('Etsy Import'!$A:$CZ,68,Settings!$C$21)&"","") | C68: =IFERROR(INDEX('Etsy Import'!$A:$CZ,68,Settings!$C$22)&"","") | D68: =IF(A68="","",IFERROR(VALUE(SUBSTITUTE(SUBSTITUTE(INDEX('Etsy Import'!$A:$CZ,68,Settings!$C$23)&"","$",""),",","")),0)) | E68: =IF(A68="","",IFERROR(VALUE(SUBSTITUTE(SUBSTITUTE(INDEX('Etsy Import'!$A:$CZ,68,Settings!$C$24)&"","$",""),",","")),0)) | F68: =IF(A68="","",D68*E68) | G68: =IF(A68="","",IF(C68="",1,COUNTIF($C$2:$C$1501,C68))) | H68: =IF(A68="","",IFERROR(VALUE(SUBSTITUTE(SUBSTITUTE(INDEX('Etsy Import'!$A:$CZ,68,Settings!$C$25)&"","$",""),",","")),0)/IF(Settings!$B$27="Yes",G68,1)) | I68: =IF(A68="","",IFERROR(VALUE(SUBSTITUTE(SUBSTITUTE(INDEX('Etsy Import'!$A:$CZ,68,Settings!$C$26)&"","$",""),",","")),0)/IF(Settings!$B$27="Yes",G68,1)) | J68: =IF(A68="","",F68+H68-I68) | K68: =IF(A68="","",IFERROR(IF(B68="",NA(),MATCH(B68,Products!$B$5:$B$204,0)),IFERROR(MATCH(A68,Products!$A$5:$A$204,0),""))) | L68: =IF(A68="","",IF(K68="","⚠ not in Products",INDEX(Products!$A$5:$A$204,K68))) | M68: =IF(A68="","",J68*(IFERROR(INDEX(Settings!$B$5:$B$9,MATCH("Etsy",Settings!$A$5:$A$9,0)),0)+IFERROR(INDEX(Settings!$E$5:$E$9,MATCH("Etsy",Settings!$A$5:$A$9,0)),0)+IFERROR(INDEX(Settings!$G$5:$G$9,MATCH("Etsy",Settings!$A$5:$A$9,0)),0))+(IFERROR(INDEX(Settings!$C$5:$C$9,MATCH("Etsy",Settings!$A$5:$A$9,0)),0)+IFERROR(INDEX(Settings!$F$5:$F$9,MATCH("Etsy",Settings!$A$5:$A$9,0)),0))/G68+IFERROR(INDEX(Settings!$D$5:$D$9,MATCH("Etsy",Settings!$A$5:$A$9,0)),0)*D68) | N68: =IF(A68="","",IF(K68="",0,D68*INDEX(Products!$I$5:$I$204,K68))) | O68: =IF(A68="","",IF(K68="",0,J68*INDEX(Products!$H$5:$H$204,K68))) | P68: =IF(A68="","",J68-M68-N68-O68)
A69: =IFERROR(INDEX('Etsy Import'!$A:$CZ,69,Settings!$C$20)&"","") | B69: =IFERROR(INDEX('Etsy Import'!$A:$CZ,69,Settings!$C$21)&"","") | C69: =IFERROR(INDEX('Etsy Import'!$A:$CZ,69,Settings!$C$22)&"","") | D69: =IF(A69="","",IFERROR(VALUE(SUBSTITUTE(SUBSTITUTE(INDEX('Etsy Import'!$A:$CZ,69,Settings!$C$23)&"","$",""),",","")),0)) | E69: =IF(A69="","",IFERROR(VALUE(SUBSTITUTE(SUBSTITUTE(INDEX('Etsy Import'!$A:$CZ,69,Settings!$C$24)&"","$",""),",","")),0)) | F69: =IF(A69="","",D69*E69) | G69: =IF(A69="","",IF(C69="",1,COUNTIF($C$2:$C$1501,C69))) | H69: =IF(A69="","",IFERROR(VALUE(SUBSTITUTE(SUBSTITUTE(INDEX('Etsy Import'!$A:$CZ,69,Settings!$C$25)&"","$",""),",","")),0)/IF(Settings!$B$27="Yes",G69,1)) | I69: =IF(A69="","",IFERROR(VALUE(SUBSTITUTE(SUBSTITUTE(INDEX('Etsy Import'!$A:$CZ,69,Settings!$C$26)&"","$",""),",","")),0)/IF(Settings!$B$27="Yes",G69,1)) | J69: =IF(A69="","",F69+H69-I69) | K69: =IF(A69="","",IFERROR(IF(B69="",NA(),MATCH(B69,Products!$B$5:$B$204,0)),IFERROR(MATCH(A69,Products!$A$5:$A$204,0),""))) | L69: =IF(A69="","",IF(K69="","⚠ not in Products",INDEX(Products!$A$5:$A$204,K69))) | M69: =IF(A69="","",J69*(IFERROR(INDEX(Settings!$B$5:$B$9,MATCH("Etsy",Settings!$A$5:$A$9,0)),0)+IFERROR(INDEX(Settings!$E$5:$E$9,MATCH("Etsy",Settings!$A$5:$A$9,0)),0)+IFERROR(INDEX(Settings!$G$5:$G$9,MATCH("Etsy",Settings!$A$5:$A$9,0)),0))+(IFERROR(INDEX(Settings!$C$5:$C$9,MATCH("Etsy",Settings!$A$5:$A$9,0)),0)+IFERROR(INDEX(Settings!$F$5:$F$9,MATCH("Etsy",Settings!$A$5:$A$9,0)),0))/G69+IFERROR(INDEX(Settings!$D$5:$D$9,MATCH("Etsy",Settings!$A$5:$A$9,0)),0)*D69) | N69: =IF(A69="","",IF(K69="",0,D69*INDEX(Products!$I$5:$I$204,K69))) | O69: =IF(A69="","",IF(K69="",0,J69*INDEX(Products!$H$5:$H$204,K69))) | P69: =IF(A69="","",J69-M69-N69-O69)
A70: =IFERROR(INDEX('Etsy Import'!$A:$CZ,70,Settings!$C$20)&"","") | B70: =IFERROR(INDEX('Etsy Import'!$A:$CZ,70,Settings!$C$21)&"","") | C70: =IFERROR(INDEX('Etsy Import'!$A:$CZ,70,Settings!$C$22)&"","") | D70: =IF(A70="","",IFERROR(VALUE(SUBSTITUTE(SUBSTITUTE(INDEX('Etsy Import'!$A:$CZ,70,Settings!$C$23)&"","$",""),",","")),0)) | E70: =IF(A70="","",IFERROR(VALUE(SUBSTITUTE(SUBSTITUTE(INDEX('Etsy Import'!$A:$CZ,70,Settings!$C$24)&"","$",""),",","")),0)) | F70: =IF(A70="","",D70*E70) | G70: =IF(A70="","",IF(C70="",1,COUNTIF($C$2:$C$1501,C70))) | H70: =IF(A70="","",IFERROR(VALUE(SUBSTITUTE(SUBSTITUTE(INDEX('Etsy Import'!$A:$CZ,70,Settings!$C$25)&"","$",""),",","")),0)/IF(Settings!$B$27="Yes",G70,1)) | I70: =IF(A70="","",IFERROR(VALUE(SUBSTITUTE(SUBSTITUTE(INDEX('Etsy Import'!$A:$CZ,70,Settings!$C$26)&"","$",""),",","")),0)/IF(Settings!$B$27="Yes",G70,1)) | J70: =IF(A70="","",F70+H70-I70) | K70: =IF(A70="","",IFERROR(IF(B70="",NA(),MATCH(B70,Products!$B$5:$B$204,0)),IFERROR(MATCH(A70,Products!$A$5:$A$204,0),""))) | L70: =IF(A70="","",IF(K70="","⚠ not in Products",INDEX(Products!$A$5:$A$204,K70))) | M70: =IF(A70="","",J70*(IFERROR(INDEX(Settings!$B$5:$B$9,MATCH("Etsy",Settings!$A$5:$A$9,0)),0)+IFERROR(INDEX(Settings!$E$5:$E$9,MATCH("Etsy",Settings!$A$5:$A$9,0)),0)+IFERROR(INDEX(Settings!$G$5:$G$9,MATCH("Etsy",Settings!$A$5:$A$9,0)),0))+(IFERROR(INDEX(Settings!$C$5:$C$9,MATCH("Etsy",Settings!$A$5:$A$9,0)),0)+IFERROR(INDEX(Settings!$F$5:$F$9,MATCH("Etsy",Settings!$A$5:$A$9,0)),0))/G70+IFERROR(INDEX(Settings!$D$5:$D$9,MATCH("Etsy",Settings!$A$5:$A$9,0)),0)*D70) | N70: =IF(A70="","",IF(K70="",0,D70*INDEX(Products!$I$5:$I$204,K70))) | O70: =IF(A70="","",IF(K70="",0,J70*INDEX(Products!$H$5:$H$204,K70))) | P70: =IF(A70="","",J70-M70-N70-O70)
A71: =IFERROR(INDEX('Etsy Import'!$A:$CZ,71,Settings!$C$20)&"","") | B71: =IFERROR(INDEX('Etsy Import'!$A:$CZ,71,Settings!$C$21)&"","") | C71: =IFERROR(INDEX('Etsy Import'!$A:$CZ,71,Settings!$C$22)&"","") | D71: =IF(A71="","",IFERROR(VALUE(SUBSTITUTE(SUBSTITUTE(INDEX('Etsy Import'!$A:$CZ,71,Settings!$C$23)&"","$",""),",","")),0)) | E71: =IF(A71="","",IFERROR(VALUE(SUBSTITUTE(SUBSTITUTE(INDEX('Etsy Import'!$A:$CZ,71,Settings!$C$24)&"","$",""),",","")),0)) | F71: =IF(A71="","",D71*E71) | G71: =IF(A71="","",IF(C71="",1,COUNTIF($C$2:$C$1501,C71))) | H71: =IF(A71="","",IFERROR(VALUE(SUBSTITUTE(SUBSTITUTE(INDEX('Etsy Import'!$A:$CZ,71,Settings!$C$25)&"","$",""),",","")),0)/IF(Settings!$B$27="Yes",G71,1)) | I71: =IF(A71="","",IFERROR(VALUE(SUBSTITUTE(SUBSTITUTE(INDEX('Etsy Import'!$A:$CZ,71,Settings!$C$26)&"","$",""),",","")),0)/IF(Settings!$B$27="Yes",G71,1)) | J71: =IF(A71="","",F71+H71-I71) | K71: =IF(A71="","",IFERROR(IF(B71="",NA(),MATCH(B71,Products!$B$5:$B$204,0)),IFERROR(MATCH(A71,Products!$A$5:$A$204,0),""))) | L71: =IF(A71="","",IF(K71="","⚠ not in Products",INDEX(Products!$A$5:$A$204,K71))) | M71: =IF(A71="","",J71*(IFERROR(INDEX(Settings!$B$5:$B$9,MATCH("Etsy",Settings!$A$5:$A$9,0)),0)+IFERROR(INDEX(Settings!$E$5:$E$9,MATCH("Etsy",Settings!$A$5:$A$9,0)),0)+IFERROR(INDEX(Settings!$G$5:$G$9,MATCH("Etsy",Settings!$A$5:$A$9,0)),0))+(IFERROR(INDEX(Settings!$C$5:$C$9,MATCH("Etsy",Settings!$A$5:$A$9,0)),0)+IFERROR(INDEX(Settings!$F$5:$F$9,MATCH("Etsy",Settings!$A$5:$A$9,0)),0))/G71+IFERROR(INDEX(Settings!$D$5:$D$9,MATCH("Etsy",Settings!$A$5:$A$9,0)),0)*D71) | N71: =IF(A71="","",IF(K71="",0,D71*INDEX(Products!$I$5:$I$204,K71))) | O71: =IF(A71="","",IF(K71="",0,J71*INDEX(Products!$H$5:$H$204,K71))) | P71: =IF(A71="","",J71-M71-N71-O71)
